Workbook
Name ____________________a65537: #REF!
Name ____________________a65537: #REF!
Name ____________________A65555: #REF!
Name ____________________A65555: #REF!
Name ____________________A65658: #REF!
Name ____________________A65658: #REF!
Name ___________________a65537: #REF!
Name ___________________a65537: #REF!
Name ___________________A65555: #REF!
Name ___________________A65555: #REF!
Name ___________________A65658: #REF!
Name ___________________A65658: #REF!
Name __________________a65537: #REF!
Name __________________a65537: #REF!
Name __________________A65555: #REF!
Name __________________A65555: #REF!
Name __________________A65658: #REF!
Name __________________A65658: #REF!
Name __________________bol1: #REF!
Name __________________bol1: #REF!
Name __________________lb1: #REF!
Name __________________lb1: #REF!
Name __________________lb2: #REF!
Name __________________lb2: #REF!
Name __________________mm1: #REF!
Name __________________mm1: #REF!
Name __________________mm2: #REF!
Name __________________mm2: #REF!
Name __________________mm3: #REF!
Name __________________mm3: #REF!
Name _________________a65537: #REF!
Name _________________a65537: #REF!
Name _________________A65555: #REF!
Name _________________A65555: #REF!
Name _________________A65658: #REF!
Name _________________A65658: #REF!
Name _________________bol1: #REF!
Name _________________bol1: #REF!
Name _________________lb1: #REF!
Name _________________lb1: #REF!
Name _________________lb2: #REF!
Name _________________lb2: #REF!
Name _________________mm1: #REF!
Name _________________mm1: #REF!
Name _________________mm2: #REF!
Name _________________mm2: #REF!
Name _________________mm3: #REF!
Name _________________mm3: #REF!
Name ________________a65537: #REF!
Name ________________a65537: #REF!
Name ________________A65555: #REF!
Name ________________A65555: #REF!
Name ________________A65658: #REF!
Name ________________A65658: #REF!
Name ________________bol1: #REF!
Name ________________bol1: #REF!
Name ________________lb1: #REF!
Name ________________lb1: #REF!
Name ________________lb2: #REF!
Name ________________lb2: #REF!

Sheet Misk Format
A1: Mawallah Site BOQ
A2: SL.NO | B2: DESCRIPTION | C2: UNIT | D2: QUANTITY | E2: UNIT RATE | F2: AMOUNT | G2: VAT 5% | H2: TOTAL AMOUNT | I2: LPO/ CONTRACT | J2: ACTUAL | K2: BALANCE TO PAY | L2: REMARKS
B3: CIVIL WORKS
A4: A | B4: Structural Works
A5: 1 | B5: Survey & Tasleem Align Marking | C5: Ls | D5: 1 | E5: 20 | F5: =(D5*E5) -> 20 | H5: =SUM(F5+G5) -> 20
A6: 2 | B6: Sub Contractor for the structure works | C6: Ls | D6: 1 | E6: 40102 | F6: =(D6*E6) -> 40102 | H6: =SUM(F6+G6) -> 40102
A7: 3 | B7: Sub Contractor for the MEP works | C7: Sqm | D7: 2721.6 | E7: 3.8 | F7: =(D7*E7) -> 10342.08 | H7: =SUM(F7+G7) -> 10342.08
A8: 4 | B8: Measuring Tape 5m | C8: Nos | D8: 2 | E8: 0.8 | F8: =(D8*E8) -> 1.6 | G8: =(F8*5%) -> 0.08 | H8: =SUM(F8+G8) -> 1.68
A9: 5 | B9: Excavation Contract | C9: Ls | D9: 1 | E9: 1400 | F9: =(D9*E9) -> 1400 | H9: =SUM(F9+G9) -> 1400
A10: 6 | B10: Backfilling equipment contract | C10: Days | D10: 5 | E10: 60 | F10: =(D10*E10) -> 300 | H10: =SUM(F10+G10) -> 300
A11: 7 | B11: ATT | C11: Sqm | D11: 450 | E11: 0.265 | F11: =(D11*E11) -> 119.25 | G11: =(F11*5%) -> 5.9625 | H11: =SUM(F11+G11) -> 125.2125
A12: 8 | B12: Polythene sheet PCC Bottom + Grade slab Bottom + Concrete protection | C12: Roll | D12: 35 | E12: 5 | F12: =(D12*E12) -> 175 | G12: =(F12*5%) -> 8.75 | H12: =SUM(F12+G12) -> 183.75
A13: 9 | B13: PCC C15 | C13: m3 | D13: 48 | E13: 17 | F13: =(D13*E13) -> 816 | G13: =(F13*5%) -> 40.8 | H13: =SUM(F13+G13) -> 856.8
A14: 10 | B14: SRC - C40 | C14: m3 | D14: 544 | E14: 22 | F14: =(D14*E14) -> 11968 | G14: =(F14*5%) -> 598.4 | H14: =SUM(F14+G14) -> 12566.4
A15: 11 | B15: OPC -C40 | C15: m3 | D15: 1082 | E15: 22 | F15: =(D15*E15) -> 23804 | G15: =(F15*5%) -> 1190.2 | H15: =SUM(F15+G15) -> 24994.2
A16: 12 | B16: SRC-C30 for the grade slab | C16: m3 | D16: 42 | E16: 18 | F16: =(D16*E16) -> 756 | G16: =(F16*5%) -> 37.8 | H16: =SUM(F16+G16) -> 793.8
A17: 13 | B17: A-193- Mesh | C17: Nos | D17: 30 | E17: 6.6 | F17: =(D17*E17) -> 198 | G17: =(F17*5%) -> 9.9 | H17: =SUM(F17+G17) -> 207.9
A18: 14 | B18: Reinforcement | C18: Ton | D18: 226.5 | E18: 287 | F18: =+D18*E18 -> 65005.5 | G18: =(F18*5%) -> 3250.275 | H18: =SUM(F18+G18) -> 68255.775
A19: 15 | B19: Binding Wire | C19: KG | D19: 1200 | E19: 0.6 | F19: =(D19*E19) -> 720 | G19: =(F19*5%) -> 36 | H19: =SUM(F19+G19) -> 756
A20: 16 | B20: Site Set up | C20: Ls | D20: 1 | E20: 1500 | F20: =(D20*E20) -> 1500 | H20: =SUM(F20+G20) -> 1500
A21: 17 | B21: Cement for the substructure works | C21: Bag | D21: 50 | E21: 1.53 | F21: =(D21*E21) -> 76.5 | G21: =(F21*5%) -> 3.825 | H21: =SUM(F21+G21) -> 80.325
A22: 18 | B22: Wash Sand | C22: Trip | D22: 1 | E22: 70 | F22: =(D22*E22) -> 70 | G22: =(F22*5%) -> 3.5 | H22: =SUM(F22+G22) -> 73.5
A23: 19 | B23: Bitumen Paint | C23: Drum | D23: 4 | E23: 45 | F23: =(D23*E23) -> 180 | G23: =(F23*5%) -> 9 | H23: =SUM(F23+G23) -> 189
A25: B | B25: Shuttering Materials | H25: =SUM(F25+G25) -> 0
A26: 1 | B26: Plywood 18mm | C26: Nos | D26: 350 | E26: 6 | F26: =(D26*E26) -> 2100 | G26: =(F26*5%) -> 105 | H26: =SUM(F26+G26) -> 2205
A27: 2 | B27: White Wood 1"4" | C27: Nos | D27: 180 | E27: 1.45 | F27: =(D27*E27) -> 261 | G27: =(F27*5%) -> 13.05 | H27: =SUM(F27+G27) -> 274.05
A28: 3 | B28: White Wood 2"*3" | C28: Nos | D28: 1350 | E28: 1.7 | F28: =(D28*E28) -> 2295 | G28: =(F28*5%) -> 114.75 | H28: =SUM(F28+G28) -> 2409.75
A29: 5 | B29: Doka System for the scaffolding | C29: Month | D29: 8 | E29: 750 | F29: =(D29*E29) -> 6000 | G29: =(F29*5%) -> 300 | H29: =SUM(F29+G29) -> 6300
A30: 6 | B30: Nail | C30: Ls | D30: 1 | E30: 800 | F30: =(D30*E30) -> 800 | G30: =(F30*5%) -> 40 | H30: =SUM(F30+G30) -> 840
A31: 7 | B31: Shuttering Tape | C31: Qtn | D31: 25 | E31: 3 | F31: =(D31*E31) -> 75 | G31: =(F31*5%) -> 3.75 | H31: =SUM(F31+G31) -> 78.75
A32: 8 | B32: C-Clamp | C32: Nos | D32: 300 | E32: 0.7 | F32: =(D32*E32) -> 210 | G32: =(F32*5%) -> 10.5 | H32: =SUM(F32+G32) -> 220.5
A33: 9 | B33: Tie Rod | C33: Ls | D33: 800 | E33: 1 | F33: =(D33*E33) -> 800 | G33: =(F33*5%) -> 40 | H33: =SUM(F33+G33) -> 840
A34: 10 | B34: 25mm Conduit Pipe | C34: Nos | D34: 350 | E34: 0.4 | F34: =(D34*E34) -> 140 | G34: =(F34*5%) -> 7 | H34: =SUM(F34+G34) -> 147
A36: C | B36: Block Works
A37: 1 | B37: 100 mm thick Bottom Closed Blockes | C37: Nos | D37: 10000 | E37: 0.15 | F37: =(D37*E37) -> 1500 | G37: =(F37*5%) -> 75 | H37: =SUM(F37+G37) -> 1575
A38: 2 | B38: 200mm thick bottom Closed Blocks | C38: Nos | D38: 63000 | E38: 0.16 | F38: =(D38*E38) -> 10080 | G38: =(F38*5%) -> 504 | H38: =SUM(F38+G38) -> 10584
A39: 3 | B39: Tower Hoist Diesl engine lift | C39: Nos | D39: 1 | E39: 2750 | F39: =(D39*E39) -> 2750 | G39: =(F39*5%) -> 137.5 | H39: =SUM(F39+G39) -> 2887.5
A40: 4 | B40: Hoist Installation | C40: ls | D40: 1 | E40: 200 | F40: =(D40*E40) -> 200 | H40: =SUM(F40+G40) -> 200
A41: 5 | B41: Cement for Block work | C41: Bag | D41: 1500 | E41: 1.37 | F41: =(D41*E41) -> 2055 | G41: =(F41*5%) -> 102.75 | H41: =SUM(F41+G41) -> 2157.75
A42: 6 | B42: Aggregate | C42: Trip | D42: 3 | E42: 50 | F42: =(D42*E42) -> 150 | G42: =(F42*5%) -> 7.5 | H42: =SUM(F42+G42) -> 157.5
A43: 7 | B43: Water Hose | C43: Roll | D43: 2 | E43: 5.6 | F43: =(D43*E43) -> 11.2 | G43: =(F43*5%) -> 0.56 | H43: =SUM(F43+G43) -> 11.76
A44: 8 | B44: Diesel for lift | C44: Ls | D44: 1 | E44: 300 | F44: =(D44*E44) -> 300 | G44: =(F44*5%) -> 15 | H44: =SUM(F44+G44) -> 315
A45: 9 | B45: Wash Sand | C45: Trip | D45: 20 | E45: 70 | F45: =(D45*E45) -> 1400 | G45: =(F45*5%) -> 70 | H45: =SUM(F45+G45) -> 1470
A46: 10 | B46: Block for 2 floor shifting | C46: Trip | D46: 20 | E46: 25 | F46: =(D46*E46) -> 500 | G46: =(F46*5%) -> 25 | H46: =SUM(F46+G46) -> 525
A48: D | B48: Plaster
A49: 1 | B49: Plaster Internal Labour Contract | C49: Sqm | D49: 9710 | E49: 0.9 | F49: =(D49*E49) -> 8739 | H49: =SUM(F49+G49) -> 8739
A50: 2 | B50: Plaster External Labour Contract | C50: Sqm | D50: 1300 | E50: 1.6 | F50: =(D50*E50) -> 2080 | H50: =SUM(F50+G50) -> 2080
A51: 3 | B51: Plaster sand for Internal & External | C51: Trip | D51: 20 | E51: 110 | F51: =(D51*E51) -> 2200 | H51: =SUM(F51+G51) -> 2200
A52: 4 | B52: Cement for the Plaster | C52: Bag | D52: 1500 | E52: 1.37 | F52: =(D52*E52) -> 2055 | H52: =SUM(F52+G52) -> 2055
A53: 5 | B53: Plaster Mesh | C53: Ls | D53: 70 | E53: 1 | F53: =(D53*E53) -> 70 | H53: =SUM(F53+G53) -> 70
A54: 6 | B54: Corner Beeding Internal | C54: Nos | D54: 500 | E54: 0.8 | F54: =(D54*E54) -> 400 | G54: =(F54*5%) -> 20 | H54: =SUM(F54+G54) -> 420
A55: 7 | B55: Corner Beeding for External | C55: Nos | D55: 500 | E55: 1.2 | F55: =(D55*E55) -> 600 | G55: =(F55*5%) -> 30 | H55: =SUM(F55+G55) -> 630
A56: 8 | B56: Water Hose | C56: Roll | D56: 1 | E56: 5.6 | F56: =(D56*E56) -> 5.6 | G56: =(F56*5%) -> 0.28 | H56: =SUM(F56+G56) -> 5.88
A57: 9 | B57: External Scaffolding | C57: Ls | D57: 1 | E57: 4000 | F57: =(D57*E57) -> 4000 | H57: =SUM(F57+G57) -> 4000
A59: E | B59: Tiles
B60: Materials Charge
A61: 1 | B61: 60*60 CM Porcelain Floor Tiles | C61: Sqm | D61: 1650 | E61: 2 | F61: =(D61*E61) -> 3300 | G61: =(F61*5%) -> 165 | H61: =SUM(F61+G61) -> 3465
A62: 2 | B62: 60*120 CM Porcelain Floor Tiles | C62: Sqm | D62: 180 | E62: 2.8 | F62: =(D62*E62) -> 504 | G62: =(F62*5%) -> 25.2 | H62: =SUM(F62+G62) -> 529.2
A63: 3 | B63: 30*60 CM Ceramic Wall Tiles Toilet | C63: Sqm | D63: 1500 | E63: 1.8 | F63: =(D63*E63) -> 2700 | G63: =(F63*5%) -> 135 | H63: =SUM(F63+G63) -> 2835
A64: 4 | B64: Ceramic Wall Tiles Kitchen | C64: Sqm | D64: 70 | E64: 1.8 | F64: =(D64*E64) -> 126 | G64: =(F64*5%) -> 6.3 | H64: =SUM(F64+G64) -> 132.3
A65: 5 | B65: 30*30 CM Ceramic Floor Tile | C65: Sqm | D65: 450 | E65: 1.8 | F65: =(D65*E65) -> 810 | G65: =(F65*5%) -> 40.5 | H65: =SUM(F65+G65) -> 850.5
A66: 6 | B66: 60*10 CM Skirting | C66: RM | D66: 1700 | E66: 0.3 | F66: =(D66*E66) -> 510 | G66: =(F66*5%) -> 25.5 | H66: =SUM(F66+G66) -> 535.5
A67: 7 | B67: 120*10 CM Skirting (Included above) | C67: RM | D67: 200 | E67: 0.3 | F67: =(D67*E67) -> 60 | G67: =(F67*5%) -> 3 | H67: =SUM(F67+G67) -> 63
A68: 8 | B68: Tile Adhessive | C68: Bag | D68: 1680 | E68: 1.2 | F68: =(D68*E68) -> 2016 | G68: =(F68*5%) -> 100.8 | H68: =SUM(F68+G68) -> 2116.8
A69: 9 | B69: Wash Sand | C69: Trip | D69: 18 | E69: 60 | F69: =(D69*E69) -> 1080 | H69: =SUM(F69+G69) -> 1080
A70: 10 | B70: Cement | C70: Bag | D70: 1200 | E70: 1.37 | F70: =(D70*E70) -> 1644 | H70: =SUM(F70+G70) -> 1644
A71: 11 | B71: Tile Grout | C71: Bag | D71: 25 | E71: 1.2 | F71: =(D71*E71) -> 30 | H71: =SUM(F71+G71) -> 30
A72: 12 | B72: Marble steps | C72: RM | D72: 180 | E72: 5 | F72: =(D72*E72) -> 900 | H72: =SUM(F72+G72) -> 900
A73: 13 | B73: White Cement | C73: Bag | D73: 100 | E73: 2.4 | F73: =(D73*E73) -> 240 | H73: =SUM(F73+G73) -> 240
A74: 14 | B74: Tile Spacer | C74: PKT | D74: 300 | E74: 0.3 | F74: =(D74*E74) -> 90 | H74: =SUM(F74+G74) -> 90
A75: 15 | B75: Tile Protection Board | C75: Sqm | D75: 1500 | E75: 0.5 | F75: =(D75*E75) -> 750 | H75: =SUM(F75+G75) -> 750
B76: Labour Charge
A77: 16 | B77: 60*60 CM Porcelain Floor Tiles | C77: Sqm | D77: 1650 | E77: 1.5 | F77: =(D77*E77) -> 2475 | H77: =SUM(F77+G77) -> 2475
A78: 17 | B78: 60*120 CM Porcelain Floor Tiles | C78: Sqm | D78: 180 | E78: 1.6 | F78: =(D78*E78) -> 288 | H78: =SUM(F78+G78) -> 288
A79: 18 | B79: 30*60 CM Ceramic Wall Tiles | C79: Sqm | D79: 1500 | E79: 2 | F79: =(D79*E79) -> 3000 | H79: =SUM(F79+G79) -> 3000
A80: 19 | B80: 30*30 CM Ceramic Floor Tile | C80: Sqm | D80: 450 | E80: 2 | F80: =(D80*E80) -> 900 | H80: =SUM(F80+G80) -> 900
A81: 20 | B81: 60*10 CM Skirting | C81: RM | D81: 1900 | E81: 0.6 | F81: =(D81*E81) -> 1140 | H81: =SUM(F81+G81) -> 1140
A82: 22 | B82: Marble steps/Granite steps | C82: RM | D82: 180 | E82: 5 | F82: =(D82*E82) -> 900 | H82: =SUM(F82+G82) -> 900
A83: 23 | B83: Labour charge for the marble | C83: RM | D83: 180 | E83: 2 | F83: =(D83*E83) -> 360 | H83: =SUM(F83+G83) -> 360
A85: F | B85: Paint
A86: 1 | B86: Painting works internal & External Labour Charge | C86: Sqm | D86: 2721 | E86: 1.8 | F86: =(D86*E86) -> 4897.8 | H86: =SUM(F86+G86) -> 4897.8
A87: 2 | B87: Materials Charge for the Paint | C87: Sqm | D87: 2721 | E87: 1.35 | F87: =(D87*E87) -> 3673.35 | H87: =SUM(F87+G87) -> 3673.35
A88: 3 | B88: Gypsum | C88: Bag | D88: 70 | E88: 1.25 | F88: =(D88*E88) -> 87.5 | H88: =SUM(F88+G88) -> 87.5
A89: 4 | B89: White Cement | C89: Bag | D89: 50 | E89: 2.47 | F89: =(D89*E89) -> 123.5 | H89: =SUM(F89+G89) -> 123.5
A90: 5 | B90: Masking tape | C90: Ctn | D90: 50 | E90: 2.5 | F90: =(D90*E90) -> 125 | H90: =SUM(F90+G90) -> 125
A91: 6 | B91: Sand Paper | C91: Pkt | D91: 8 | E91: 2.2 | F91: =(D91*E91) -> 17.6 | H91: =SUM(F91+G91) -> 17.6
A92: 7 | B92: Epoxy Paint in steps | C92: ls | D92: 1 | E92: 600 | F92: =(D92*E92) -> 600 | H92: =SUM(F92+G92) -> 600
A94: G | B94: Carpentry Works
A95: 1 | B95: D5 - 1000 X 2200 | C95: Nos | D95: 37 | E95: 80 | F95: =(D95*E95) -> 2960 | H95: =SUM(F95+G95) -> 2960
A96: 2 | B96: D6 - 800 X 2200 | C96: Nos | D96: 22 | E96: 73 | F96: =(D96*E96) -> 1606 | H96: =SUM(F96+G96) -> 1606
A97: 3 | B97: D7 - 1000 X 2200 | C97: Nos | D97: 1 | E97: 80 | F97: =(D97*E97) -> 80 | H97: =SUM(F97+G97) -> 80
A98: 4 | B98: D8 - 1100 X 2200 - Fire Door - 60 Minute | C98: Nos | D98: 35 | E98: 108 | F98: =(D98*E98) -> 3780 | H98: =SUM(F98+G98) -> 3780
A99: 5 | B99: D9 - 900 X 2200 | C99: Nos | D99: 50 | E99: 78 | F99: =(D99*E99) -> 3900 | H99: =SUM(F99+G99) -> 3900
A100: 6 | B100: D4 - 1200 X 2200 | C100: Nos | D100: 4 | E100: 90 | F100: =(D100*E100) -> 360 | H100: =SUM(F100+G100) -> 360
A101: 7 | B101: D3 - 1000* 2200 - Fire Door - 90 Minute | C101: Nos | D101: 11 | E101: 148 | F101: =(D101*E101) -> 1628 | H101: =SUM(F101+G101) -> 1628
A103: H | B103: Roofing Works
A104: 1 | B104: Light weight Concrete | C104: m3 | D104: 32 | E104: 22 | F104: =(D104*E104) -> 704 | G104: =(F104*5%) -> 35.2 | H104: =SUM(F104+G104) -> 739.2
A105: 2 | B105: Waterproofing memberane 4mm Thick | C105: m2 | D105: 500 | E105: 1.65 | F105: =(D105*E105) -> 825 | G105: =(F105*5%) -> 41.25 | H105: =SUM(F105+G105) -> 866.25
A106: 3 | B106: Polythene sheet laying | C106: Roll | D106: 6 | E106: 5.6 | F106: =(D106*E106) -> 33.6 | G106: =(F106*5%) -> 1.68 | H106: =SUM(F106+G106) -> 35.28
A107: 4 | B107: Tiles 30*30*3cm | C107: sqm | D107: 430 | E107: 2 | F107: =(D107*E107) -> 860 | G107: =(F107*5%) -> 43 | H107: =SUM(F107+G107) -> 903
...

Sheet GS
A1: CONSTRUCTION OF RESIDENTAL/COMMERCIAL BUILDING @ Alansab Plot 1127
A4: GENERAL SUMMARY
A8: ITEM | B8: ITEM DESCRIPTION | E8: AMOUNT
A9: REF. | E9: ( R.O. )
C13: BILL NO. 1 PRELIMINARIES | E13: 3000
C16: BILL NO. 2 Sub Contractors Price
C17: 1) Structural Subcontractor | E17: 86446.16
C18: 2) MEP Sub Contractors | E18: 20927.55
C20: BILL NO. 3 Main building | E20: =+'C_Bill No. 3 Main bld (2)'!H367 -> 490778.86
C23: BILL NO. 4 Ancillary Structures | E23: ='Bill No. 4 Ancillary'!H35 -> 2901.7897
C25: BILL NO. 5 Electrical & ELV | E25: =+'Bill No.5 Electrical & ELV'!H592 -> 77653.48
C27: BILL NO. 6 Plumbing Work | E27: =+'Bill No.6 Plumbing'!H212 -> 43662.305
C30: BILL NO. 7 Finishing Work Packages | E30: =+'BILL NO.9 PROVISIONAL'!H38 -> 152700
C37: TOTAL AMOUNT (RO.) | E37: =SUM(E13:E35) -> 878070.15
C42: TOTAL CARRIED TO LITTER OF TENDER
E43: =E37+E39 -> 878070.15
C45: Total Area of the Building | E45: 5979.3
C46: Rate for the building (Rial/Sqm) | E46: =E43/E45 -> 146.85166
E51: =+E42*0.05 -> 0

Sheet C_Bill No. 3 Main bld (2)
A2: BILL NO. 3 - CIVIL WORKS
A4: ITEM | B4: ITEM DESCRIPTION | E4: QTY. | F4: UNIT | G4: RATE | H4: AMOUNT | K4: Calculated Qty
A5: REF. | H5: ( R.O. )
C7: CIVIL WORKS
C9: SUBSTRUCTURE
C11: Note:- Substructure Quantities are measured up to Ground Floor level except Finishes
C13: Excavation
A15: A | C15: Site preparation, removing 200mm depth top soil, clearing shrubs including cart away etc. | E15: =K15 -> 752.103 | F15: m2 | G15: 0 | H15: =+G15*E15 -> 0 | K15: =M.S!F8*M.S!G8 -> 752.103
M16: =4100/5227 -> 0.78438875
A17: B | C17: Excavation to reduce level including to receive pits for the foundations | E17: =K17 -> 5227.1159 | F17: m3 | G17: 0.78439 | H17: =(G17*E17) -> 4100.0974 | I17: 1900+400+1800 | K17: =M.S!I10 -> 5227.1159
A19: C | C19: Extra over for excavating in rock | E19: =K19 -> 0 | F19: m3 | H19: =+G19*E19 -> 0 | K19: 0
C21: Filling and Removals
A23: D | C23: Fill excavations and under floors & Outside with graded and hard imported granular material in layers not exceeding 150mm high and compacting the soil to obtain a density of 98% of the maximum dry density including watering and compaction tests to the approval of the Engineer | E23: 1400 | F23: m3 | G23: 2 | H23: =(G23*E23) -> 2800 | K23: 0
A25: E | C25: Spreading suitable excavated material over the site and compaction in layers not exceeding 150mm high and compacting the soil to obtain a density of 98% of the maximum dry density including watering and compaction tests to the approval of the Engineer | E25: =K25 -> 0 | F25: m3 | K25: 0
A27: F | C27: Remove unsuitable excavated material and cart away to Municipal approved dumping yard | E27: =K27 -> 5227.1159 | F27: m3 | H27: 500 | K27: =M.S!I10 -> 5227.1159
C28: To Collection | G28: R.O.
H29: =SUM(H15:H28) -> 7400.0974
C31: Substructure (Cont'd)
C33: Anti-termite barrier
P34: =+E75+E130+'Bill No. 4 Ancillary'!E20 -> 492873.14
A35: A | C35: Anti-termite treatment applied to surface of filling under floors including peripheral area with approved chemicals with 10-years guarantee as specified and to the approval of the Engineer (measured flat over plinth area) | E35: 1500 | F35: m2 | G35: 0.265 | H35: =+G35*E35 -> 397.5 | K35: =M.S!F8*M.S!G8 -> 752.103
C37: Concrete Work
C39: SRC plain poured pre-mixed concrete, Grade 15N/mm² including placing, curing, cube tests and form work as required.
A41: B | C41: Blinding Concrete | E41: =K41 -> 165.3649 | F41: m3 | G41: 17.5 | H41: =+G41*E41 -> 2893.8857 | K41: =M.S!R27+M.S!S27 -> 165.3649
C43: SRC reinforced pre-mixed cement concrete, Grade 40N/mm² as specified including placing, vibrating, curing and cube tests, etc.,
A45: C | C45: Raft, Shore pile, Capping beam | E45: =K45 -> 670.7941 | F45: m3 | G45: 19.75 | H45: =+G45*E45 -> 13248.183 | K45: =M.S!V31+M.S!H291+M.S!I293 -> 670.7941
A47: D | C47: Columns | E47: =K47 -> 62.115 | F47: m3 | G47: 19.75 | H47: =+G47*E47 -> 1226.7713 | K47: =M.S!V43 -> 62.115
A49: E | C49: RCC Lift wall/Core wall | E49: =K49 -> 35.8566 | F49: m3 | G49: 19.75 | H49: =+G49*E49 -> 708.16785 | K49: =M.S!V89 -> 35.8566
A51: F | C51: Shear Wall | E51: =+K51 -> 192.8043 | F51: m3 | G51: 19.75 | H51: =+G51*E51 -> 3807.8849 | K51: =M.S!V109 -> 192.8043
C52: To Collection | G52: R.O.
H53: =SUM(H35:H52) -> 22282.393
C55: Substructure (Cont'd)
C57: Formwork
A59: A | C59: Foundations | E59: =K59 -> 88.848 | F59: m2 | G59: 2 | H59: =+G59*E59 -> 177.696 | K59: =M.S!X31 -> 88.848
A61: B | C61: Columns | E61: =K61 -> 62.115 | F61: m2 | G61: 2 | H61: =+G61*E61 -> 124.23 | K61: =M.S!V43 -> 62.115
A63: C | C63: RCC Lift wall/Core wall | E63: =K63 -> 1664.208 | F63: m2 | G63: 2 | H63: =+G63*E63 -> 3328.416 | K63: =M.S!X89+M.S!X109 -> 1664.208
A65: D | C65: Plinth Beams | E65: =K65 -> 10.5522 | F65: m2 | G65: 2 | H65: =+G65*E65 -> 21.1044 | K65: =M.S!V127 -> 10.5522
A67: E | C67: Ramp | E67: =K67 -> 5 | F67: m2 | G67: 2 | H67: =+G67*E67 -> 10 | K67: 5
A69: F | C69: Shear Wall | E69: =+K69 -> 3156.392 | F69: m3 | G69: 2 | H69: =+G69*E69 -> 6312.784 | K69: =M.S!X100+M.S!X109 -> 3156.392
C71: Reinforcement Works
C73: High yield steel deformed bar reinforcement BS 4449 (Grade Fe 500) of all including cutting, bending, fixing in position, binding wire, chairs, spacers, extra bars at cutouts/opening and protection against rusting etc as per structural drawing and schedule
A75: G | C75: 8mm to 25mm diameter bars | E75: =K75 -> 130471.1 | F75: Kg | G75: 0.3 | H75: =+G75*E75 -> 39141.329 | K75: =6323.835+53873.6415+28651.1505+13238.94+4320.31+550.85+381.71+23130.66 -> 130471.1
A77: H | C77: A-193 Mesh | E77: =K77 -> 753 | F77: m2 | G77: 1.5 | H77: =+G77*E77 -> 1129.5 | K77: 753
C78: To Collection | G78: R.O.
H79: =SUM(H59:H78) -> 50245.06
C81: Substructure (Cont'd)
C83: Moisture Protection
A85: C | C85: 1000 gauge polythene sheet membrane with double welt folded joints | E85: =K85 -> 1653.649 | F85: m2 | G85: 0.2 | H85: =+G85*E85 -> 330.7298 | K85: =M.S!Z31 -> 1653.649
A87: D | C87: Two coats of fibre reinforced high build bitumen protective coating over the concrete and block surfaces below ground to achieve an overall DFT of 750 microns | E87: =K87 -> 1770.53 | F87: m2 | G87: 0.4 | H87: =+G87*E87 -> 708.212 | K87: =M.S!AD31+M.S!AD127+M.S!AD145 -> 1770.53
A89: E | C89: Water proofing with 3 mm thick bitumen sheet | E89: 1500 | F89: m2 | G89: 1.6 | H89: =+G89*E89 -> 2400
A90: F | C90: Protection board | E90: 700 | F90: m2 | G90: 2.1 | H90: =+G90*E90 -> 1470
C91: Damp proof course
A93: G | C93: 3 mm thick bituminised fibre felt damp proof course over the ground beams or grade slabs for blockwork (External wall) | E93: =K93 -> 150.5 | F93: m2 | G93: 1 | H93: =+G93*E93 -> 150.5 | K93: 150.5
C94: To Collection | G94: R.O.
H95: =SUM(H83:H94) -> 5059.4418
C97: SUPERSTRUCTURE
C98: Concrete Works
C100: Ordinary reinforced pre-mixed cement concrete Grade 40N/mm² including placing, vibrating, curing and cube tests etc. all complete with grooves/ recess/patterns as indicated in the Drawings
A102: A | C102: Columns | E102: =K102 -> 243.915 | F102: m3 | G102: 19.25 | H102: =+G102*E102 -> 4695.3638 | K102: =M.S!V55+M.S!V67 -> 243.915
A104: B | C104: RCC Walls | E104: =K104 -> 181.411 | F104: m3 | G104: 19.25 | H104: =+G104*E104 -> 3492.1618 | K104: =M.S!V100 -> 181.411
A106: C | C106: Slab, PT slab | E106: =K106 -> 1952.9757 | F106: m3 | G106: 19.25 | H106: =+G106*E106 -> 37594.782 | K106: =M.S!V136+M.S!V177+M.S!V204+M.S!V240 -> 1952.9757
A108: D | C108: Beams | E108: =K108 -> 36.9426 | F108: m3 | G108: 19.25 | H108: =+G108*E108 -> 711.14505 | K108: =M.S!R168+M.S!R195+M.S!R231 -> 36.9426
A110: E | C110: Lintels and window sills | E110: =K110 -> 48.321 | F110: m3 | G110: 19.25 | H110: =+G110*E110 -> 930.17925 | K110: ='D&W'!AF28+SUM('D&W'!X26:AE26) -> 48.321
A112: F | C112: Staircases | E112: =K112 -> 183.15258 | F112: m3 | G112: 19.25 | H112: =+G112*E112 -> 3525.6872 | K112: =M.S!V145 -> 183.15258
A114: G | C114: Columns for future extension (1.50m high) | E114: =K114 -> 90.9 | F114: m3 | G114: 19.25 | H114: =+G114*E114 -> 1749.825 | K114: =M.S!V79 -> 90.9
A116: H | C116: Shear Wall | E116: =K116 -> 181.411 | F116: m3 | G116: 19.25 | H116: =+G116*E116 -> 3492.1618 | K116: =M.S!V100 -> 181.411
C118: Concrete pedestal
A120: H | C120: Allow for concrete pedestal for AC outdoor unit, dish antenna, water tanks and other electro mechanical services including formwork, nominal reinforcement etc all complete as indicated in the drawings | E120: =K120 -> 1 | F120: Item | G120: 100 | H120: =+G120*E120 -> 100 | K120: 1
A122: J | C122: Cast in place Light weight concrete element As per elevation and details (Average thickness 650mm | E122: =K122 -> 759 | F122: m2 | G122: 3 | H122: =+G122*E122 -> 2277 | K122: =33*23 -> 759
C123: To Collection | G123: R.O.
H124: =SUM(H102:H123) -> 58568.306
C126: Reinforcement Works
C128: High yield steel deformed bar reinforcement BS 4449 (Grade Fe 500) of all including cutting, bending, fixing in position, binding wire, chairs, spacers, extra bars at cutouts/opening and protection against rusting etc as per structural drawing and schedule
A130: A | C130: 8mm to 25mm diameter bars | E130: =K130 -> 357487.29 | F130: Kgs | G130: 0.3 | H130: =+G130*E130 -> 107246.19 | K130: =487958.3835-K75 -> 357487.29
C132: Formwork
A134: H | C134: Columns | E134: =K134 -> 2419.95 | F134: m2 | G134: 2 | H134: =+G134*E134 -> 4839.9 | K134: =M.S!X55+M.S!X67+M.S!X79 -> 2419.95
A136: J | C136: RCC Walls (fair face) | E136: =K136 -> 1856.99 | F136: m2 | G136: 2 | H136: =+G136*E136 -> 3713.98 | K136: =M.S!X100 -> 1856.99
A138: K | C138: Conventional Slabs (fair face), PT Slab | E138: =K138 -> 5750.577 | F138: m2 | G138: 2 | H138: =+G138*E138 -> 11501.154 | K138: =M.S!X177*8-SUM(M.S!I36:I41)-SUM(M.S!I114:I122)-SUM(M.S!J151:J163)*7 -> 5750.577
A140: L | C140: Beams (fair face) | E140: =K140 -> 116.483 | F140: m2 | G140: 2 | H140: =+G140*E140 -> 232.966 | K140: =SUM(M.S!I114:I122)+SUM(M.S!I151:I163)*7 -> 116.483
A142: M | C142: Lintels and window sills | E142: =K142 -> 1 | F142: Item | G142: 500 | H142: =+G142*E142 -> 500 | K142: 1
A144: N | C144: Parapet Wall /Copping Beams | E144: =K144 -> 22.4 | F144: m2 | G144: 2 | H144: =+G144*E144 -> 44.8 | K144: =33*2*0.2+23*2*0.2 -> 22.4
A146: P | C146: Staircases (fair face) | E146: =K146 -> 755.04 | F146: m2 | G146: 2 | H146: =+G146*E146 -> 1510.08 | K146: =M.S!X145 -> 755.04
A148: H | C148: Shear Wall | E148: =K148 -> 1856.99 | F148: m2 | G148: 2 | H148: =+G148*E148 -> 3713.98 | K148: =M.S!X100 -> 1856.99
A150: Q | C150: Columns for future extension (fair face) | E150: =K150 -> 1 | F150: Item | G150: 100 | H150: =+G150*E150 -> 100 | K150: 1
C151: To Collection | G151: R.O.
H152: =SUM(H130:H151) -> 133403.05
C154: MASONRY WORKS
C156: Masonry works in cement sand mortar (1:4) including wall ties, laying, finishing, Concrete filling in hollow blocks at both side of Joinery to receive Door & Windows, curing etc. all complete as indicated in the drawings and as specified
A158: A | C158: 100 mm thick precast concrete hollow block work walls | E158: =K158 -> 943.075 | F158: m2 | G158: 2.5 | H158: =+G158*E158 -> 2357.6875 | I158: 1.875+0.233+0.4 | K158: =BW!M169 -> 943.075
A160: B | C160: 200 mm thick precast concrete hollow block work walls | E160: =K160 -> 16290.852 | F160: m2 | G160: 2.85 | H160: =+G160*E160 -> 46428.927 | K160: =BW!L169+Finishesh!U258 -> 16290.852
A162: C | C162: 200 mm thick precast concrete hollow block work walls (Parapet wall) | E162: =K162 -> 179.2 | F162: m2 | G162: 2.85 | H162: =+G162*E162 -> 510.72 | K162: =BW!L174 -> 179.2
A164: D | C164: 300 mm thick precast concrete hollow block work walls | E164: =K164 -> 0 | F164: m2 | G164: 4 | H164: =+G164*E164 -> 0
A165: E | C165: Fixing of Tower Hoist Diesel Engine lift | E165: 1 | F165: Nos | G165: 1500 | H165: =+G165*E165 -> 1500 | K165: =BW!K169 -> 30.37
C166: To Collection | G166: R.O.
H167: =SUM(H158:H166) -> 50797.334
C169: Metal Work (Cont'd).
C170: Staircase Handrail
C171: Supply & fixing of Polished SS Handrail (316 grade) including supports, etc., all complete as per detailed drawings and as specified
A172: A | C172: For Staircases & Ramp at basement level only | E172: =K172 -> 4 | F172: m | G172: 40 | H172: =+G172*E172 -> 160 | K172: =M.S!I534 -> 4
A173: B | C173: Internally staiarcase Floor mounted Handrail average 900mm High | E173: =K173 -> 51.85 | F173: m | G173: 15 | H173: =+G173*E173 -> 777.75 | K173: =Finishesh!F270 -> 51.85
...

Sheet Finishesh
A1: Project
A2: sub-masonry works
A4: S.No | B4: Description | C4: Unit | D4: No | F4: L | G4: B | H4: D | I4: Remarks | K4: Flooring | P4: Skirting | T4: Wall | V4: Ceiling | X4: Railings | Y4: LW CON FOR SLOPE | Z4: WPM 0.4cm | AA4: Cement Screed 3cm | AB4: EXTRUDED POLYSTYRENE 5cm. | AC4: PROTECTION BOARD 0.2cm. | AD4: SAND AND MORTAR BED 5cm. | AE4: TERRAZZO TILES 30x30x3cm. | AF4: TERRAZZO SKIRTING 30x10x3cm.
B6: internal
A7: 1 | B7: Ground floor | K7: F1 | L7: F2 | M7: F3 | N7: F4 | O7: F5 | P7: S1 | Q7: S2 | R7: S3 | S7: S4 | T7: W1 | U7: W2 | V7: C1 | W7: C2 | AG7: SCHEDULE OF FINISHING
B8: Shop 13 | C8: SQ M | D8: 1 | E8: 1 | F8: =5.47 -> 5.47 | G8: 3.3 | H8: 4.3 | N8: =F8*G8*D8*E8 -> 18.051 | R8: =((F8+G8*2)*0.15)*D8*E8 -> 1.8105 | U8: =(F8+G8*2)*H8*D8*E8 -> 51.901 | V8: =N8 -> 18.051 | AG8: FLOORING
B9: Shop 14 | C9: SQ M | D9: 1 | E9: 1 | F9: 7.1 | G9: 3.885 | H9: 4.3 | N9: =F9*G9*D9*E9 -> 27.5835 | R9: =((F9+G9*2)*0.15)*E9*D9 -> 2.2305 | U9: =(F9+G9*2)*H9*D9*E9 -> 63.941 | V9: =N9 -> 27.5835 | AG9: TYPE | AH9: DESCRIPTION
B10: Shop 15 | C10: SQ M | D10: 1 | E10: 1 | F10: =SQRT(15) -> 3.8729833 | G10: =F10 -> 3.8729833 | H10: 4.3 | N10: =F10*G10*D10*E10 -> 15 | R10: =((F10+G10*2)*0.15)*E10*D10 -> 1.7428425 | U10: =(F10+G10*2)*H10*D10*E10 -> 49.961485 | V10: =N10 -> 15 | AG10: F1 | AH10: 20mm THICK ITALIAN MARBLE STEPS COLOR ,DESIGN & SHAPE TO BE APPROVED
B11: Shop 16 | C11: SQ M | D11: 1 | E11: 1 | F11: =SQRT(14) -> 3.7416574 | G11: =F11 -> 3.7416574 | H11: 4.3 | N11: =F11*G11*D11*E11 -> 14 | R11: =((F11+G11*2)*0.15)*E11*D11 -> 1.6837458 | U11: =(F11+G11*2)*H11*D11*E11 -> 48.26738 | V11: =N11 -> 14 | AG11: F2 | AH11: 300X600X20mm ITALIAN MARBLE TILES COLOR ,DESIGN & SHAPE TO BE APPROVED
B12: Shop 17 | C12: SQ M | D12: 1 | E12: 1 | F12: =SQRT(30.2) -> 5.4954527 | G12: =F12 -> 5.4954527 | H12: 4.3 | N12: =F12*G12*D12*E12 -> 30.2 | R12: =((F12+G12*2)*0.15)*E12*D12 -> 2.4729537 | U12: =(F12+G12*2)*H12*D12*E12 -> 70.891339 | V12: =N12 -> 30.2 | AG12: F3 | AH12: 400X400X20mm PORCELAIN TILES COLOR ,DESIGN & SHAPE TO BE APPROVED
B13: Guard Room | C13: SQ M | D13: 1 | E13: 1 | F13: 2.84 | G13: 2.84 | H13: 4.3 | N13: =F13*G13*D13*E13 -> 8.0656 | R13: =((F13+G13*2)*0.15)*E13*D13 -> 1.278 | U13: =(F13+G13*2)*H13*D13*E13 -> 36.636 | V13: =N13 -> 8.0656 | AG13: F4 | AH13: 200X200X8mm FULLY VITRIFIED NON-SLIPPERY ITALIAN CERAMIC TILES COLOR ,DESIGN & SHAPE TO BE APPROVED
B14: D5 | D14: -1 | E14: 1 | F14: 1 | H14: 2.2 | N14: =F14*G14*D14*E14 -> 0 | R14: =((F14+G14*2)*0.15)*E14*D14 -> -0.15 | U14: =(F14+G14*2)*H14*D14*E14 -> -2.2 | V14: =N14 -> 0 | AG14: F5 | AH14: 300X300X8mm BEST QUALITY TERRAZZO TILES COLOR ,DESIGN & SHAPE TO BE APPROVED
B15: D6 | D15: -1 | E15: 1 | F15: 0.8 | H15: 2.2 | N15: =F15*G15*D15*E15 -> 0 | R15: =((F15+G15*2)*0.15)*E15*D15 -> -0.12 | U15: =(F15+G15*2)*H15*D15*E15 -> -1.76 | V15: =N15 -> 0 | AG15: SKIRTING
B16: D7 | D16: -1 | E16: 1 | F16: 0.8 | H16: 2.2 | N16: =F16*G16*D16*E16 -> 0 | R16: =((F16+G16*2)*0.15)*E16*D16 -> -0.12 | U16: =(F16+G16*2)*H16*D16*E16 -> -1.76 | V16: =N16 -> 0 | AG16: TYPE | AH16: DESCRIPTION
B17: Gents Toilet | C17: SQ M | D17: 1 | E17: 1 | F17: 1 | G17: 2 | H17: 4.3 | O17: =G17*D17*E17*F17 -> 2 | U17: =(F17+G17*2)*H17*D17*E17 -> 21.5 | W17: =O17 -> 2 | AG17: S1 | AH17: 600X100X20mm ITALIAN MARBLE SKIRTING WITH HALF ROUND TOP EDGE COLOR ,DESIGN & SHAPE TO BE APPROVED.
B18: D6 | D18: -1 | E18: 1 | F18: 0.8 | H18: 2.2 | O18: =G18*D18*E18*F18 -> 0 | U18: =(F18+G18*2)*H18*D18*E18 -> -1.76 | W18: =O18 -> 0 | AG18: S2 | AH18: 400X100X20mm HEIGHT PORCELAIN SKIRTING WITH HALF ROUND TOP EDGE
B19: Ladies Toilet | C19: SQ M | D19: 1 | E19: 1 | F19: 1.5 | G19: 2 | H19: 4.3 | O19: =G19*D19*E19*F19 -> 3 | U19: =(F19+G19*2)*H19*D19*E19 -> 23.65 | W19: =O19 -> 3 | AG19: S3 | AH19: 300X100X20mm HEIGHT TERRAZZO SKIRTING WITH HALF ROUND TOP EDGE
B20: D6* | D20: -1 | E20: 1 | F20: 1 | H20: 2.2 | O20: =G20*D20*E20*F20 -> 0 | U20: =(F20+G20*2)*H20*D20*E20 -> -2.2 | W20: =O20 -> 0 | AG20: S4 | AH20: 20mm THICK GRAY NIGHT MARBLE STEPS COLOR ,DESIGN & SHAPE TO BE APPROVED
B21: Electric room | C21: SQ M | D21: 2 | E21: 1 | F21: 3.56 | G21: 3.56 | H21: 4.3 | O21: =G21*D21*E21*F21 -> 25.3472 | S21: =((G21+F21*2)*0.5)*D21*E21 -> 10.68 | U21: =(F21+G21*2)*H21*D21*E21 -> 91.848 | W21: =O21 -> 25.3472 | AG21: WALLS
B22: D10 | D22: -1 | E22: 1 | F22: 0.9 | H22: 2.2 | O22: =G22*D22*E22*F22 -> 0 | U22: =(F22+G22*2)*H22*D22*E22 -> -1.98 | W22: =O22 -> 0 | AG22: TYPE | AH22: DESCRIPTION
B23: staircse front lobby | C23: SQ M | D23: 1 | E23: 1 | F23: 2.2 | G23: 4.6 | H23: 4.3 | L23: =PRODUCT(D23:G23) -> 10.12 | Q23: =(F23*2+G23*2)*0.15*D23*E23 -> 2.04 | U23: =(F23+G23*2)*H23*D23*E23 -> 49.02 | W23: =L23 -> 10.12 | AG23: W1 | AH23: 1 COAT PRIMER +2 COATS OF PUTTY + 3 COATS OF FENOMASTIC GOLD PAINT OR EQUIVALENT (COLOR SHALL BE FROM M.LN COLOR CHART AS APPROVED BY ENGINEER) ON 20mm THICK CEMENT SAND PLASTER
B24: D10 | D24: -1 | E24: 1 | F24: 0.9 | H24: 2.2 | L24: =F22*G22*D22*E22 -> 0 | Q24: =((F16+G16*2)*0.15)*E16*D16 -> -0.12 | U24: =(F24+G24*2)*H24*D24*E24 -> -1.98 | W24: =L24 -> 0 | AG24: W2 | AH24: 200X300mm GLAZED ITALIAN CERAMIC TILES FOR WALLS UP TO CEILING LEVEL COLOR & DESIGN TO BE APPROVED
B25: Shop 1 | C25: SQ M | D25: 1 | E25: 1 | F25: 3 | G25: 10.45 | H25: 4.3 | N25: =F25*G25*D25*E25 -> 31.35 | R25: =((F25+G25*2)*0.15)*D25*E25 -> 3.585 | U25: =(F25+G25*2)*H25*D25*E25 -> 102.77 | V25: =N25 -> 31.35 | AG25: CEILING
B26: D15 | D26: -1 | E26: 1 | F26: 1.35 | H26: 2.2 | N26: =F26*G26*D26*E26 -> 0 | R26: =((F26+G26*2)*0.15)*E26*D26 -> -0.2025 | U26: =(F26+G26*2)*H26*D26*E26 -> -2.97 | V26: =N26 -> 0 | AG26: TYPE | AH26: DESCRIPTION
B27: Shop 2 | C27: SQ M | D27: 1 | E27: 1 | F27: 3.25 | G27: 9.6 | H27: 4.3 | N27: =F27*G27*D27*E27 -> 31.2 | R27: =((F27+G27*2)*0.15)*D27*E27 -> 3.3675 | U27: =(F27+G27*2)*H27*D27*E27 -> 96.535 | V27: =N27 -> 31.2 | AG27: C1 | AH27: 1 COAT PRIMER +2 COATS OF PUTTY + 3 COATS OF FENOMASTIC GOLD PAINT OR EQUIVALENT (COLOR SHALL BE FROM AS APPROVED BY ENGINEER)
B28: D15 | D28: -1 | E28: 1 | F28: 1.56 | H28: 2.2 | N28: =F28*G28*D28*E28 -> 0 | R28: =((F28+G28*2)*0.15)*E28*D28 -> -0.234 | U28: =(F28+G28*2)*H28*D28*E28 -> -3.432 | V28: =N28 -> 0 | AG28: C2 | AH28: DECORATIVE SUSPENDED FIRE RESISTANT 12mm THICK GYPSUM BOARD (DANOGIPS OR EQUIVALENT) CEILING FIXED WITH CONCEALED METAL SUSPENSION SYSTEM FIXED TO THE SOFFIT OF SLAB/BEAM OR TO WALL ALL BOARD JOINTS TO BE TAPED AND SKIMMED AND PAINTED AS STANDARD IN C2
B29: Shop 3 | C29: SQ M | D29: 1 | E29: 1 | F29: 3 | G29: 12.1 | H29: 4.3 | N29: =F29*G29*D29*E29 -> 36.3 | R29: =((F29+G29*2)*0.15)*D29*E29 -> 4.08 | U29: =(F29+G29*2)*H29*D29*E29 -> 116.96 | V29: =N29 -> 36.3
B30: D2 | D30: -1 | E30: 1 | F30: 1.8 | H30: 2.2 | N30: =F30*G30*D30*E30 -> 0 | R30: =((F30+G30*2)*0.15)*E30*D30 -> -0.27 | U30: =(F30+G30*2)*H30*D30*E30 -> -3.96 | V30: =N30 -> 0
B31: Shop 4,5,6,7 | C31: SQ M | D31: 1 | E31: 4 | F31: 2.7 | G31: 11.1 | H31: 4.3 | N31: =F31*G31*D31*E31 -> 119.88 | R31: =((F31+G31*2)*0.15)*D31*E31 -> 14.94 | U31: =(F31+G31*2)*H31*D31*E31 -> 428.28 | V31: =N31 -> 119.88
B32: D2 | D32: -1 | E32: 1 | F32: 1.8 | H32: 2.2 | N32: =F32*G32*D32*E32 -> 0 | R32: =((F32+G32*2)*0.15)*E32*D32 -> -0.27 | U32: =(F32+G32*2)*H32*D32*E32 -> -3.96 | V32: =N32 -> 0
B33: Shop 8 | C33: SQ M | D33: 1 | E33: 1 | F33: 3 | G33: 8.1 | H33: 4.3 | N33: =F33*G33*D33*E33 -> 24.3 | R33: =((F33+G33*2)*0.15)*D33*E33 -> 2.88 | U33: =(F33+G33*2)*H33*D33*E33 -> 82.56 | V33: =N33 -> 24.3
B34: D2 | D34: -1 | E34: 1 | F34: 1.8 | H34: 2.2 | N34: =F34*G34*D34*E34 -> 0 | R34: =((F34+G34*2)*0.15)*E34*D34 -> -0.27 | U34: =(F34+G34*2)*H34*D34*E34 -> -3.96 | V34: =N34 -> 0
B35: Shop 9 | C35: SQ M | D35: 1 | E35: 1 | F35: 5.81 | G35: 5.81 | H35: 4.3 | N35: =F35*G35*D35*E35 -> 33.7561 | R35: =((F35+G35*2)*0.15)*D35*E35 -> 2.6145 | U35: =(F35+G35*2)*H35*D35*E35 -> 74.949 | V35: =N35 -> 33.7561
B36: D2 | D36: -1 | E36: 2 | F36: 1.8 | H36: 2.2 | N36: =F36*G36*D36*E36 -> 0 | R36: =((F36+G36*2)*0.15)*E36*D36 -> -0.54 | U36: =(F36+G36*2)*H36*D36*E36 -> -7.92 | V36: =N36 -> 0
B37: Shop 10 | C37: SQ M | D37: 1 | E37: 1 | F37: 2.7 | G37: 10.1 | H37: 4.3 | N37: =F37*G37*D37*E37 -> 27.27 | R37: =((F37+G37*2)*0.15)*D37*E37 -> 3.435 | U37: =(F37+G37*2)*H37*D37*E37 -> 98.47 | V37: =N37 -> 27.27
B38: D2 | D38: -1 | E38: 1 | F38: 1.8 | H38: 2.2 | N38: =F38*G38*D38*E38 -> 0 | R38: =((F38+G38*2)*0.15)*E38*D38 -> -0.27 | U38: =(F38+G38*2)*H38*D38*E38 -> -3.96 | V38: =N38 -> 0
B39: Shop 11 | C39: SQ M | D39: 1 | E39: 1 | F39: 2.75 | G39: 11 | H39: 4.3 | N39: =F39*G39*D39*E39 -> 30.25 | R39: =((F39+G39*2)*0.15)*D39*E39 -> 3.7125 | U39: =(F39+G39*2)*H39*D39*E39 -> 106.425 | V39: =N39 -> 30.25
B40: D2 | D40: -1 | E40: 1 | F40: 1.8 | H40: 2.2 | N40: =F40*G40*D40*E40 -> 0 | R40: =((F40+G40*2)*0.15)*E40*D40 -> -0.27 | U40: =(F40+G40*2)*H40*D40*E40 -> -3.96 | V40: =N40 -> 0
B41: Shop 12 | C41: SQ M | D41: 1 | E41: 1 | F41: 3.3 | G41: 11.9 | H41: 4.3 | N41: =F41*G41*D41*E41 -> 39.27 | R41: =((F41+G41*2)*0.15)*D41*E41 -> 4.065 | U41: =(F41+G41*2)*H41*D41*E41 -> 116.53 | V41: =N41 -> 39.27
B42: D2 | D42: -1 | E42: 1 | F42: 1.8 | H42: 2.2 | N42: =F42*G42*D42*E42 -> 0 | R42: =((F42+G42*2)*0.15)*E42*D42 -> -0.27 | U42: =(F42+G42*2)*H42*D42*E42 -> -3.96 | V42: =N42 -> 0
B44: Flat 1
B45: Family Hall | C45: SQ M | D45: 6 | E45: 1 | F45: 5.6 | G45: 5.6 | H45: 3.3 | N45: =F45*G45*D45*E45 -> 188.16 | R45: =((F45+G45*2)*0.15)*E45*D45 -> 15.12 | U45: =(F45*2+G45*2)*H45*D45*E45 -> 443.52 | W45: =N45 -> 188.16
B46: D9 | D46: -6 | E46: 1 | F46: 1.1 | H46: 2.2 | N46: =F46*G46*D46*E46 -> 0 | R46: =((F46+G46*2)*0.15)*E46*D46 -> -0.99 | U46: =(F46+G46*2)*H46*D46*E46 -> -14.52 | W46: =N46 -> 0
B47: D6 | D47: -6 | E47: 1 | F47: 0.8 | H47: 2.2 | N47: =F47*G47*D47*E47 -> 0 | R47: =((F47+G47*2)*0.15)*E47*D47 -> -0.72 | U47: =(F47+G47*2)*H47*D47*E47 -> -10.56 | W47: =N47 -> 0
B48: D11 | D48: -6 | E48: 1 | F48: 1 | H48: 2.2 | N48: =F48*G48*D48*E48 -> 0 | R48: =((F48+G48*2)*0.15)*E48*D48 -> -0.9 | U48: =(F48+G48*2)*H48*D48*E48 -> -13.2 | W48: =N48 -> 0
B49: Bed Room | C49: SQ M | D49: 6 | E49: 1 | F49: 4.1 | G49: 3 | H49: 3.3 | N49: =F49*G49*D49*E49 -> 73.8 | R49: =((F49+G49*2)*0.15)*E49*D49 -> 9.09 | U49: =(F49*2+G49*2)*H49*D49*E49 -> 281.16 | W49: =N49 -> 73.8
B50: W1 | D50: -6 | E50: 1 | F50: 2 | H50: 1.4 | N50: =F50*G50*D50*E50 -> 0 | R50: 0 | U50: =(F50+G50*2)*H50*D50*E50 -> -16.8 | W50: =N50 -> 0
B51: Balcony | C51: SQ M | D51: 6 | E51: 1 | F51: 1.3 | G51: 1.96 | H51: 3.3 | N51: =F51*G51*D51*E51 -> 15.288 | R51: =((F51+G51*2)*0.15)*E51*D51 -> 4.698 | U51: =G51*2*H51*D51*E51 -> 77.616 | W51: =N51 -> 15.288
B52: Toilet | C52: SQ M | D52: 6 | E52: 1 | F52: 1.5 | G52: 1.15 | H52: 3.3 | O52: =F52*G52*D52*E52 -> 10.35 | U52: =(G52+F52*2)*H52*D52*E52 -> 82.17 | W52: =O52 -> 10.35
B53: Bath | C53: SQ M | D53: 6 | E53: 1 | F53: 1.5 | G53: 1.15 | H53: 3.3 | O53: =F53*G53*D53*E53 -> 10.35 | U53: =(G53*2+F53*2)*H53*D53*E53 -> 104.94 | W53: =O53 -> 10.35
B54: D12 | D54: -6 | E54: 1 | F54: 0.9 | H54: 2.2 | O54: =F54*G54*D54*E54 -> 0 | U54: =(G54*2+F54*2)*H54*D54*E54 -> -23.76 | W54: =O54 -> 0
B55: Open Kitchen | C55: SQ M | D55: 6 | E55: 1 | F55: 2.7 | G55: 1.4 | H55: 3.3 | O55: =F55*G55*D55*E55 -> 22.68 | U55: =(G55*2+F55*2)*H55*D55*E55 -> 162.36 | W55: =O55 -> 22.68
B56: D7 | D56: -6 | E56: 1 | F56: 0.8 | H56: 2.2 | O56: =F56*G56*D56*E56 -> 0 | U56: =(G56*2+F56*2)*H56*D56*E56 -> -21.12 | W56: =O56 -> 0
B57: Balcony | C57: SQ M | D57: 6 | E57: 1 | F57: 2.83 | G57: 0.9 | H57: 3.3 | N57: =F57*G57*D57*E57 -> 15.282 | R57: =((F57+G57*2)*0.15)*E57*D57 -> 4.167 | U57: =G57*2*H57*D57*E57 -> 35.64 | W57: =N57 -> 15.282
B58: D7 | D58: -6 | E58: 1 | F58: 0.8 | H58: 2.2 | N58: =F58*G58*D58*E58 -> 0 | U58: =(G58*2+F58*2)*H58*D58*E58 -> -21.12 | W58: =O58 -> 0
B59: Flat 2
B60: Family Hall | C60: SQ M | D60: 6 | E60: 1 | F60: 3.96 | G60: 3.96 | H60: 3.3 | N60: =F60*G60*D60*E60 -> 94.0896 | R60: =((F60+G60*2)*0.15)*E60*D60 -> 10.692 | U60: =(F60*2+G60*2)*H60*D60*E60 -> 313.632 | W60: =N60 -> 94.0896
B61: D6 | D61: -6 | E61: 1 | F61: 0.8 | H61: 2.2 | N61: =F61*G61*D61*E61 -> 0 | R61: =((F61+G61*2)*0.15)*E61*D61 -> -0.72 | U61: =(F61+G61*2)*H61*D61*E61 -> -10.56 | W61: =N61 -> 0
B62: D11 | D62: -6 | E62: 1 | F62: 1 | H62: 2.2 | N62: =F62*G62*D62*E62 -> 0 | R62: =((F62+G62*2)*0.15)*E62*D62 -> -0.9 | U62: =(F62+G62*2)*H62*D62*E62 -> -13.2 | W62: =N62 -> 0
B63: D5 | D63: -6 | E63: 1 | F63: 1 | H63: 2.2 | N63: =F63*G63*D63*E63 -> 0 | R63: =((F63+G63*2)*0.15)*E63*D63 -> -0.9 | U63: =(F63+G63*2)*H63*D63*E63 -> -13.2 | W63: =N63 -> 0
B64: D9 | D64: -6 | E64: 1 | F64: 1.1 | H64: 2.2 | N64: =F64*G64*D64*E64 -> 0 | R64: =((F64+G64*2)*0.15)*E64*D64 -> -0.99 | U64: =(F64+G64*2)*H64*D64*E64 -> -14.52 | W64: =N64 -> 0
B65: Bed Room | C65: SQ M | D65: 6 | E65: 1 | F65: 3.8 | G65: 3.3 | H65: 3.3 | N65: =F65*G65*D65*E65 -> 75.24 | R65: =((F65+G65*2)*0.15)*E65*D65 -> 9.36 | U65: =(F65*2+G65*2)*H65*D65*E65 -> 281.16 | W65: =N65 -> 75.24
B66: D11 | D66: -6 | E66: 1 | F66: 1 | H66: 2.2 | N66: =F66*G66*D66*E66 -> 0 | R66: =((F66+G66*2)*0.15)*E66*D66 -> -0.9 | U66: =(F66+G66*2)*H66*D66*E66 -> -13.2 | W66: =N66 -> 0
B67: D5 | D67: -6 | E67: 1 | F67: 1 | H67: 2.2 | N67: =F67*G67*D67*E67 -> 0 | R67: =((F67+G67*2)*0.15)*E67*D67 -> -0.9 | U67: =(F67+G67*2)*H67*D67*E67 -> -13.2 | W67: =N67 -> 0
B68: Bath | C68: SQ M | D68: 6 | E68: 1 | F68: 1.5 | G68: 1.15 | H68: 3.3 | O68: =F68*G68*D68*E68 -> 10.35 | U68: =(G68*2+F68*2)*H68*D68*E68 -> 104.94 | W68: =O68 -> 10.35
B69: D12 | D69: -6 | E69: 1 | F69: 0.9 | H69: 2.2 | O69: =F69*G69*D69*E69 -> 0 | U69: =(G69*2+F69*2)*H69*D69*E69 -> -23.76 | W69: =O69 -> 0
B70: D11 | D70: -6 | E70: 1 | F70: 1 | H70: 2.2 | N70: =F70*G70*D70*E70 -> 0 | R70: =((F70+G70*2)*0.15)*E70*D70 -> -0.9 | U70: =(F70+G70*2)*H70*D70*E70 -> -13.2 | W70: =N70 -> 0
B71: Balcony | C71: SQ M | D71: 6 | E71: 1 | F71: 1.4 | G71: 2.4 | H71: 3.3 | N71: =F71*G71*D71*E71 -> 20.16 | R71: =((F71+G71*2)*0.15)*E71*D71 -> 5.58 | U71: =G71*2*H71*D71*E71 -> 95.04 | W71: =N71 -> 20.16
B72: D11 | D72: -6 | E72: 1 | F72: 1 | H72: 2.2 | N72: =F72*G72*D72*E72 -> 0 | R72: =((F72+G72*2)*0.15)*E72*D72 -> -0.9 | U72: =(F72+G72*2)*H72*D72*E72 -> -13.2 | W72: =N72 -> 0
B73: Open Kitchen | C73: SQ M | D73: 6 | E73: 1 | F73: 3 | G73: 2 | H73: 3.3 | O73: =F73*G73*D73*E73 -> 36 | U73: =(G73*2+F73*2)*H73*D73*E73 -> 198 | W73: =O73 -> 36
B74: W2 | D74: -6 | E74: 1 | F74: 1 | H74: 1.1 | N74: =F74*G74*D74*E74 -> 0 | R74: 0 | U74: =(F74+G74*2)*H74*D74*E74 -> -6.6 | W74: =N74 -> 0
B75: D7 | D75: -6 | E75: 1 | F75: 0.8 | H75: 2.2 | O75: =F75*G75*D75*E75 -> 0 | U75: =(G75*2+F75*2)*H75*D75*E75 -> -21.12 | W75: =O75 -> 0
B76: Balcony | C76: SQ M | D76: 6 | E76: 1 | F76: 2.83 | G76: 0.9 | H76: 3.3 | N76: =F76*G76*D76*E76 -> 15.282 | R76: =((F76+G76*2)*0.15)*E76*D76 -> 4.167 | U76: =G76*2*H76*D76*E76 -> 35.64 | W76: =N76 -> 15.282
B77: D7 | D77: -6 | E77: 1 | F77: 0.8 | H77: 2.2 | N77: =F77*G77*D77*E77 -> 0 | U77: =(G77*2+F77*2)*H77*D77*E77 -> -21.12 | W77: =O77 -> 0
B78: Balcony | C78: SQ M | D78: 6 | E78: 1 | F78: 2.83 | G78: 0.9 | H78: 3.3 | N78: =F78*G78*D78*E78 -> 15.282 | R78: =((F78+G78*2)*0.15)*E78*D78 -> 4.167 | U78: =G78*2*H78*D78*E78 -> 35.64 | W78: =N78 -> 15.282
B79: D11 | D79: -6 | E79: 1 | F79: 1 | H79: 2.2 | N79: =F79*G79*D79*E79 -> 0 | R79: =((F79+G79*2)*0.15)*E79*D79 -> -0.9 | U79: =(F79+G79*2)*H79*D79*E79 -> -13.2 | W79: =N79 -> 0
B80: Toilet | C80: SQ M | D80: 6 | E80: 1 | F80: 1.69 | G80: 1 | H80: 3.3 | O80: =F80*G80*D80*E80 -> 10.14 | U80: =(G80+F80*2)*H80*D80*E80 -> 86.724 | W80: =O80 -> 10.14
B81: D6 | D81: -6 | E81: 1 | F81: 0.8 | H81: 2.2 | N81: =F81*G81*D81*E81 -> 0 | R81: =((F81+G81*2)*0.15)*E81*D81 -> -0.72 | U81: =(F81+G81*2)*H81*D81*E81 -> -10.56 | W81: =N81 -> 0
B82: Flat 3
B83: Family Hall | C83: SQ M | D83: 6 | E83: 1 | F83: 4.62 | G83: 4.62 | H83: 3.3 | N83: =F83*G83*D83*E83 -> 128.0664 | R83: =((F83+G83*2)*0.15)*E83*D83 -> 12.474 | U83: =(F83*2+G83*2)*H83*D83*E83 -> 365.904 | W83: =N83 -> 128.0664
B84: D6 | D84: -6 | E84: 1 | F84: 0.8 | H84: 2.2 | N84: =F84*G84*D84*E84 -> 0 | R84: =((F84+G84*2)*0.15)*E84*D84 -> -0.72 | U84: =(F84+G84*2)*H84*D84*E84 -> -10.56 | W84: =N84 -> 0
B85: D11 | D85: -6 | E85: 1 | F85: 1 | H85: 2.2 | N85: =F85*G85*D85*E85 -> 0 | R85: =((F85+G85*2)*0.15)*E85*D85 -> -0.9 | U85: =(F85+G85*2)*H85*D85*E85 -> -13.2 | W85: =N85 -> 0
B86: D5 | D86: -6 | E86: 1 | F86: 1 | H86: 2.2 | N86: =F86*G86*D86*E86 -> 0 | R86: =((F86+G86*2)*0.15)*E86*D86 -> -0.9 | U86: =(F86+G86*2)*H86*D86*E86 -> -13.2 | W86: =N86 -> 0
B87: D9 | D87: -6 | E87: 1 | F87: 1.1 | H87: 2.2 | N87: =F87*G87*D87*E87 -> 0 | R87: =((F87+G87*2)*0.15)*E87*D87 -> -0.99 | U87: =(F87+G87*2)*H87*D87*E87 -> -14.52 | W87: =N87 -> 0
B88: Bed Room | C88: SQ M | D88: 6 | E88: 1 | F88: 3.8 | G88: 3.2 | H88: 3.3 | N88: =F88*G88*D88*E88 -> 72.96 | R88: =((F88+G88*2)*0.15)*E88*D88 -> 9.18 | U88: =(F88*2+G88*2)*H88*D88*E88 -> 277.2 | W88: =N88 -> 72.96
B89: D11 | D89: -6 | E89: 1 | F89: 1 | H89: 2.2 | N89: =F89*G89*D89*E89 -> 0 | R89: =((F89+G89*2)*0.15)*E89*D89 -> -0.9 | U89: =(F89+G89*2)*H89*D89*E89 -> -13.2 | W89: =N89 -> 0
B90: D5 | D90: -6 | E90: 1 | F90: 1 | H90: 2.2 | N90: =F90*G90*D90*E90 -> 0 | R90: =((F90+G90*2)*0.15)*E90*D90 -> -0.9 | U90: =(F90+G90*2)*H90*D90*E90 -> -13.2 | W90: =N90 -> 0
B91: Bath | C91: SQ M | D91: 6 | E91: 1 | F91: 2.7 | G91: 1.5 | H91: 3.3 | O91: =F91*G91*D91*E91 -> 24.3 | U91: =(G91*2+F91*2)*H91*D91*E91 -> 166.32 | W91: =O91 -> 24.3
B92: D12 | D92: -6 | E92: 1 | F92: 0.9 | H92: 2.2 | O92: =F92*G92*D92*E92 -> 0 | U92: =(G92*2+F92*2)*H92*D92*E92 -> -23.76 | W92: =O92 -> 0
B93: Toilet | C93: SQ M | D93: 6 | E93: 1 | F93: 1.8 | G93: 1 | H93: 3.3 | O93: =F93*G93*D93*E93 -> 10.8 | U93: =(G93+F93*2)*H93*D93*E93 -> 91.08 | W93: =O93 -> 10.8
B94: D6 | D94: -6 | E94: 1 | F94: 0.8 | H94: 2.2 | N94: =F94*G94*D94*E94 -> 0 | R94: =((F94+G94*2)*0.15)*E94*D94 -> -0.72 | U94: =(F94+G94*2)*H94*D94*E94 -> -10.56 | W94: =N94 -> 0
B95: Open Kitchen | C95: SQ M | D95: 6 | E95: 1 | F95: 2.6 | G95: 2 | H95: 3.3 | O95: =F95*G95*D95*E95 -> 31.2 | U95: =(G95*2+F95*2)*H95*D95*E95 -> 182.16 | W95: =O95 -> 31.2
B96: W2 | D96: -6 | E96: 1 | F96: 1 | H96: 1.1 | N96: =F96*G96*D96*E96 -> 0 | R96: 0 | U96: =(F96+G96*2)*H96*D96*E96 -> -6.6 | W96: =N96 -> 0
B97: D7 | D97: -6 | E97: 1 | F97: 0.8 | H97: 2.2 | O97: =F97*G97*D97*E97 -> 0 | U97: =(G97*2+F97*2)*H97*D97*E97 -> -21.12 | W97: =O97 -> 0
B98: Balcony | C98: SQ M | D98: 6 | E98: 1 | F98: 2.2 | G98: 0.8 | H98: 3.3 | N98: =F98*G98*D98*E98 -> 10.56 | R98: =((F98+G98*2)*0.15)*E98*D98 -> 3.42 | U98: =G98*2*H98*D98*E98 -> 31.68 | W98: =N98 -> 10.56
B99: D7 | D99: -6 | E99: 1 | F99: 0.8 | H99: 2.2 | N99: =F99*G99*D99*E99 -> 0 | U99: =(G99*2+F99*2)*H99*D99*E99 -> -21.12 | W99: =O99 -> 0
B100: Balcony | C100: SQ M | D100: 6 | E100: 2 | F100: 2.4 | G100: 1.2 | H100: 3.3 | N100: =F100*G100*D100*E100 -> 34.56 | R100: =((F100+G100*2)*0.15)*E100*D100 -> 8.64 | U100: =G100*2*H100*D100*E100 -> 95.04 | W100: =N100 -> 34.56
B101: D11 | D101: -6 | E101: 2 | F101: 1 | H101: 2.2 | N101: =F101*G101*D101*E101 -> 0 | R101: =((F101+G101*2)*0.15)*E101*D101 -> -1.8 | U101: =(F101+G101*2)*H101*D101*E101 -> -26.4 | W101: =N101 -> 0
B102: Flat 4
B103: Family Hall | C103: SQ M | D103: 6 | E103: 1 | F103: 4.05 | G103: 4.05 | H103: 3.3 | N103: =F103*G103*D103*E103 -> 98.415 | R103: =((F103+G103*2)*0.15)*E103*D103 -> 10.935 | U103: =(F103*2+G103*2)*H103*D103*E103 -> 320.76 | W103: =N103 -> 98.415
...

Sheet M.S
A1: PROJECT:- RESIDENTIAL / COMMERCIAL BUILDING
A2: SUB:- Main bld measurement
R3: Blindings or P.C.C | V3: RCC works | Z3: Polythene sheet | AD3: Water proofing to RCC | AH3: isolation joint | AK3: Solid blockworks
A4: S.No | B4: Description | C4: Unit | D4: No | F4: L | G4: B | H4: D | I4: Qty | J4: If Irregular Area of Concrete | L4: If Irregular perimeter form works | N4: Remarks | P4: Blindings | R4: Concrete | T4: Shuttering | V4: Concrete | X4: Shuttering | Z4: Bottom of P.C.C | AA4: Sides of P.C.C | AD4: Bottom of RCC | AE4: Sides of RCC | AF4: Top of RCC | AH4: sides of grade slab and plinth | AK4: Masonry works | AM4: BRC mesh | AO4: Construction joint
J5: PCC | K5: RCC | L5: PCC | M5: RCC | P5: Thk | Q5: Offset | R5: P.C.C shape ''m3'' | S5: P.C.C Irregular ''m3'' | T5: P.C.C shape ''m2'' | U5: P.C.C Irregular ''m2'' | V5: R.C.C shape ''m3'' | W5: R.C.C Irregular ''m3'' | X5: R.C.C shape ''m2'' | Y5: R.C.C Irregular ''m2'' | Z5: Bottom''m2'' | AA5: Sides and Top''m2'' | AD5: Bottom''m2'' | AE5: Sides''m2'' | AF5: Top''m2'' | AH5: R.C.C shape ''m'' | AI5: R.C.C Irregular ''m'' | AK5: Externally | AL5: Internally | AM5: R.C.C shape ''m2'' | AN5: R.C.C Irregular ''m2'' | AO5: Vertical | AP5: Horizontally
B7: Earth works
B8: Footing base | C8: m3 | D8: 1 | E8: 1 | F8: 32.1 | G8: 23.43 | H8: 6.95 | I8: =PRODUCT(D8:H8) -> 5227.1159
B10: Total | I10: =SUM(I8:I9) -> 5227.1159
B12: Back filling
B13: Total excavated | C13: m3 | D13: 1 | E13: 1 | F13: =I10 -> 5227.1159 | I13: =PRODUCT(D13:H13) -> 5227.1159
B14: Deduction
B15: Basement deduction | C15: m3 | D15: 1 | E15: 1 | F15: 0 | H15: 0 | I15: =PRODUCT(D15:H15) -> 0
B16: Workikng space filling afterwork | C16: m3 | D16: 1 | E16: 1 | F16: 0 | G16: 0 | H16: =H15 -> 0 | I16: =PRODUCT(D16:H16) -> 0
B17: Above NGL Filling if Any
B19: Total | I19: =SUM(I13:I18) -> 5227.1159
B21: Grave Filling | C21: m3 | D21: 1 | E21: 1 | F21: 0 | G21: 0 | H21: 0 | I21: =PRODUCT(D21:H21) -> 0
B23: Total | I23: =SUM(I21:I22) -> 0
B25: Concrete works
B26: Foundation
B27: Footing or raft | C27: m3 | D27: 1 | E27: 1 | F27: 32.1 | G27: 23.43 | H27: 0.8 | J27: =875+(121*0.1)+(33*0.1) -> 890.4 | K27: 875 | L27: 121 | M27: 120 | P27: 0.1 | Q27: 0.1 | R27: =(((F27+Q27*2)*(G27+Q27*2))*P27)*E27*D27 -> 76.3249 | S27: =((J27*P27)*E27*D27) -> 89.04 | T27: =((((F27+Q27*2)+(G27+Q27*2))*2)*P27)*E27*D27 -> 11.186 | U27: =((L27*P27)*E27*D27) -> 12.1 | V27: =(((F27*G27*H27)*E27*D27)) -> 601.6824 | W27: =((K27*H27)*E27*D27) -> 700 | X27: =((F27*2+G27*2)*H27)*E27*D27 -> 88.848 | Y27: =((M27*H27)*E27*D27) -> 96 | Z27: =(R27/P27)+(S27/P27) -> 1653.649 | AA27: =(T27*2+U27*2) -> 46.572 | AD27: =(((F27*G27)*E27*D27))+K27 -> 1627.103 | AE27: =(X27+Y27) -> 184.848 | AF27: =AD27 -> 1627.103
B28: lift pit concrete section 5-5 | C28: m3 | D28: 1 | E28: 1
B29: lift pit concrete section 6-6 | C29: m3 | D29: 1 | E29: 1
B31: Total | R31: =SUM(R27:R30) -> 76.3249 | S31: =SUM(S27:S30) -> 89.04 | T31: =SUM(T27:T30) -> 11.186 | U31: =SUM(U27:U30) -> 12.1 | V31: =SUM(V27:V30) -> 601.6824 | W31: =SUM(W27:W30) -> 700 | X31: =SUM(X27:X30) -> 88.848 | Y31: =SUM(Y27:Y30) -> 96 | ... AA31: =SUM(AA27:AA30) -> 46.572 | AD31: =SUM(AD27:AD30) -> 1627.103 | AE31: =SUM(AE27:AE30) -> 184.848 | AF31: =SUM(AF27:AF30) -> 1627.103 | AH31: =SUM(AH27:AH30) -> 0 | AI31: =SUM(AI27:AI30) -> 0 | AK31: =SUM(AK27:AK30) -> 0 | AL31: =SUM(AL27:AL30) -> 0
B33: Stub column or pedestals
B35: Column
B36: C1 | C36: m3 | D36: 1 | E36: 11 | F36: 0.4 | G36: 0.8 | H36: =$H$8-$H$27 -> 6.15 | I36: =PRODUCT(D36:G36) -> 3.52 | V36: =PRODUCT(D36:H36) -> 21.648 | W36: =((K36*H36)*E36*D36) -> 0 | X36: =((F36*2+G36*2)*H36)*E36*D36 -> 162.36 | Y36: =((M36*H36)*E36*D36) -> 0 | AE36: =(X36+Y36) -> 162.36 | AF36: =(V36/H36)+(W36/H36) -> 3.52 | AH36: =(G36*2)*E36*D36 -> 17.6 | AI36: =(M36*E36*D36) -> 0
B37: C2 | C37: m3 | D37: 1 | E37: 7 | F37: 0.4 | G37: 0.8 | H37: =$H$8-$H$27 -> 6.15 | I37: =PRODUCT(D37:G37) -> 2.24 | V37: =PRODUCT(D37:H37) -> 13.776 | W37: =((K37*H37)*E37*D37) -> 0 | X37: =((F37*2+G37*2)*H37)*E37*D37 -> 103.32 | Y37: =((M37*H37)*E37*D37) -> 0 | AE37: =(X37+Y37) -> 103.32 | AF37: =(V37/H37)+(W37/H37) -> 2.24 | AH37: =(G37*2)*E37*D37 -> 11.2 | AI37: =(M37*E37*D37) -> 0
B38: C3 | C38: m3 | D38: 1 | E38: 2 | F38: 0.4 | G38: 0.9 | H38: =$H$8-$H$27 -> 6.15 | I38: =PRODUCT(D38:G38) -> 0.72 | V38: =PRODUCT(D38:H38) -> 4.428 | W38: =((K38*H38)*E38*D38) -> 0 | X38: =((F38*2+G38*2)*H38)*E38*D38 -> 31.98 | Y38: =((M38*H38)*E38*D38) -> 0 | AF38: =(V38/H38)+(W38/H38) -> 0.72
B39: C4 | C39: m3 | D39: 1 | E39: 2 | F39: 0.4 | G39: 0.75 | H39: =$H$8-$H$27 -> 6.15 | I39: =PRODUCT(D39:G39) -> 0.6 | V39: =PRODUCT(D39:H39) -> 3.69 | W39: =((K39*H39)*E39*D39) -> 0 | X39: =((F39*2+G39*2)*H39)*E39*D39 -> 28.29 | Y39: =((M39*H39)*E39*D39) -> 0 | AF39: =(V39/H39)+(W39/H39) -> 0.6
B40: C5 | C40: m3 | D40: 1 | E40: 6 | F40: 0.5 | G40: 0.9 | H40: =$H$8-$H$27 -> 6.15 | I40: =PRODUCT(D40:G40) -> 2.7 | V40: =PRODUCT(D40:H40) -> 16.605 | W40: =((K40*H40)*E40*D40) -> 0 | X40: =((F40*2+G40*2)*H40)*E40*D40 -> 103.32 | Y40: =((M40*H40)*E40*D40) -> 0 | AF40: =(V40/H40)+(W40/H40) -> 2.7
B41: C* | C41: m3 | D41: 1 | E41: 2 | F41: 0.4 | G41: 0.4 | H41: =$H$8-$H$27 -> 6.15 | I41: =PRODUCT(D41:G41) -> 0.32 | V41: =PRODUCT(D41:H41) -> 1.968 | W41: =((K41*H41)*E41*D41) -> 0 | X41: =((F41*2+G41*2)*H41)*E41*D41 -> 19.68 | Y41: =((M41*H41)*E41*D41) -> 0 | AF41: =(V41/H41)+(W41/H41) -> 0.32
B43: Total | E43: =SUM(E36:E42) -> 30 | R43: =SUM(R36:R42) -> 0 | S43: =SUM(S36:S42) -> 0 | T43: =SUM(T36:T42) -> 0 | U43: =SUM(U36:U42) -> 0 | V43: =SUM(V36:V42) -> 62.115 | W43: =SUM(W36:W42) -> 0 | X43: =SUM(X36:X42) -> 448.95 | Y43: =SUM(Y36:Y42) -> 0 | ... AA43: =SUM(AA36:AA42) -> 0 | AD43: =SUM(AD36:AD42) -> 0 | AE43: =SUM(AE36:AE42) -> 265.68 | AF43: =SUM(AF36:AF42) -> 10.1 | AH43: =SUM(AH36:AH42) -> 28.8 | AI43: =SUM(AI36:AI42) -> 0 | AK43: =SUM(AK36:AK42) -> 0 | AL43: =SUM(AL36:AL42) -> 0
B45: Stub column of GF
B47: Column
B48: C1 | C48: m3 | D48: 1 | E48: 11 | F48: 0.4 | G48: 0.8 | H48: =4.65-0.3 -> 4.35 | I48: =PRODUCT(D48:G48) -> 3.52 | V48: =PRODUCT(D48:H48) -> 15.312 | W48: =((K48*H48)*E48*D48) -> 0 | X48: =((F48*2+G48*2)*H48)*E48*D48 -> 114.84 | Y48: =((M48*H48)*E48*D48) -> 0 | AE48: =(X48+Y48) -> 114.84 | AF48: =(V48/H48)+(W48/H48) -> 3.52 | AH48: =(G48*2)*E48*D48 -> 17.6 | AI48: =(M48*E48*D48) -> 0
B49: C2 | C49: m3 | D49: 1 | E49: 7 | F49: 0.4 | G49: 0.8 | H49: =4.65-0.3 -> 4.35 | I49: =PRODUCT(D49:G49) -> 2.24 | V49: =PRODUCT(D49:H49) -> 9.744 | W49: =((K49*H49)*E49*D49) -> 0 | X49: =((F49*2+G49*2)*H49)*E49*D49 -> 73.08 | Y49: =((M49*H49)*E49*D49) -> 0 | AE49: =(X49+Y49) -> 73.08 | AF49: =(V49/H49)+(W49/H49) -> 2.24 | AH49: =(G49*2)*E49*D49 -> 11.2 | AI49: =(M49*E49*D49) -> 0
B50: C3 | C50: m3 | D50: 1 | E50: 2 | F50: 0.4 | G50: 0.9 | H50: =4.65-0.3 -> 4.35 | I50: =PRODUCT(D50:G50) -> 0.72 | V50: =PRODUCT(D50:H50) -> 3.132 | W50: =((K50*H50)*E50*D50) -> 0 | X50: =((F50*2+G50*2)*H50)*E50*D50 -> 22.62 | Y50: =((M50*H50)*E50*D50) -> 0 | AF50: =(V50/H50)+(W50/H50) -> 0.72
B51: C4 | C51: m3 | D51: 1 | E51: 2 | F51: 0.4 | G51: 0.75 | H51: =4.65-0.3 -> 4.35 | I51: =PRODUCT(D51:G51) -> 0.6 | V51: =PRODUCT(D51:H51) -> 2.61 | W51: =((K51*H51)*E51*D51) -> 0 | X51: =((F51*2+G51*2)*H51)*E51*D51 -> 20.01 | Y51: =((M51*H51)*E51*D51) -> 0 | AF51: =(V51/H51)+(W51/H51) -> 0.6
B52: C5 | C52: m3 | D52: 1 | E52: 6 | F52: 0.5 | G52: 0.9 | H52: =4.65-0.3 -> 4.35 | I52: =PRODUCT(D52:G52) -> 2.7 | V52: =PRODUCT(D52:H52) -> 11.745 | W52: =((K52*H52)*E52*D52) -> 0 | X52: =((F52*2+G52*2)*H52)*E52*D52 -> 73.08 | Y52: =((M52*H52)*E52*D52) -> 0 | AF52: =(V52/H52)+(W52/H52) -> 2.7
B53: C* | C53: m3 | D53: 1 | E53: 2 | F53: 0.4 | G53: 0.4 | H53: =4.65-0.3 -> 4.35 | I53: =PRODUCT(D53:G53) -> 0.32 | V53: =PRODUCT(D53:H53) -> 1.392 | W53: =((K53*H53)*E53*D53) -> 0 | X53: =((F53*2+G53*2)*H53)*E53*D53 -> 13.92 | Y53: =((M53*H53)*E53*D53) -> 0 | AF53: =(V53/H53)+(W53/H53) -> 0.32
B55: Total | E55: =SUM(E48:E54) -> 30 | R55: =SUM(R48:R54) -> 0 | S55: =SUM(S48:S54) -> 0 | T55: =SUM(T48:T54) -> 0 | U55: =SUM(U48:U54) -> 0 | V55: =SUM(V48:V54) -> 43.935 | W55: =SUM(W48:W54) -> 0 | X55: =SUM(X48:X54) -> 317.55 | Y55: =SUM(Y48:Y54) -> 0 | ... AA55: =SUM(AA48:AA54) -> 0 | AD55: =SUM(AD48:AD54) -> 0 | AE55: =SUM(AE48:AE54) -> 187.92 | AF55: =SUM(AF48:AF54) -> 10.1 | AH55: =SUM(AH48:AH54) -> 28.8 | AI55: =SUM(AI48:AI54) -> 0 | AK55: =SUM(AK48:AK54) -> 0 | AL55: =SUM(AL48:AL54) -> 0
B57: Stub column of 1st to PH
B59: Column
B60: C1 | C60: m3 | D60: 6 | E60: 11 | F60: 0.4 | G60: 0.8 | H60: =3.6-0.3 -> 3.3 | I60: =PRODUCT(D60:G60) -> 21.12 | V60: =PRODUCT(D60:H60) -> 69.696 | W60: =((K60*H60)*E60*D60) -> 0 | X60: =((F60*2+G60*2)*H60)*E60*D60 -> 522.72 | Y60: =((M60*H60)*E60*D60) -> 0 | AE60: =(X60+Y60) -> 522.72 | AF60: =(V60/H60)+(W60/H60) -> 21.12 | AH60: =(G60*2)*E60*D60 -> 105.6 | AI60: =(M60*E60*D60) -> 0
B61: C2 | C61: m3 | D61: 6 | E61: 7 | F61: 0.4 | G61: 0.8 | H61: =3.6-0.3 -> 3.3 | I61: =PRODUCT(D61:G61) -> 13.44 | V61: =PRODUCT(D61:H61) -> 44.352 | W61: =((K61*H61)*E61*D61) -> 0 | X61: =((F61*2+G61*2)*H61)*E61*D61 -> 332.64 | Y61: =((M61*H61)*E61*D61) -> 0 | AE61: =(X61+Y61) -> 332.64 | AF61: =(V61/H61)+(W61/H61) -> 13.44 | AH61: =(G61*2)*E61*D61 -> 67.2 | AI61: =(M61*E61*D61) -> 0
B62: C3 | C62: m3 | D62: 6 | E62: 2 | F62: 0.4 | G62: 0.9 | H62: =3.6-0.3 -> 3.3 | I62: =PRODUCT(D62:G62) -> 4.32 | V62: =PRODUCT(D62:H62) -> 14.256 | W62: =((K62*H62)*E62*D62) -> 0 | X62: =((F62*2+G62*2)*H62)*E62*D62 -> 102.96 | Y62: =((M62*H62)*E62*D62) -> 0 | AF62: =(V62/H62)+(W62/H62) -> 4.32
B63: C4 | C63: m3 | D63: 6 | E63: 2 | F63: 0.4 | G63: 0.75 | H63: =3.6-0.3 -> 3.3 | I63: =PRODUCT(D63:G63) -> 3.6 | V63: =PRODUCT(D63:H63) -> 11.88 | W63: =((K63*H63)*E63*D63) -> 0 | X63: =((F63*2+G63*2)*H63)*E63*D63 -> 91.08 | Y63: =((M63*H63)*E63*D63) -> 0 | AF63: =(V63/H63)+(W63/H63) -> 3.6
B64: C5 | C64: m3 | D64: 6 | E64: 6 | F64: 0.5 | G64: 0.9 | H64: =3.6-0.3 -> 3.3 | I64: =PRODUCT(D64:G64) -> 16.2 | V64: =PRODUCT(D64:H64) -> 53.46 | W64: =((K64*H64)*E64*D64) -> 0 | X64: =((F64*2+G64*2)*H64)*E64*D64 -> 332.64 | Y64: =((M64*H64)*E64*D64) -> 0 | AF64: =(V64/H64)+(W64/H64) -> 16.2
B65: C* | C65: m3 | D65: 6 | E65: 2 | F65: 0.4 | G65: 0.4 | H65: =3.6-0.3 -> 3.3 | I65: =PRODUCT(D65:G65) -> 1.92 | V65: =PRODUCT(D65:H65) -> 6.336 | W65: =((K65*H65)*E65*D65) -> 0 | X65: =((F65*2+G65*2)*H65)*E65*D65 -> 63.36 | Y65: =((M65*H65)*E65*D65) -> 0 | AF65: =(V65/H65)+(W65/H65) -> 1.92
B67: Total | E67: =SUM(E60:E66) -> 30 | R67: =SUM(R60:R66) -> 0 | S67: =SUM(S60:S66) -> 0 | T67: =SUM(T60:T66) -> 0 | U67: =SUM(U60:U66) -> 0 | V67: =SUM(V60:V66) -> 199.98 | W67: =SUM(W60:W66) -> 0 | X67: =SUM(X60:X66) -> 1445.4 | Y67: =SUM(Y60:Y66) -> 0 | ... AA67: =SUM(AA60:AA66) -> 0 | AD67: =SUM(AD60:AD66) -> 0 | AE67: =SUM(AE60:AE66) -> 855.36 | AF67: =SUM(AF60:AF66) -> 60.6 | AH67: =SUM(AH60:AH66) -> 172.8 | AI67: =SUM(AI60:AI66) -> 0 | AK67: =SUM(AK60:AK66) -> 0 | AL67: =SUM(AL60:AL66) -> 0
B69: Stub column of 1.5m
B71: Column
B72: C1 | C72: m3 | D72: 6 | E72: 11 | F72: 0.4 | G72: 0.8 | H72: 1.5 | I72: =PRODUCT(D72:G72) -> 21.12 | V72: =PRODUCT(D72:H72) -> 31.68 | W72: =((K72*H72)*E72*D72) -> 0 | X72: =((F72*2+G72*2)*H72)*E72*D72 -> 237.6 | Y72: =((M72*H72)*E72*D72) -> 0 | AE72: =(X72+Y72) -> 237.6 | AF72: =(V72/H72)+(W72/H72) -> 21.12 | AH72: =(G72*2)*E72*D72 -> 105.6 | AI72: =(M72*E72*D72) -> 0
B73: C2 | C73: m3 | D73: 6 | E73: 7 | F73: 0.4 | G73: 0.8 | H73: 1.5 | I73: =PRODUCT(D73:G73) -> 13.44 | V73: =PRODUCT(D73:H73) -> 20.16 | W73: =((K73*H73)*E73*D73) -> 0 | X73: =((F73*2+G73*2)*H73)*E73*D73 -> 151.2 | Y73: =((M73*H73)*E73*D73) -> 0 | AE73: =(X73+Y73) -> 151.2 | AF73: =(V73/H73)+(W73/H73) -> 13.44 | AH73: =(G73*2)*E73*D73 -> 67.2 | AI73: =(M73*E73*D73) -> 0
B74: C3 | C74: m3 | D74: 6 | E74: 2 | F74: 0.4 | G74: 0.9 | H74: 1.5 | I74: =PRODUCT(D74:G74) -> 4.32 | V74: =PRODUCT(D74:H74) -> 6.48 | W74: =((K74*H74)*E74*D74) -> 0 | X74: =((F74*2+G74*2)*H74)*E74*D74 -> 46.8 | Y74: =((M74*H74)*E74*D74) -> 0 | AF74: =(V74/H74)+(W74/H74) -> 4.32
B75: C4 | C75: m3 | D75: 6 | E75: 2 | F75: 0.4 | G75: 0.75 | H75: 1.5 | I75: =PRODUCT(D75:G75) -> 3.6 | V75: =PRODUCT(D75:H75) -> 5.4 | W75: =((K75*H75)*E75*D75) -> 0 | X75: =((F75*2+G75*2)*H75)*E75*D75 -> 41.4 | Y75: =((M75*H75)*E75*D75) -> 0 | AF75: =(V75/H75)+(W75/H75) -> 3.6
B76: C5 | C76: m3 | D76: 6 | E76: 6 | F76: 0.5 | G76: 0.9 | H76: 1.5 | I76: =PRODUCT(D76:G76) -> 16.2 | V76: =PRODUCT(D76:H76) -> 24.3 | W76: =((K76*H76)*E76*D76) -> 0 | X76: =((F76*2+G76*2)*H76)*E76*D76 -> 151.2 | Y76: =((M76*H76)*E76*D76) -> 0 | AF76: =(V76/H76)+(W76/H76) -> 16.2
B77: C* | C77: m3 | D77: 6 | E77: 2 | F77: 0.4 | G77: 0.4 | H77: 1.5 | I77: =PRODUCT(D77:G77) -> 1.92 | V77: =PRODUCT(D77:H77) -> 2.88 | W77: =((K77*H77)*E77*D77) -> 0 | X77: =((F77*2+G77*2)*H77)*E77*D77 -> 28.8 | Y77: =((M77*H77)*E77*D77) -> 0 | AF77: =(V77/H77)+(W77/H77) -> 1.92
B79: Total | E79: =SUM(E72:E78) -> 30 | R79: =SUM(R72:R78) -> 0 | S79: =SUM(S72:S78) -> 0 | T79: =SUM(T72:T78) -> 0 | U79: =SUM(U72:U78) -> 0 | V79: =SUM(V72:V78) -> 90.9 | W79: =SUM(W72:W78) -> 0 | X79: =SUM(X72:X78) -> 657 | Y79: =SUM(Y72:Y78) -> 0 | ... AA79: =SUM(AA72:AA78) -> 0 | AD79: =SUM(AD72:AD78) -> 0 | AE79: =SUM(AE72:AE78) -> 388.8 | AF79: =SUM(AF72:AF78) -> 60.6 | AH79: =SUM(AH72:AH78) -> 172.8 | AI79: =SUM(AI72:AI78) -> 0 | AK79: =SUM(AK72:AK78) -> 0 | AL79: =SUM(AL72:AL78) -> 0
B82: RCC Wall Up to Grade Slab
B83: 12080X6150X250 mm
B84: 250mm thk wall W1 | C84: m3 | D84: 1 | E84: 1 | F84: =12080/1000 -> 12.08 | G84: 0.2 | H84: 5.85 | V84: =PRODUCT(D84:H84) -> 14.1336 | W84: =((K84*H84)*E84*D84) -> 0 | X84: =((F84*2+G84*2)*H84)*E84*D84 -> 143.676 | Y84: =((M84*H84)*E84*D84) -> 0 | AE84: =(X84+Y84) -> 143.676 | AF84: =(V84/H84)+(W84/H84) -> 2.416
B85: 250mm thk wall W2 | C85: m3 | D85: 1 | E85: 2 | F85: 2.25 | G85: 0.2 | H85: 5.85 | V85: =PRODUCT(D85:H85) -> 5.265 | W85: =((K85*H85)*E85*D85) -> 0 | X85: =((F85*2+G85*2)*H85)*E85*D85 -> 57.33 | Y85: =((M85*H85)*E85*D85) -> 0 | AE85: =(X85+Y85) -> 57.33 | AF85: =(V85/H85)+(W85/H85) -> 0.9
B86: 250mm thk wall W3 | C86: m3 | D86: 1 | E86: 1 | F86: 13.8 | G86: 0.2 | H86: 5.85 | V86: =PRODUCT(D86:H86) -> 16.146 | W86: =((K86*H86)*E86*D86) -> 0 | X86: =((F86*2+G86*2)*H86)*E86*D86 -> 163.8 | Y86: =((M86*H86)*E86*D86) -> 0 | AE86: =(X86+Y86) -> 163.8 | AF86: =(V86/H86)+(W86/H86) -> 2.76
B87: Deduction | C87: m3 | D87: 1 | F87: 2.6 | G87: 0.2 | H87: 0.6 | V87: =PRODUCT(D87:H87) -> 0.312 | W87: =((K87*H87)*E87*D87) -> 0 | X87: =((F87*2+G87*2)*H87)*E87*D87 -> 0 | Y87: =((M87*H87)*E87*D87) -> 0 | AE87: =(X87+Y87) -> 0 | AF87: =(V87/H87)+(W87/H87) -> 0.52
B89: Total | R89: =SUM(R83:R88) -> 0 | S89: =SUM(S83:S88) -> 0 | T89: =SUM(T83:T88) -> 0 | U89: =SUM(U83:U88) -> 0 | V89: =SUM(V83:V88) -> 35.8566 | W89: =SUM(W83:W88) -> 0 | X89: =SUM(X83:X88) -> 364.806 | Y89: =SUM(Y83:Y88) -> 0 | ... AA89: =SUM(AA83:AA88) -> 0 | AD89: =SUM(AD83:AD88) -> 0 | AE89: =SUM(AE83:AE88) -> 364.806 | AF89: =SUM(AF83:AF88) -> 6.596 | AK89: =SUM(AK83:AK88) -> 0 | AL89: =SUM(AL83:AL88) -> 0
B93: RCC Wall
B94: 12080X6150X250 mm
B95: 250mm thk wall W1 | C95: m3 | D95: 1 | E95: 1 | F95: =12080/1000 -> 12.08 | G95: 0.2 | H95: =36.1-5.85 -> 30.25 | V95: =PRODUCT(D95:H95) -> 73.084 | W95: =((K95*H95)*E95*D95) -> 0 | X95: =((F95*2+G95*2)*H95)*E95*D95 -> 742.94 | Y95: =((M95*H95)*E95*D95) -> 0 | AE95: =(X95+Y95) -> 742.94 | AF95: =(V95/H95)+(W95/H95) -> 2.416
B96: 250mm thk wall W2 | C96: m3 | D96: 1 | E96: 2 | F96: 2.25 | G96: 0.2 | H96: =33.3-0.2-5.85 -> 27.25 | V96: =PRODUCT(D96:H96) -> 24.525 | W96: =((K96*H96)*E96*D96) -> 0 | X96: =((F96*2+G96*2)*H96)*E96*D96 -> 267.05 | Y96: =((M96*H96)*E96*D96) -> 0 | AE96: =(X96+Y96) -> 267.05 | AF96: =(V96/H96)+(W96/H96) -> 0.9
B97: 250mm thk wall W3 | C97: m3 | D97: 1 | E97: 1 | F97: 13.8 | G97: 0.2 | H97: =36.1-5.85 -> 30.25 | V97: =PRODUCT(D97:H97) -> 83.49 | W97: =((K97*H97)*E97*D97) -> 0 | X97: =((F97*2+G97*2)*H97)*E97*D97 -> 847 | Y97: =((M97*H97)*E97*D97) -> 0 | AE97: =(X97+Y97) -> 847 | AF97: =(V97/H97)+(W97/H97) -> 2.76
B98: Deduction | C98: m3 | D98: 1 | F98: 2.6 | G98: 0.2 | H98: 0.6 | V98: =PRODUCT(D98:H98) -> 0.312 | W98: =((K98*H98)*E98*D98) -> 0 | X98: =((F98*2+G98*2)*H98)*E98*D98 -> 0 | Y98: =((M98*H98)*E98*D98) -> 0 | AE98: =(X98+Y98) -> 0 | AF98: =(V98/H98)+(W98/H98) -> 0.52
B100: Total | R100: =SUM(R94:R99) -> 0 | S100: =SUM(S94:S99) -> 0 | T100: =SUM(T94:T99) -> 0 | U100: =SUM(U94:U99) -> 0 | V100: =SUM(V94:V99) -> 181.411 | W100: =SUM(W94:W99) -> 0 | X100: =SUM(X94:X99) -> 1856.99 | Y100: =SUM(Y94:Y99) -> 0 | ... AA100: =SUM(AA94:AA99) -> 0 | AD100: =SUM(AD94:AD99) -> 0 | AE100: =SUM(AE94:AE99) -> 1856.99 | AF100: =SUM(AF94:AF99) -> 6.596 | AK100: =SUM(AK94:AK99) -> 0 | AL100: =SUM(AL94:AL99) -> 0
B103: Retaining Wall
B104: 300 mm
B105: 300mm thk wall | C105: m3 | D105: 1 | E105: 2 | F105: 31.5 | G105: 0.3 | H105: =6.95-0.8-0.3 -> 5.85 | V105: =PRODUCT(D105:H105) -> 110.565 | W105: =((K105*H105)*E105*D105) -> 0 | X105: =((F105*2+G105*2)*H105)*E105*D105 -> 744.12 | Y105: =((M105*H105)*E105*D105) -> 0 | AE105: =(X105+Y105) -> 744.12 | AF105: =(V105/H105)+(W105/H105) -> 18.9
B106: 300mm thk wall | C106: m3 | D106: 1 | E106: 2 | F106: 23.43 | G106: 0.3 | H106: =6.95-0.8-0.3 -> 5.85 | V106: =PRODUCT(D106:H106) -> 82.2393 | W106: =((K106*H106)*E106*D106) -> 0 | X106: =((F106*2+G106*2)*H106)*E106*D106 -> 555.282 | Y106: =((M106*H106)*E106*D106) -> 0 | AE106: =(X106+Y106) -> 555.282 | AF106: =(V106/H106)+(W106/H106) -> 14.058
B107: Deduction | C107: m3 | D107: 0 | E107: 0 | F107: 2.6 | G107: 0.2 | H107: 0.6 | V107: =PRODUCT(D107:H107) -> 0 | W107: =((K107*H107)*E107*D107) -> 0 | X107: =((F107*2+G107*2)*H107)*E107*D107 -> 0 | Y107: =((M107*H107)*E107*D107) -> 0 | AE107: =(X107+Y107) -> 0 | AF107: =(V107/H107)+(W107/H107) -> 0
B109: Total | R109: =SUM(R104:R108) -> 0 | S109: =SUM(S104:S108) -> 0 | T109: =SUM(T104:T108) -> 0 | U109: =SUM(U104:U108) -> 0 | V109: =SUM(V104:V108) -> 192.8043 | W109: =SUM(W104:W108) -> 0 | X109: =SUM(X104:X108) -> 1299.402 | Y109: =SUM(Y104:Y108) -> 0 | ... AA109: =SUM(AA104:AA108) -> 0 | AD109: =SUM(AD104:AD108) -> 0 | AE109: =SUM(AE104:AE108) -> 1299.402 | AF109: =SUM(AF104:AF108) -> 32.958 | AK109: =SUM(AK104:AK108) -> 0 | AL109: =SUM(AL104:AL108) -> 0
B112: Plinth beam
B113: Externally | AB113: EXT lvl AVG | AC113: GS thk | AJ113: Depth
B114: PB1-250X700mm | C114: m3 | D114: 1 | E114: 1 | F114: 4.2 | G114: 0.25 | H114: =0.7-0.1 -> 0.6 | I114: =PRODUCT(D114:G114) -> 1.05 | P114: 0 | Q114: 0 | R114: =(((F114)*(G114+Q114*2))*P114)*E114*D114 -> 0 | S114: =((J114*P114)*E114*D114) -> 0 | T114: =((F114*P114)*2)*D114*E114 -> 0 | U114: =((L114*P114)*E114*D114) -> 0 | V114: =PRODUCT(D114:H114) -> 0.63 | W114: =(K114*H114)*E114*D114 -> 0 | X114: =((F114)*(H114*2))*E114*D114 -> 5.04 | Y114: =((M114)*H114)*E114*D114 -> 0 | Z114: =(R114/P114)+(S114/P114) -> #DIV/0! | AA114: =(T114+U114) -> 0 | AB114: 0.15 | AC114: 0.15 | AD114: =(((F114*G114)*E114*D114))+K114 -> 1.05 | AE114: =(((F114*(H114-AB114))+(F114*(H114-AC114)))*E114*D114)+Y114 -> 3.78 | AF114: =AD114 -> 1.05 | AH114: =F114*E114*D114 -> 4.2 | AJ114: =$H$8-0.1-H114+0.3 -> 6.55 | AK114: =((F114*AJ114)*E114*D114) -> 27.51
B115: PB1-250X700mm | C115: m3 | D115: 1 | E115: 2 | F115: 6.8 | G115: 0.25 | H115: =0.7-0.1 -> 0.6 | I115: =PRODUCT(D115:G115) -> 3.4 | P115: 0 | Q115: 0 | R115: =(((F115)*(G115+Q115*2))*P115)*E115*D115 -> 0 | S115: =((J115*P115)*E115*D115) -> 0 | T115: =((F115*P115)*2)*D115*E115 -> 0 | U115: =((L115*P115)*E115*D115) -> 0 | V115: =PRODUCT(D115:H115) -> 2.04 | W115: =(K115*H115)*E115*D115 -> 0 | X115: =((F115)*(H115*2))*E115*D115 -> 16.32 | Y115: =((M115)*H115)*E115*D115 -> 0 | Z115: =(R115/P115)+(S115/P115) -> #DIV/0! | AA115: =(T115+U115) -> 0 | AB115: 0.15 | AC115: 0.15 | AD115: =(((F115*G115)*E115*D115))+K115 -> 3.4 | AE115: =(((F115*(H115-AB115))+(F115*(H115-AC115)))*E115*D115)+Y115 -> 12.24 | AF115: =AD115 -> 3.4 | AH115: =F115*E115*D115 -> 13.6 | AJ115: =$H$8-0.1-H115+0.3 -> 6.55 | AK115: =((F115*AJ115)*E115*D115) -> 89.08
B116: PB1-250X700mm | C116: m3 | D116: 1 | E116: 2 | F116: 0.95 | G116: 0.25 | H116: =0.7-0.1 -> 0.6 | I116: =PRODUCT(D116:G116) -> 0.475 | P116: 0 | Q116: 0 | R116: =(((F116)*(G116+Q116*2))*P116)*E116*D116 -> 0 | S116: =((J116*P116)*E116*D116) -> 0 | T116: =((F116*P116)*2)*D116*E116 -> 0 | U116: =((L116*P116)*E116*D116) -> 0 | V116: =PRODUCT(D116:H116) -> 0.285 | W116: =(K116*H116)*E116*D116 -> 0 | X116: =((F116)*(H116*2))*E116*D116 -> 2.28 | Y116: =((M116)*H116)*E116*D116 -> 0 | Z116: =(R116/P116)+(S116/P116) -> #DIV/0! | AA116: =(T116+U116) -> 0 | AB116: 0.15 | AC116: 0.15 | AD116: =(((F116*G116)*E116*D116))+K116 -> 0.475 | AE116: =(((F116*(H116-AB116))+(F116*(H116-AC116)))*E116*D116)+Y116 -> 1.71 | AF116: =AD116 -> 0.475 | AH116: =F116*E116*D116 -> 1.9 | AJ116: =$H$8-0.1-H116+0.3 -> 6.55 | AK116: =((F116*AJ116)*E116*D116) -> 12.445
B117: PB1-250X700mm | C117: m3 | D117: 1 | E117: 2 | F117: 1 | G117: 0.25 | H117: =0.7-0.1 -> 0.6 | I117: =PRODUCT(D117:G117) -> 0.5 | P117: 0 | Q117: 0 | R117: =(((F117)*(G117+Q117*2))*P117)*E117*D117 -> 0 | S117: =((J117*P117)*E117*D117) -> 0 | T117: =((F117*P117)*2)*D117*E117 -> 0 | U117: =((L117*P117)*E117*D117) -> 0 | V117: =PRODUCT(D117:H117) -> 0.3 | W117: =(K117*H117)*E117*D117 -> 0 | X117: =((F117)*(H117*2))*E117*D117 -> 2.4 | Y117: =((M117)*H117)*E117*D117 -> 0 | Z117: =(R117/P117)+(S117/P117) -> #DIV/0! | AA117: =(T117+U117) -> 0 | AB117: 0.15 | AC117: 0.15 | AD117: =(((F117*G117)*E117*D117))+K117 -> 0.5 | AE117: =(((F117*(H117-AB117))+(F117*(H117-AC117)))*E117*D117)+Y117 -> 1.8 | AF117: =AD117 -> 0.5 | AH117: =F117*E117*D117 -> 2 | AJ117: =$H$8-0.1-H117+0.3 -> 6.55 | AK117: =((F117*AJ117)*E117*D117) -> 13.1
B118: PB1-250X700mm | C118: m3 | D118: 1 | E118: 2 | F118: 1.1 | G118: 0.25 | H118: =0.7-0.1 -> 0.6 | I118: =PRODUCT(D118:G118) -> 0.55 | P118: 0 | Q118: 0 | R118: =(((F118)*(G118+Q118*2))*P118)*E118*D118 -> 0 | S118: =((J118*P118)*E118*D118) -> 0 | T118: =((F118*P118)*2)*D118*E118 -> 0 | U118: =((L118*P118)*E118*D118) -> 0 | V118: =PRODUCT(D118:H118) -> 0.33 | W118: =(K118*H118)*E118*D118 -> 0 | X118: =((F118)*(H118*2))*E118*D118 -> 2.64 | Y118: =((M118)*H118)*E118*D118 -> 0 | Z118: =(R118/P118)+(S118/P118) -> #DIV/0! | AA118: =(T118+U118) -> 0 | AB118: 0.15 | AC118: 0.15 | AD118: =(((F118*G118)*E118*D118))+K118 -> 0.55 | AE118: =(((F118*(H118-AB118))+(F118*(H118-AC118)))*E118*D118)+Y118 -> 1.98 | AF118: =AD118 -> 0.55 | AH118: =F118*E118*D118 -> 2.2 | AJ118: =$H$8-0.1-H118+0.3 -> 6.55 | AK118: =((F118*AJ118)*E118*D118) -> 14.41
B119: PB2-400X700mm | C119: m3 | D119: 1 | E119: 4 | F119: 2.2 | G119: 0.4 | H119: =0.7-0.1 -> 0.6 | I119: =PRODUCT(D119:G119) -> 3.52 | P119: 0 | Q119: 0 | R119: =(((F119)*(G119+Q119*2))*P119)*E119*D119 -> 0 | S119: =((J119*P119)*E119*D119) -> 0 | T119: =((F119*P119)*2)*D119*E119 -> 0 | U119: =((L119*P119)*E119*D119) -> 0 | V119: =PRODUCT(D119:H119) -> 2.112 | W119: =(K119*H119)*E119*D119 -> 0 | X119: =((F119)*(H119*2))*E119*D119 -> 10.56 | Y119: =((M119)*H119)*E119*D119 -> 0 | Z119: =(R119/P119)+(S119/P119) -> #DIV/0! | AA119: =(T119+U119) -> 0 | AB119: 0.15 | AC119: 0.15 | AD119: =(((F119*G119)*E119*D119))+K119 -> 3.52 | AE119: =(((F119*(H119-AB119))+(F119*(H119-AC119)))*E119*D119)+Y119 -> 7.92 | AF119: =AD119 -> 3.52 | AH119: =F119*E119*D119 -> 8.8 | AJ119: =$H$8-0.1-H119+0.3 -> 6.55 | AK119: =((F119*AJ119)*E119*D119) -> 57.64
B120: PB2-400X700mm | C120: m3 | D120: 1 | E120: 1 | F120: 6.79 | G120: 0.4 | H120: =0.7-0.1 -> 0.6 | I120: =PRODUCT(D120:G120) -> 2.716 | P120: 0 | Q120: 0 | R120: =(((F120)*(G120+Q120*2))*P120)*E120*D120 -> 0 | S120: =((J120*P120)*E120*D120) -> 0 | T120: =((F120*P120)*2)*D120*E120 -> 0 | U120: =((L120*P120)*E120*D120) -> 0 | V120: =PRODUCT(D120:H120) -> 1.6296 | W120: =(K120*H120)*E120*D120 -> 0 | X120: =((F120)*(H120*2))*E120*D120 -> 8.148 | Y120: =((M120)*H120)*E120*D120 -> 0 | Z120: =(R120/P120)+(S120/P120) -> #DIV/0! | AA120: =(T120+U120) -> 0 | AB120: 0.15 | AC120: 0.15 | AD120: =(((F120*G120)*E120*D120))+K120 -> 2.716 | AE120: =(((F120*(H120-AB120))+(F120*(H120-AC120)))*E120*D120)+Y120 -> 6.111 | AF120: =AD120 -> 2.716 | AH120: =F120*E120*D120 -> 6.79 | AJ120: =$H$8-0.1-H120+0.3 -> 6.55 | AK120: =((F120*AJ120)*E120*D120) -> 44.4745
B121: PB2-400X700mm | C121: m3 | D121: 1 | E121: 1 | F121: 6.64 | G121: 0.4 | H121: =0.7-0.1 -> 0.6 | I121: =PRODUCT(D121:G121) -> 2.656 | P121: 0 | Q121: 0 | R121: =(((F121)*(G121+Q121*2))*P121)*E121*D121 -> 0 | S121: =((J121*P121)*E121*D121) -> 0 | T121: =((F121*P121)*2)*D121*E121 -> 0 | U121: =((L121*P121)*E121*D121) -> 0 | V121: =PRODUCT(D121:H121) -> 1.5936 | W121: =(K121*H121)*E121*D121 -> 0 | X121: =((F121)*(H121*2))*E121*D121 -> 7.968 | Y121: =((M121)*H121)*E121*D121 -> 0 | Z121: =(R121/P121)+(S121/P121) -> #DIV/0! | AA121: =(T121+U121) -> 0 | AB121: 0.15 | AC121: 0.15 | AD121: =(((F121*G121)*E121*D121))+K121 -> 2.656 | AE121: =(((F121*(H121-AB121))+(F121*(H121-AC121)))*E121*D121)+Y121 -> 5.976 | AF121: =AD121 -> 2.656 | AH121: =F121*E121*D121 -> 6.64 | AJ121: =$H$8-0.1-H121+0.3 -> 6.55 | AK121: =((F121*AJ121)*E121*D121) -> 43.492
B122: PB2-400X700mm | C122: m3 | D122: 1 | E122: 2 | F122: 3.4 | G122: 0.4 | H122: =0.7-0.1 -> 0.6 | I122: =PRODUCT(D122:G122) -> 2.72 | P122: 0 | Q122: 0 | R122: =(((F122)*(G122+Q122*2))*P122)*E122*D122 -> 0 | S122: =((J122*P122)*E122*D122) -> 0 | T122: =((F122*P122)*2)*D122*E122 -> 0 | U122: =((L122*P122)*E122*D122) -> 0 | V122: =PRODUCT(D122:H122) -> 1.632 | W122: =(K122*H122)*E122*D122 -> 0 | X122: =((F122)*(H122*2))*E122*D122 -> 8.16 | Y122: =((M122)*H122)*E122*D122 -> 0 | Z122: =(R122/P122)+(S122/P122) -> #DIV/0! | AA122: =(T122+U122) -> 0 | AB122: 0.15 | AC122: 0.15 | AD122: =(((F122*G122)*E122*D122))+K122 -> 2.72 | AE122: =(((F122*(H122-AB122))+(F122*(H122-AC122)))*E122*D122)+Y122 -> 6.12 | AF122: =AD122 -> 2.72 | AH122: =F122*E122*D122 -> 6.8 | AJ122: =$H$8-0.1-H122+0.3 -> 6.55 | AK122: =((F122*AJ122)*E122*D122) -> 44.54
B124: Internally
B125: PB1-200X600mm | C125: m3 | D125: 0 | E125: 0 | F125: 0 | G125: 0 | H125: 0 | P125: 0 | Q125: 0 | R125: =(((F125)*(G125+Q125*2))*P125)*E125*D125 -> 0 | S125: =((J125*P125)*E125*D125) -> 0 | T125: =((F125*P125)*2)*D125*E125 -> 0 | U125: =((L125*P125)*E125*D125) -> 0 | V125: =PRODUCT(D125:H125) -> 0 | W125: =(K125*H125)*E125*D125 -> 0 | X125: =((F125)*(H125*2))*E125*D125 -> 0 | Y125: =((M125)*H125)*E125*D125 -> 0 | Z125: =(R125/P125)+(S125/P125) -> #DIV/0! | AA125: =(T125+U125) -> 0 | AB125: 0.15 | AC125: 0.15 | AD125: =(((F125*G125)*E125*D125))+K125 -> 0 | AE125: =(((F125*(H125-AC125))+(F125*(H125-AC125)))*E125*D125)+Y125 -> 0 | AF125: =AD125 -> 0 | AH125: =(F125*2)*E125*D125 -> 0 | AJ125: 0 | AL125: =((F125*AJ125)*E125*D125) -> 0
B127: Total | R127: =SUM(R114:R126) -> 0 | S127: =SUM(S114:S126) -> 0 | T127: =SUM(T114:T126) -> 0 | U127: =SUM(U114:U126) -> 0 | V127: =SUM(V114:V126) -> 10.5522 | W127: =SUM(W114:W126) -> 0 | X127: =SUM(X114:X126) -> 63.516 | Y127: =SUM(Y114:Y126) -> 0 | ... AA127: =SUM(AA114:AA126) -> 0 | AD127: =SUM(AD114:AD126) -> 17.587 | AE127: =SUM(AE114:AE126) -> 47.637 | AF127: =SUM(AF114:AF126) -> 17.587 | AH127: =SUM(AH114:AH126) -> 52.93 | AI127: =SUM(AI114:AI126) -> 0 | AK127: =SUM(AK114:AK126) -> 346.6915 | AL127: =SUM(AL114:AL126) -> 0
B129: 100mm thick grade slab
B130: over all plinth area | C130: m3 | D130: 1 | E130: 1 | F130: 31.5 | G130: 23.51 | H130: 0.1 | I130: =PRODUCT(D130:H130) -> 74.0565 | J130: =PRODUCT(D130:G130) -> 740.565 | K130: 0 | P130: 0 | R130: =((F130*G130)*P130)*E130*D130 -> 0 | S130: =(J130*P130)*E130*D130 -> 0 | V130: =PRODUCT(D130:H130) -> 74.0565 | W130: =((K130*H130)*E130*D130) -> 0 | Z130: =(R130/P130)+(S130/P130) -> #DIV/0! | AH130: =AH127 -> 52.93 | AI130: =AI127 -> 0 | AM130: =((F130*G130)*E130*D130) -> 740.565 | AN130: =((K130)*E130*D130) -> 0
B131: Deduction of plinth area | C131: m3 | D131: 0 | E131: 0 | H131: 0 | J131: =(15.29+0.69+29.45+15.79+16.5+36.13+30.95+23.16+7.15+45.09)*-1 -> -220.2 | P131: 0 | R131: =((F131*G131)*P131)*E131*D131 -> 0 | S131: =(J131*P131)*E131*D131 -> 0 | V131: =PRODUCT(D131:H131) -> 0 | W131: =((K131*H131)*E131*D131) -> 0 | Z131: =(R131/P131)+(S131/P131) -> #DIV/0! | AH131: =AH128 -> 0 | AI131: =AI128 -> 0 | AM131: =((F131*G131)*E131*D131) -> 0 | AN131: =((K131)*E131*D131) -> 0
B132: Deduction of Column area | C132: m3 | D132: 0 | E132: 0 | H132: 0 | J132: =-1.22 -> -1.22 | K132: =AF128 -> 0 | P132: 0 | R132: =((F132*G132)*P132)*E132*D132 -> 0 | S132: =(J132*P132)*E132*D132 -> 0 | V132: =PRODUCT(D132:H132) -> 0 | W132: =((K132*H132)*E132*D132) -> 0 | Z132: =(R132/P132)+(S132/P132) -> #DIV/0! | AH132: =AH43 -> 28.8 | AI132: =AI43 -> 0 | AM132: =((F132*G132)*E132*D132) -> 0 | AN132: =((K132)*E132*D132) -> 0
B136: Total | R136: =SUM(R130:R135) -> 0 | S136: =SUM(S130:S135) -> 0 | T136: =SUM(T130:T135) -> 0 | U136: =SUM(U130:U135) -> 0 | V136: =SUM(V130:V135) -> 74.0565 | W136: =SUM(W130:W135) -> 0 | X136: =SUM(X130:X135) -> 0 | Y136: =SUM(Y130:Y135) -> 0 | ... AA136: =SUM(AA130:AA135) -> 0 | AD136: =SUM(AD130:AD135) -> 0 | AE136: =SUM(AE130:AE135) -> 0 | AF136: =SUM(AF130:AF135) -> 0 | AH136: =SUM(AH130:AH135) -> 81.73 | AI136: =SUM(AI130:AI135) -> 0 | AK136: =SUM(AK130:AK135) -> 0 | AL136: =SUM(AL130:AL135) -> 0 | AM136: =SUM(AM130:AM135) -> 740.565 | AN136: =SUM(AN130:AN135) -> 0
B137: Total stair volume
B138: Sections
...

Sheet Bill No. 4 Ancillary
A2: BILL NO. 4 - ANCILLARY
C3: Holding Tank
A4: ITEM | B4: ITEM DESCRIPTION | E4: QTY. | F4: UNIT | G4: RATE | H4: AMOUNT | J4: Calculated Qty
A5: REF. | H5: ( R.O. )
C7: CIVIL WORKS
C8: Holding tank & Fire Tank
C9: Concrete Work
C10: SRC reinforced pre-mixed cement concrete, Grade 40N/mm² as specified including placing, vibrating, curing and cube tests, etc.,
A12: A | C12: Base, wall, slab | E12: =J12 -> 47.92625 | F12: m3 | G12: 19.75 | H12: =+G12*E12 -> 946.54344 | J12: =M.S!I296+M.S!I297+M.S!I302+M.S!I303 -> 47.92625
C14: Formwork
A15: B | C15: Base, wall, slab | E15: =J15 -> 33.757 | F15: m2 | G15: 2 | H15: =+G15*E15 -> 67.514 | J15: =M.S!X299+M.S!X305 -> 33.757
C17: Reinforcement Works
C18: High yield steel deformed bar reinforcement BS 4449 (Grade Fe 500) of all including cutting, bending, fixing in position, binding wire, chairs, spacers, extra bars at cutouts/opening and protection against rusting etc as per structural drawing and schedule
A20: C | C20: 8mm - 32mm diameter bars | E20: =J20 -> 4914.756 | F20: Kgs | G20: 0.295 | H20: =+G20*E20 -> 1449.853 | J20: =4680.72*1.05 -> 4914.756
C22: Moisture Protection
C23: External between two RCC for floor and wall
A24: D | C24: Waterproofing and filler board | E24: =J24 -> 33.757 | F24: m2 | G24: 3.6 | H24: =+G24*E24 -> 121.5252 | J24: =M.S!AE299+M.S!AE305 -> 33.757
C26: internally waterproofing to holding tank
A27: E | C27: internal waterproofing to holding tank | E27: =J27 -> 33.757 | F27: m2 | G27: 2 | H27: =+G27*E27 -> 67.514 | J27: =J24 -> 33.757
A29: F | C29: Water bars | E29: =J29 -> 34.42 | F29: m | G29: 2 | H29: =+G29*E29 -> 68.84 | J29: =4.05*2+3.98*4+5.2*2 -> 34.42
A31: G | C31: Manhole cover | E31: =J31 -> 4 | F31: No | G31: 45 | H31: =+G31*E31 -> 180 | J31: 4
C32: To Collection | G32: R.O.
H33: =SUM(H6:H32) -> 2901.7897
C34: TOTAL FOR BILL NO.4 ANCILLARY- CARRIED TO GENERAL SUMMARY | G34: R.O.
H35: =+H33 -> 2901.7897

Sheet Bill No.5 Electrical & ELV
A2: BILL NO. 5 - Electrical & ELV
A4: ITEM | B4: ITEM DESCRIPTION | E4: QTY. | F4: UNIT | G4: RATE | H4: AMOUNT
A5: REF. | H5: ( R.O. )
C7: ELECTRICAL INSTALLATION
C9: MAINS INSTALLATIONS
C11: SUB MAINS INSTALLATIONS
C13: Supply and install LV panels with control gear, as specified, complete with volt selection switches, voltmeters, indicator lamps , all as shown on drawings. Complete all in accordance with standard OES-4 specifications.
A15: 1 | C15: Feeder pillar | E15: 1 | F15: Nr. | H15: =G15*E15 -> 0
A17: 2 | C17: MDB -1 | E17: 1 | F17: Nr. | G17: 1857 | H17: =G17*E17 -> 1857
A19: 3 | C19: MDB -2 | E19: 1 | F19: Nr. | G19: 1307 | H19: =G19*E19 -> 1307
A21: 4 | C21: MDB -3 | E21: 1 | F21: Nr. | G21: 1203 | H21: =G21*E21 -> 1203
C23: EARTHING
A25: 1 | C25: Earthing as per MEDC sandard ,as specified to LV power supply and distribution installtion including necessary accessories (Civil work not included) | E25: 1 | F25: L/S | G25: 150 | H25: =G25*E25 -> 150
A27: 2 | C27: Rubber mat for Electrical room | E27: 1 | F27: L/S | G27: 80 | H27: =G27*E27 -> 80
C28: To Collection
C29: To Collection | G29: R.O. | H29: =SUM(H14:H28) -> 4597
C31: ELECTRICAL INSTALLATION (CONT'D.)
C32: Supply and install quipment and control gear, as specified and detailed on drawing. Including cable (not measured separately) & cable terminations, cable trays from proposed panel to Distribution Board Complete all in accordance with drawings and standard OES-4 specifications.
C33: Distribution Board
C34: GROUND FLOOR
A36: 1 | C36: DB GC - 16 WAY TPN | E36: 1 | F36: Nr. | H36: =G36*E36 -> 0
A38: 2 | C38: DB SH 1 - 14 WAY SPN | E38: 1 | F38: Nr. | H38: =G38*E38 -> 0
A40: 3 | C40: DB SH 2 - 14 WAY SPN | E40: 1 | F40: Nr. | H40: =G40*E40 -> 0
A42: 4 | C42: DB SH 3 - 14 WAY SPN | E42: 1 | F42: Nr. | H42: =G42*E42 -> 0
A44: 5 | C44: DB SH 4 - 14 WAY SPN | E44: 1 | F44: Nr. | H44: =G44*E44 -> 0
A46: 6 | C46: DB SH 5 - 14 WAY SPN | E46: 1 | F46: Nr. | H46: =G46*E46 -> 0
A48: 7 | C48: DB SH 6 - 14 WAY SPN | E48: 1 | F48: Nr. | H48: =G48*E48 -> 0
A50: 8 | C50: DB SH 7 - 14 WAY SPN | E50: 1 | F50: Nr. | H50: =G50*E50 -> 0
A52: 9 | C52: DB SH 8 - 14 WAY SPN | E52: 1 | F52: Nr. | H52: =G52*E52 -> 0
A54: 10 | C54: DB SH 9 - 14 WAY SPN | E54: 1 | F54: Nr. | H54: =G54*E54 -> 0
A56: 11 | C56: DB SH 10 - 14 WAY SPN | E56: 1 | F56: Nr. | H56: =G56*E56 -> 0
A58: 12 | C58: DB SH 11 - 14 WAY SPN | E58: 1 | F58: Nr. | H58: =G58*E58 -> 0
... A70: 18 | C70: DB SH 17 - 14 WAY SPN | E70: 1 | F70: Nr. | H70: =G70*E70 -> 0
C72: FIRST FLOOR TO FIFTH FLOOR
A74: 1 | C74: DB-1F1 - 16 WAY SPN (TYP) | E74: 5 | F74: Nr. | H74: =SUM(G74*E74) -> 0
A76: 2 | C76: DB-1F2 - 16 WAY SPN (TYP) | E76: 5 | F76: Nr. | H76: =SUM(G76*E76) -> 0
A78: 3 | C78: DB-1F3 - 16 WAY SPN (TYP) | E78: 5 | F78: Nr. | H78: =SUM(G78*E78) -> 0
A80: 4 | C80: DB-1F4 - 16 WAY SPN (TYP) | E80: 5 | F80: Nr. | H80: =SUM(G80*E80) -> 0
A82: 5 | C82: DB-1F5 - 16 WAY SPN (TYP) | E82: 5 | F82: Nr. | H82: =SUM(G82*E82) -> 0
A84: 6 | C84: DB-1F6 - 16 WAY SPN (TYP) | E84: 5 | F84: Nr. | H84: =SUM(G84*E84) -> 0
A86: 7 | C86: DB-1F7 - 8 WAY TPN (TYP) | E86: 5 | F86: Nr. | H86: =SUM(G86*E86) -> 0
A88: 8 | C88: DB-1F8 - 8 WAY TPN (TYP) | E88: 5 | F88: Nr. | H88: =SUM(G88*E88) -> 0
A90: 9 | C90: DB-1F9 - 8 WAY TPN (TYP) | E90: 5 | F90: Nr. | H90: =SUM(G90*E90) -> 0
C92: To Collection
C93: To Collection | G93: R.O. | H93: =SUM(H34:H92) -> 0
C94: PENT HOUSE FLOOR
A96: 1 | C96: DB-PF1 - 8 WAY TPN | E96: 1 | F96: Nr. | H96: =SUM(G96*E96) -> 0
A98: 2 | C98: DB-PF2 - 8 WAY TPN | E98: 1 | F98: Nr. | H98: =SUM(G98*E98) -> 0
A100: 3 | C100: DB-PF3 - 8 WAY TPN | E100: 1 | F100: Nr. | H100: =SUM(G100*E100) -> 0
A102: 4 | C102: DB-PF4 - 8 WAY TPN | E102: 1 | F102: Nr. | H102: =SUM(G102*E102) -> 0
A104: 5 | C104: DB-PF5 - 8 WAY TPN | E104: 1 | F104: Nr. | H104: =SUM(G104*E104) -> 0
A106: 6 | C106: DB-PF6 - 8 WAY TPN | E106: 1 | F106: Nr. | H106: =SUM(G106*E106) -> 0
A108: 7 | C108: DB-PF7 - 8 WAY TPN | E108: 1 | F108: Nr. | H108: =SUM(G108*E108) -> 0
A109: 8 | C109: DB-PF8 - 8 WAY TPN | E109: 1 | F109: Nr. | H109: =SUM(G109*E109) -> 0
A110: 9 | C110: DB-PF9 - 8 WAY TPN | E110: 1 | F110: Nr. | H110: =SUM(G110*E110) -> 0
C111: To Collection
C112: To Collection | G112: R.O. | H112: 7337
C114: ELECTRICAL INSTALLATION (CONT'D.)
C116: LV CABLES
C118: Conductors and Cables
C120: Power supply distribution copper cables with earth continuity cable surface fixed in cable ladders/ trays / direct burried in ground / laid in iPVC ducts with approved supports or/and laid in floor service trenches, as specified to complete installation with terminations at both ends; complete all as specified and detailed on drawings and specification.
C121: FROM FEEDER PILLAR
A122: 1 | C122: 4C X 240 sqmm XLPE/SWA/PVC/Cu Cable + 1C X 120 sqmm ECC from Feeder Pillar to MDB-01,02 & 03 | E122: 200 | F122: M | G122: 38 | H122: =G122*E122 -> 7600
C124: DISTRIBUTION CABLES
C125: FROM MDB - 01
A126: 1 | C126: 4C X 25 SQMM XLPE Cable + 1C X 16 SQMM Y/G ECC for DB-GC | E126: =5+3+5 -> 13 | F126: M | G126: 8.7 | H126: =G126*E126 -> 113.1
A128: 2 | C128: 4C X 25 SQMM XLPE Cable + 1C X 16 SQMM Y/G ECC for Mech. Parking | E128: =9+5+20 -> 34 | F128: M | G128: 8.7 | H128: =G128*E128 -> 295.8
A130: 3 | C130: 4C X 16 SQMM XLPE Cable + 1C X 16 SQMM Y/G ECC for Lift 1 & 2 | E130: =(23+5+2+5+5+5+5+5+5+5)*2 -> 130 | F130: M | G130: 4.5 | H130: =G130*E130 -> 585
A132: 4 | C132: 4C X 10 SQMM XLPE Cable + 1C X 10 SQMM Y/G ECC for Fire Pump | E132: =5+5+5 -> 15 | F132: M | G132: 3.5 | H132: =G132*E132 -> 52.5
A134: 5 | C134: 4C X 6 SQMM XLPE Cable + 1C X 6 SQMM Y/G ECC for Tran. Pump | E134: =5+5+5+5 -> 20 | F134: M | G134: 3.27 | H134: =G134*E134 -> 65.4
A136: 6 | C136: 4C X 4 SQMM XLPE Cable + 1C X 4 SQMM Y/G ECC for Booster Pump | E136: =18+5+5+5+5+5+5+5+5+5 -> 63 | F136: M | G136: 2.56 | H136: =G136*E136 -> 161.28
A138: 7 | C138: 2C X 35 sqmm XLPE/PVC/Cu Cable + 1C X 16 sqmm Y/G ECC for DB-SH1 | E138: =8+5 -> 13 | F138: M | G138: 6.65 | H138: =G138*E138 -> 86.45
A140: 8 | C140: 2C X 35 sqmm XLPE/PVC/Cu Cable + 1C X 16 sqmm Y/G ECC for DB-SH2 | E140: =15+5 -> 20 | F140: M | G140: 6.65 | H140: =G140*E140 -> 133
A142: 9 | C142: 2C X 35 sqmm XLPE/PVC/Cu Cable + 1C X 16 sqmm Y/G ECC for DB-SH3 | E142: =9+5 -> 14 | F142: M | G142: 6.65 | H142: =G142*E142 -> 93.1
A144: 10 | C144: 2C X 35 sqmm XLPE/PVC/Cu Cable + 1C X 16 sqmm Y/G ECC for DB-SH4 | E144: =13+5 -> 18 | F144: M | G144: 6.65 | H144: =G144*E144 -> 119.7
A146: 11 | C146: 2C X 35 sqmm XLPE/PVC/Cu Cable + 1C X 16 sqmm Y/G ECC for DB-SH5 | E146: =16+5 -> 21 | F146: M | G146: 6.65 | H146: =G146*E146 -> 139.65
A148: 12 | C148: 2C X 35 sqmm XLPE/PVC/Cu Cable + 1C X 16 sqmm Y/G ECC for DB-SH6 | E148: =19+5 -> 24 | F148: M | G148: 6.65 | H148: =G148*E148 -> 159.6
A150: 13 | C150: 2C X 35 sqmm XLPE/PVC/Cu Cable + 1C X 16 sqmm Y/G ECC for DB-SH7 | E150: =22+5 -> 27 | F150: M | G150: 6.65 | H150: =G150*E150 -> 179.55
A152: 14 | C152: 2C X 35 sqmm XLPE/PVC/Cu Cable + 1C X 16 sqmm Y/G ECC for DB-SH8 | E152: =28+5 -> 33 | F152: M | G152: 6.65 | H152: =G152*E152 -> 219.45
A154: 15 | C154: 2C X 35 sqmm XLPE/PVC/Cu Cable + 1C X 16 sqmm Y/G ECC for DB-SH9 | E154: =35+5 -> 40 | F154: M | G154: 6.65 | H154: =G154*E154 -> 266
A156: 16 | C156: 2C X 35 sqmm XLPE/PVC/Cu Cable + 1C X 16 sqmm Y/G ECC for DB-SH10 | E156: =25+5 -> 30 | F156: M | G156: 6.65 | H156: =G156*E156 -> 199.5
A158: 17 | C158: 2C X 35 sqmm XLPE/PVC/Cu Cable + 1C X 16 sqmm Y/G ECC for DB-SH11 | E158: =30+5 -> 35 | F158: M | G158: 6.65 | H158: =G158*E158 -> 232.75
A160: 18 | C160: 2C X 35 sqmm XLPE/PVC/Cu Cable + 1C X 16 sqmm Y/G ECC for DB-SH12 | E160: =27+5 -> 32 | F160: M | G160: 6.65 | H160: =G160*E160 -> 212.8
A162: 19 | C162: 2C X 35 sqmm XLPE/PVC/Cu Cable + 1C X 16 sqmm Y/G ECC for DB-SH13 | E162: =27+5 -> 32 | F162: M | G162: 6.65 | H162: =G162*E162 -> 212.8
A164: 20 | C164: 2C X 35 sqmm XLPE/PVC/Cu Cable + 1C X 16 sqmm Y/G ECC for DB-SH14 | E164: =23+5 -> 28 | F164: M | G164: 6.65 | H164: =G164*E164 -> 186.2
A166: 21 | C166: 2C X 35 sqmm XLPE/PVC/Cu Cable + 1C X 16 sqmm Y/G ECC for DB-SH15 | E166: =18+5 -> 23 | F166: M | G166: 6.65 | H166: =G166*E166 -> 152.95
A168: 22 | C168: 2C X 35 sqmm XLPE/PVC/Cu Cable + 1C X 16 sqmm Y/G ECC for DB-SH16 | E168: =15+5 -> 20 | F168: M | G168: 6.65 | H168: =G168*E168 -> 133
A170: 23 | C170: 2C X 35 sqmm XLPE/PVC/Cu Cable + 1C X 16 sqmm Y/G ECC for DB-SH17 | E170: =11+5 -> 16 | F170: M | G170: 6.65 | H170: =G170*E170 -> 106.4
A172: 24 | C172: 2C X 35 sqmm XLPE/PVC/Cu Cable + 1C X 16 sqmm Y/G ECC for DB-1F1 | E172: =11+5+5 -> 21 | F172: M | G172: 6.65 | H172: =G172*E172 -> 139.65
A174: 25 | C174: 2C X 35 sqmm XLPE/PVC/Cu Cable + 1C X 16 sqmm Y/G ECC for DB-1F2 | E174: =11+5+5 -> 21 | F174: M | G174: 6.65 | H174: =G174*E174 -> 139.65
A176: 26 | C176: 2C X 35 sqmm XLPE/PVC/Cu Cable + 1C X 16 sqmm Y/G ECC for DB-1F3 | E176: =23+5+2+5 -> 35 | F176: M | G176: 6.65 | H176: =G176*E176 -> 232.75
A178: 27 | C178: 2C X 35 sqmm XLPE/PVC/Cu Cable + 1C X 16 sqmm Y/G ECC for DB-1F4 | E178: =28+5+5 -> 38 | F178: M | G178: 6.65 | H178: =G178*E178 -> 252.7
A180: 28 | C180: 2C X 35 sqmm XLPE/PVC/Cu Cable + 1C X 16 sqmm Y/G ECC for DB-1F5 | E180: =28+5+5 -> 38 | F180: M | G180: 6.65 | H180: =G180*E180 -> 252.7
A182: 29 | C182: 2C X 35 sqmm XLPE/PVC/Cu Cable + 1C X 16 sqmm Y/G ECC for DB-1F6 | E182: =28+5+5 -> 38 | F182: M | G182: 6.65 | H182: =G182*E182 -> 252.7
A184: 30 | C184: 4C X 25 SQMM XLPE Cable + 1C X 16 SQMM Y/G ECC for DB-1F7 | E184: =31+5+5 -> 41 | F184: M | G184: 8.7 | H184: =G184*E184 -> 356.7
A186: 31 | C186: 4C X 25 SQMM XLPE Cable + 1C X 16 SQMM Y/G ECC for DB-1F8 | E186: =22+5+4+5 -> 36 | F186: M | G186: 8.7 | H186: =G186*E186 -> 313.2
A188: 32 | C188: 4C X 25 SQMM XLPE Cable + 1C X 16 SQMM Y/G ECC for DB-1F9 | E188: =18+5+5 -> 28 | F188: M | G188: 8.7 | H188: =G188*E188 -> 243.6
A190: 33 | C190: 2C X 35 sqmm XLPE/PVC/Cu Cable + 1C X 16 sqmm Y/G ECC for DB-2F1 | E190: =11+5+5+5 -> 26 | F190: M | G190: 6.65 | H190: =G190*E190 -> 172.9
A192: 34 | C192: 2C X 35 sqmm XLPE/PVC/Cu Cable + 1C X 16 sqmm Y/G ECC for DB-2F2 | E192: =11+5+5+5 -> 26 | F192: M | G192: 6.65 | H192: =G192*E192 -> 172.9
C193: To Collection
...

Sheet Bill No.6 Plumbing
A2: BILL NO. 6 - Plumbing Installations
A4: ITEM | B4: ITEM DESCRIPTION | E4: QTY. | F4: UNIT | G4: RATE | H4: AMOUNT
A5: REF. | H5: ( R.O. )
C7: PLUMBING INSTALLATIONS
C9: DRAINAGE INSTALLATIONS
C11: DRAINAGE PIPING (BM & GF)
C13: Supply, install; Unplasticized Polyvinyl chloride (uPVC) pipe; above ground confirming to BS 4514 for above ground and BS 4660 for below ground piping including all supports fittings, markings, excavation, bedding, backfilling, concrete encasement (where required).
A15: 1 | C15: 200 mm diameter SP | E15: =6*1.5 -> 9 | F15: M | G15: 2.7 | H15: =G15*E15 -> 24.3
A17: 2 | C17: 200 mm diameter WP | E17: =6*1.5 -> 9 | F17: M | G17: 2.7 | H17: =G17*E17 -> 24.3
A19: 3 | C19: 110 mm diameter SP | E19: =57*1.5 -> 85.5 | F19: M | G19: 0.5 | H19: =G19*E19 -> 42.75
A21: 4 | C21: 110 mm diameter WP | E21: =65*1.5 -> 97.5 | F21: M | G21: 0.5 | H21: =G21*E21 -> 48.75
A23: 5 | C23: 110 mm Roding Eye | E23: =10*1.5 -> 15 | F23: Nr | G23: 0.6 | H23: =G23*E23 -> 9
C25: STORM WATER SYSTEM
C26: Supply, install; Unplasticized Polyvinyl chloride (uPVC) pipe; above ground confirming to BS 4514 for above groundBS 4660 for below ground piping including all supports fittings, markings, excavation, bedding, backfilling, concrete encasement (where required).
A28: 1 | C28: 110 mm diameter (BM) | E28: =14*1.5 -> 21 | F28: M | G28: 0.6 | H28: =G28*E28 -> 12.6
A30: 2 | C30: 300 mm HD DI Chanel grating | E30: =15+9 -> 24 | F30: M | G30: 10 | H30: =G30*E30 -> 240
C31: To Collection
C32: To Collection | G32: R.O. | H32: =SUM(H6:H31) -> 401.7
C34: RAIN WATER SYSTEM
C35: Supply, install; Unplasticized Polyvinyl chloride (uPVC) pipe; above ground confirming to BS 4514 for above ground including all supports fittings, markings, excavation, bedding, backfilling, concrete encasement (where required).
A37: 1 | C37: 110 mm diameter RWP | E37: =20*1.5 -> 30 | F37: M | G37: 1.325 | H37: =G37*E37 -> 39.75
A39: 2 | C39: Rain water Outlet 110mm | E39: 4 | F39: Nr | G39: 8 | H39: =G39*E39 -> 32
C41: SUMP PUMP
A43: 1 | C43: 25m3/hr @20m Head Duty/ Assist | E43: 1 | F43: Set | G43: 1400 | H43: =G43*E43 -> 1400
A45: 2 | C45: 110 mm Hpvc pipes and fittings | E45: 6 | F45: M | G45: 1.8 | H45: =G45*E45 -> 10.8
C47: DRAINAGE SYSTEM (SOIL & WASTE LINES)
C49: Supply, install; Unplasticized Polyvinyl chloride (uPVC) pipe; above ground confirming to BS 4514 for above groundBS 4660 for below ground piping including all supports fittings, markings, excavation, bedding, backfilling, concrete encasement (where required).
A51: 1 | C51: 160 mm diameter (GF & External) | E51: =97*1.1 -> 106.7 | F51: M | G51: 1.325 | H51: =G51*E51 -> 141.3775
A53: 2 | C53: 110 mm diameter SVP | E53: =25*2*6 -> 300 | F53: M | G53: 0.5 | H53: =G53*E53 -> 150
A55: 3 | C55: 110 mm diameter WVP | E55: =30*2*6+20 -> 380 | F55: M | G55: 0.5 | H55: =G55*E55 -> 190
A57: 4 | C57: 82 mm diameter WVP | E57: =16*2*6 -> 192 | F57: M | G57: 0.141 | H57: =G57*E57 -> 27.072
A59: 5 | C59: 55 mm diameter WVP | E59: =17*2*6 -> 204 | F59: M | G59: 0.083 | H59: =G59*E59 -> 16.932
A61: 6 | C61: 160 mm Roding Eye | E61: =11*1.25 -> 13.75 | F61: Nr | G61: 0.457 | H61: =G61*E61 -> 6.28375
A63: 7 | C63: 110 mm Roding Eye | E63: =4+26*6*1.1 -> 175.6 | F63: Nr | G63: 0.6 | H63: =G63*E63 -> 105.36
A65: 8 | C65: 82 mm Roding Eye | E65: =8*6*1.1 -> 52.8 | F65: Nr | G65: 0.3 | H65: =G65*E65 -> 15.84
A67: 9 | C67: 110 mm Vent Cowl | E67: =17*2*1.25 -> 42.5 | F67: Nr | G67: 0.4 | H67: =G67*E67 -> 17
C68: To Collection
C69: To Collection | G69: R.O. | H69: =SUM(H35:H68) -> 2152.4153
C71: HOLDING TANK INSTALLATION
A73: 1 | C73: 110 mm diameter HDPE Pipe (BOWSER) | E73: 7 | F73: M | G73: 2 | H73: =G73*E73 -> 14
A75: 2 | C75: 110mm End connetor for suking line | E75: 1 | F75: Nr | G75: 1 | H75: =G75*E75 -> 1
C77: DRAINAGE INSTALLATIONS
A79: 1 | C79: 4" X 4" FT Grating SS 316 | E79: =39*6*1.1 -> 257.4 | G79: 8 | H79: =G79*E79 -> 2059.2
C81: ACOUSTIC PIPE INSULATION
A83: 1 | C83: High level Drainage pipes at Ground floor only | E83: 183 | F83: M | G83: 3.5 | H83: =G83*E83 -> 640.5
C84: To Collection
C85: To Collection | G85: R.O. | H85: =SUM(H71:H84) -> 2714.7
C86: SANITARY WARE
C87: Supply of the following sanitary ware and accessories including providing and fixing of angle valves as necessary, brackets, fixing bolts and the like and connecting to pipe work as per specifications.
A88: 1 | C88: EWC assembly, floor mounted type, complete with seat, including flush valve assembly and installation. | E88: =24*6*1.1 -> 158.4 | F88: Nr. | G88: 35 | H88: =G88*E88 -> 5544
A89: 2 | C89: 1/2" 2 feet Flexible & 1/2" x 1/2" Angle valve | E89: =24*2*6*1.1 -> 316.8 | F89: Nr. | G89: 1.7 | H89: =G89*E89 -> 538.56
A90: 3 | C90: SS Kitchen sink single bowl and drain excluding upper cabinet base top cabin units all fittings & doors | E90: =9*6*1.1 -> 59.4 | F90: Nr. | G90: 36 | H90: =G90*E90 -> 2138.4
A91: 4 | C91: 1/2" x 1/2" Angle Valve | E91: =33*6*1.1 -> 217.8 | F91: Nr. | G91: 1.7 | H91: =G91*E91 -> 370.26
A92: 5 | C92: Kitchen sink 11/2" bottle trap | E92: =9*6*1.1 -> 59.4 | F92: Nr. | G92: 1.8 | H92: =G92*E92 -> 106.92
A93: 6 | C93: Shower mixer with head | E93: =13*6*1.1 -> 85.8 | F93: Nr. | G93: 30 | H93: =G93*E93 -> 2574
A94: 7 | C94: 30ltr water Heater | E94: =9*6*1.1 -> 59.4 | F94: Nr. | G94: 38 | H94: =G94*E94 -> 2257.2
A95: 8 | C95: 50ltr water Heater | E95: =14*6*1.1 -> 92.4 | F95: Nr. | G95: 55 | H95: =G95*E95 -> 5082
A96: 9 | C96: 1/2" 2 feet Flexible & 1/2" x 1/2" Angle valve | E96: =24*2*6*1.1 -> 316.8 | F96: Nr. | G96: 1.54 | H96: =G96*E96 -> 487.872
A97: 10 | C97: Towell Rod | E97: =24*6*1.1 -> 158.4 | F97: Nr. | G97: 9.8 | H97: =G97*E97 -> 1552.32
A98: 11 | C98: Paper Towel | E98: =24*6*1.1 -> 158.4 | F98: Nr. | H98: =G98*E98 -> 0
A99: 12 | C99: Toilet paper Holder | E99: =24*6*1.1 -> 158.4 | F99: Nr. | G99: 6.7 | H99: =G99*E99 -> 1061.28
A100: 13 | C100: Glass shelf | E100: =24*6*1.1 -> 158.4 | F100: Nr. | G100: 12.6 | H100: =G100*E100 -> 1995.84
A101: 14 | C101: Soap dispenser | E101: =24*6*1.1 -> 158.4 | F101: Nr. | G101: 12.5 | H101: =G101*E101 -> 1980
A102: 15 | C102: Mirror 600x800mm | E102: =24*6*1.1 -> 158.4 | F102: Nr. | G102: 12 | H102: =G102*E102 -> 1900.8
A103: 16 | C103: 1/2" Bip tap | E103: =11*6*1.1 -> 72.6 | F103: Nr. | G103: 15 | H103: =G103*E103 -> 1089
C104: To Collection
C105: To Collection | G105: R.O. | H105: =SUM(H88:H103) -> 28678.452
C106: PLUMBING INSTALLATIONS (Cont'd)
C107: HOT & COLD WATER/PPR PIPE INSTALLATIONS
C109: Supply and install PPR Pipes type 3 DIN 8076,8077 & 8078 including fittings , non return valve , supports , and other necessary accessories.
C110: (Ground floor , Typical floor,shaft and Roof)
A112: A | C112: 20 mm diameter pipe (CWS) | E112: =24*6*1.5 -> 216 | F112: M | G112: 1.12 | H112: =G112*E112 -> 241.92
A114: B | C114: 25 mm diameter pipe (CWS) | E114: =82*6*1.5 -> 738 | F114: M | G114: 1.165 | H114: =G114*E114 -> 859.77
A116: C | C116: 25 mm diameter pipe (HWS) | E116: =77*6*1.5 -> 693 | F116: M | G116: 1.165 | H116: =G116*E116 -> 807.345
A118: D | C118: 32 mm diameter pipe (CWS) | E118: =32*6*1.5 -> 288 | F118: M | G118: 1.882 | H118: =G118*E118 -> 542.016
C120: Gate Valves and accessories as specified
A122: A | C122: 20 mm diameter pipe | E122: =16*6*1.1 -> 105.6 | F122: Nr. | G122: 1.12 | H122: =G122*E122 -> 118.272
A124: B | C124: 25 mm diameter pipe | E124: =32*6*1.1 -> 211.2 | F124: Nr. | G124: 1.165 | H124: =G124*E124 -> 246.048
A126: C | C126: 32 mm diameter pipe | E126: =22*6*1.1 -> 145.2 | F126: Nr. | G126: 1.882 | H126: =G126*E126 -> 273.2664
C127: To Collection
C128: To Collection | G128: R.O. | H128: =SUM(H111:H127) -> 3088.6374
C130: PLUMBING INSTALLATIONS (Cont'd)
C132: COLD WATER/MMS PIPE INSTALLATIONS
C134: Cold water system inside building
A136: 1 | C136: 75mm diameter PPR Main line from BM Water tank to Roof | E136: 35 | F136: M | G136: 1.1 | H136: =G136*E136 -> 38.5
A138: 2 | C138: 75MM PPR Gate valve & Accessories | E138: 2 | F138: Nr. | G138: 3 | H138: =G138*E138 -> 6
C140: Bowser and PAW line
A142: 1 | C142: 75mm diameter HPVC Main & Bowser fill line from BM Water tank to Roof | E142: =27*2+8*2 -> 70 | F142: M | G142: 1.1 | H142: =G142*E142 -> 77 | I142: =27*2+8*2 -> 70
C144: Gate Valves and accessories as specified
A146: 1 | C146: 54mm diameter GV | E146: 2 | F146: Nr. | G146: 1.3 | H146: =G146*E146 -> 2.6
A148: 2 | C148: 75mm diameter GV | E148: 2 | F148: Nr. | G148: 1.6 | H148: =G148*E148 -> 3.2
C149: To Collection
C150: To Collection | G150: R.O. | H150: =SUM(H131:H149) -> 127.3
C151: WATER METER (Main)
A153: 1 | C153: Supply and fixing of bulk water meter including necessary accessories | E153: 1 | F153: Nr. | H153: =G153*E153 -> 0
A155: 2 | C155: 1/2" Garden tap (Roof) | E155: 2 | F155: Nr. | G155: 1 | H155: =G155*E155 -> 2
C157: WATER METER
A159: 1 | C159: Supply and fixing of water meter with accessories | E159: 54 | F159: Nr. | G159: 20 | H159: =G159*E159 -> 1080
A161: 2 | C161: Float switch | E161: 4 | F161: Nr. | G161: 1.5 | H161: =G161*E161 -> 6
A163: 3 | C163: Float Valve | E163: 4 | F163: Nr. | G163: 1.5 | H163: =G163*E163 -> 6
...

Sheet BILL NO.9 PROVISIONAL
A2: BILL NO. 5 - Finishing Work Package
A4: Item | C4: Work Description | E4: Qty | F4: Unit | G4: Rate | H4: R.O. Bz.
C6: Finishing work Packages
C8: Allow for the following Provisional Sums to be expended as directed by the Engineer/Employer's Representative or deducted in whole or in part if not required
A10: A | C10: LIFT INSTALLATION | E10: 2 | F10: Nos | G10: 11250 | H10: =(E10*G10) -> 22500
A12: B | C12: Kitchen Cabinet including the appliances | E12: 54 | F12: Nos | G12: 600 | H12: =(E12*G12) -> 32400
A14: C | C14: EXTERNAL CAR PARKING | E14: 33 | F14: Nos | G14: 50 | H14: =(E14*G14) -> 1650
A16: D | C16: SHORING | E16: 1 | F16: Item | G16: 6500 | H16: =(E16*G16) -> 6500
A18: E | C18: PUZZLE CAR PARKING Mechanically operated and lifting Car lifting REFER DWG - A111 | E18: 1 | F18: Item | G18: 20000 | H18: =(E18*G18) -> 20000
A20: F | C20: Electrical Main Connection Works | E20: 1 | F20: Item | G20: 2000 | H20: =(E20*G20) -> 2000
A22: G | C22: Waterline Main Connection Works including FEES | E22: 1 | F22: Item | G22: 1650 | H22: =(E22*G22) -> 1650
A24: H | C24: HVAC Package | E24: 1 | F24: Items | G24: 35000 | H24: =(E24*G24) -> 35000
A26: I | C26: Fire Alarm & Fire Fighting works | E26: 1 | F26: Items | G26: 10000 | H26: =(E26*G26) -> 10000
A28: J | C28: Swimming Pool | E28: 1 | F28: Items | G28: 8000 | H28: =(E28*G28) -> 8000
A30: K | C30: Swimming Pool Deck | E30: 1 | F30: Items | G30: 3000 | H30: =(E30*G30) -> 3000
A32: L | C32: GYM | E32: 1 | F32: Items | G32: 10000 | H32: =(E32*G32) -> 10000
C37: PROVISIONAL SUMS
C38: Carried to General Summary | F38: R.O. | H38: =SUM(H10:H37) -> 152700

Sheet BW
A1: Project
A2: sub-masonry works
A4: S.No | B4: Description | C4: Unit | D4: No | F4: L | G4: B | H4: D | I4: Remarks | K4: 300mm hick | L4: 200mm thick | M4: 100mm thick
B5: Basement 01 floor
B6: 300mm thick | C6: m2 | D6: 1 | E6: 1 | F6: 6.95 | H6: =4.35-0.7 -> 3.65 | K6: =PRODUCT(D6:H6) -> 25.3675
B7: 200mm thick | C7: m2 | D7: 1 | E7: 2 | F7: 3 | H7: =4.35-0.7 -> 3.65 | L7: =PRODUCT(D7:H7) -> 21.9
B8: 200mm thick | C8: m2 | D8: 1 | E8: 3 | F8: 6.95 | H8: =4.35-0.7 -> 3.65 | L8: =PRODUCT(D8:H8) -> 76.1025
B9: 200mm thick | C9: m2 | D9: 1 | E9: 2 | F9: 1.1 | H9: =4.35-0.7 -> 3.65 | L9: =PRODUCT(D9:H9) -> 8.03
B10: 200mm thick | C10: m2 | D10: 1 | E10: 2 | F10: 2.2 | H10: =4.35-0.7 -> 3.65 | L10: =PRODUCT(D10:H10) -> 16.06
B11: 200mm thick | C11: m2 | D11: 1 | E11: 1 | F11: 1.26 | H11: =4.35-0.7 -> 3.65 | L11: =PRODUCT(D11:H11) -> 4.599
B12: 200mm thick | C12: m2 | D12: 1 | E12: 1 | F12: 2.5 | H12: =4.35-0.7 -> 3.65 | L12: =PRODUCT(D12:H12) -> 9.125
B13: 200mm thick | C13: m2 | D13: 1 | E13: 1 | F13: 5.72 | H13: 4.35 | L13: =PRODUCT(D13:H13) -> 24.882
B14: D5 | C14: m2 | D14: -1 | E14: ='D&W'!I5 -> 2 | F14: ='D&W'!BG7/1000 -> 1 | H14: ='D&W'!BH7/1000 -> 2.2 | L14: =PRODUCT(D14:H14) -> -4.4
B15: D10 | C15: m2 | D15: -1 | E15: ='D&W'!O5 -> 2 | F15: 1.1 | H15: 2.2 | L15: =PRODUCT(D15:H15) -> -4.84
B16: D3 | C16: m2 | D16: -1 | E16: 1 | F16: ='D&W'!BG5/1000 -> 1.5 | H16: 2.2 | L16: =PRODUCT(D16:H16) -> -3.3
B18: Ground floor
B19: 300mm thick | C19: m2 | D19: 1 | E19: 1 | F19: 1.15 | H19: 4.35 | K19: =PRODUCT(D19:H19) -> 5.0025
B20: 200mm thick | C20: m2 | D20: 1 | E20: 1 | F20: 4.84 | H20: =4.65-0.7 -> 3.95 | L20: =PRODUCT(D20:H20) -> 19.118
B21: 200mm thick | C21: m2 | D21: 1 | E21: 1 | F21: 0.75 | H21: =4.65-0.7 -> 3.95 | L21: =PRODUCT(D21:H21) -> 2.9625
B22: 200mm thick | C22: m2 | D22: 1 | E22: 1 | F22: 0.63 | H22: =4.65-0.7 -> 3.95 | L22: =PRODUCT(D22:H22) -> 2.4885
B23: 200mm thick | C23: m2 | D23: 1 | E23: 1 | F23: 10.25 | H23: =4.65-0.7 -> 3.95 | L23: =PRODUCT(D23:H23) -> 40.4875
B24: 200mm thick | C24: m2 | D24: 1 | E24: 1 | F24: 10.76 | H24: =4.65-0.3 -> 4.35 | L24: =PRODUCT(D24:H24) -> 46.806
B25: 200mm thick | C25: m2 | D25: 1 | E25: 2 | F25: 0.37 | H25: =4.65-0.3 -> 4.35 | L25: =PRODUCT(D25:H25) -> 3.219
B26: 200mm thick | C26: m2 | D26: 1 | E26: 1 | F26: 0.5 | H26: =4.65-0.3 -> 4.35 | L26: =PRODUCT(D26:H26) -> 2.175
B27: 200mm thick | C27: m2 | D27: 1 | E27: 1 | F27: 6.8 | H27: =4.65-0.3 -> 4.35 | L27: =PRODUCT(D27:H27) -> 29.58
B28: 200mm thick | C28: m2 | D28: 1 | E28: 2 | F28: 3.6 | H28: =4.65-0.3 -> 4.35 | L28: =PRODUCT(D28:H28) -> 31.32
B29: 200mm thick | C29: m2 | D29: 1 | E29: 1 | F29: 5.47 | H29: =4.65-0.3 -> 4.35 | L29: =PRODUCT(D29:H29) -> 23.7945
B30: 200mm thick | C30: m2 | D30: 1 | E30: 1 | F30: 7.3 | H30: =4.65-0.3 -> 4.35 | L30: =PRODUCT(D30:H30) -> 31.755
B31: 200mm thick | C31: m2 | D31: 1 | E31: 3 | F31: 5.49 | H31: =4.65-0.3 -> 4.35 | L31: =PRODUCT(D31:H31) -> 71.6445
B32: 200mm thick | C32: m2 | D32: 1 | E32: 1 | F32: 5.19 | H32: =4.65-0.3 -> 4.35 | L32: =PRODUCT(D32:H32) -> 22.5765
B33: 200mm thick | C33: m2 | D33: 1 | E33: 1 | F33: 4.53 | H33: =4.65-0.3 -> 4.35 | L33: =PRODUCT(D33:H33) -> 19.7055
B34: 200mm thick | C34: m2 | D34: 1 | E34: 1 | F34: 1.02 | H34: 4.35 | L34: =PRODUCT(D34:H34) -> 4.437
B35: 200mm thick | C35: m2 | D35: 1 | E35: 1 | F35: 3 | H35: 4.35 | L35: =PRODUCT(D35:H35) -> 13.05
B36: 200mm thick | C36: m2 | D36: 1 | E36: 1 | F36: 12 | H36: 4.35 | L36: =PRODUCT(D36:H36) -> 52.2
B37: 200mm thick | C37: m2 | D37: 1 | E37: 1 | F37: 1.2 | H37: 4.35 | L37: =PRODUCT(D37:H37) -> 5.22
B38: 200mm thick | C38: m2 | D38: 1 | E38: 1 | F38: 2.2 | H38: 4.35 | L38: =PRODUCT(D38:H38) -> 9.57
B39: 200mm thick | C39: m2 | D39: 1 | E39: 1 | F39: 1.3 | H39: 4.35 | L39: =PRODUCT(D39:H39) -> 5.655
B40: 200mm thick | C40: m2 | D40: 1 | E40: 1 | F40: 2 | H40: 4.35 | L40: =PRODUCT(D40:H40) -> 8.7
B41: 200mm thick | C41: m2 | D41: 1 | E41: 1 | F41: 2.7 | H41: 4.35 | L41: =PRODUCT(D41:H41) -> 11.745
B42: 200mm thick | C42: m2 | D42: 1 | E42: 1 | F42: 2.5 | H42: 4.35 | L42: =PRODUCT(D42:H42) -> 10.875
B43: 200mm thick | C43: m2 | D43: 1 | E43: 1 | F43: 1.96 | H43: 4.35 | L43: =PRODUCT(D43:H43) -> 8.526
B44: 200mm thick | C44: m2 | D44: 1 | E44: 1 | F44: 0.8 | H44: 4.35 | L44: =PRODUCT(D44:H44) -> 3.48
B45: 200mm thick | C45: m2 | D45: 1 | E45: 1 | F45: 2.2 | H45: 4.35 | L45: =PRODUCT(D45:H45) -> 9.57
... B69: D6* | C69: m2 | D69: -1 | E69: 1 | F69: 1 | H69: 2.2 | L69: =PRODUCT(D69:H69) -> -2.2
B70: 100mm thick | C70: m2 | D70: 1 | E70: 1 | F70: 1.3 | H70: 4.35 | M70: =PRODUCT(D70:I70) -> 5.655
B71: D6 | C71: m2 | D71: -1 | E71: 1 | F71: 0.8 | H71: 2.2 | M71: =PRODUCT(D71:I71) -> -1.76
B74: First floor topenthouse floor
B75: 200mm thick | C75: m2 | D75: 6 | E75: 1 | F75: 33.9 | H75: 3.3 | L75: =PRODUCT(D75:H75) -> 671.22
B76: W4 | C76: m2 | D76: -6 | E76: 1 | F76: 0.6 | H76: 0.8 | L76: =PRODUCT(D76:H76) -> -2.88
B77: Aluiminium Luver 3 | C77: m2 | D77: -6 | E77: 3 | F77: 0.8 | H77: 2.76 | L77: =PRODUCT(D77:H77) -> -39.744
B78: TEMPERED GLASS HANDRAIL 4 | C78: m2 | D78: -6 | E78: 2 | F78: 1.3 | H78: 1 | L78: =PRODUCT(D78:H78) -> -15.6
B79: TEMPERED GLASS HANDRAIL 4 | C79: m2 | D79: -6 | E79: 1 | F79: 1.8 | H79: 1 | L79: =PRODUCT(D79:H79) -> -10.8
B80: TEMPERED GLASS HANDRAIL 4 | C80: m2 | D80: -6 | E80: 4 | F80: 1.2 | H80: 1 | L80: =PRODUCT(D80:H80) -> -28.8
B81: W2 | C81: m2 | D81: -6 | E81: 3 | F81: 1 | H81: 1.1 | L81: =PRODUCT(D81:H81) -> -19.8
B82: W1 | C82: m2 | D82: -6 | E82: 1 | F82: 2 | H82: 1.4 | L82: =PRODUCT(D82:H82) -> -16.8
B83: 200mm thick | C83: m2 | D83: -6 | E83: 1 | F83: 13.89 | H83: =3.6-0.8 -> 2.8 | L83: =PRODUCT(D83:H83) -> -233.352
B84: 200mm thick | C84: m2 | D84: -6 | E84: 1 | F84: 7.13 | H84: =3.6-0.3 -> 3.3 | L84: =PRODUCT(D84:H84) -> -141.174
B85: 200mm thick | C85: m2 | D85: -6 | E85: 1 | F85: 11.5 | H85: =3.6-0.3 -> 3.3 | L85: =PRODUCT(D85:H85) -> -227.7
B86: Aluiminium Luver 3 | C86: m2 | D86: -6 | E86: 3 | F86: 0.8 | H86: 2.76 | L86: =PRODUCT(D86:H86) -> -39.744
B87: TEMPERED GLASS HANDRAIL 4 | C87: m2 | D87: -6 | E87: 3 | F87: 1.2 | H87: 1 | L87: =PRODUCT(D87:H87) -> -21.6
B88: TEMPERED GLASS HANDRAIL 4 | C88: m2 | D88: -6 | E88: 1 | F88: 1.5 | H88: 1 | L88: =PRODUCT(D88:H88) -> -9
B89: TEMPERED GLASS HANDRAIL 4 | C89: m2 | D89: -6 | E89: 1 | F89: 1.65 | H89: 1 | L89: =PRODUCT(D89:H89) -> -9.9
B90: TEMPERED GLASS HANDRAIL 4 | C90: m2 | D90: -6 | E90: 1 | F90: 1.35 | H90: 1.2 | L90: =PRODUCT(D90:H90) -> -9.72
B91: 200mm thick | C91: m2 | D91: 6 | E91: 1 | F91: 10.6 | H91: 3.3 | L91: =PRODUCT(D91:H91) -> 209.88
B92: D5 | C92: m2 | D92: -6 | E92: 2 | F92: 1 | H92: 2.2 | L92: =PRODUCT(D92:H92) -> -26.4
B93: 200mm thick | C93: m2 | D93: 6 | E93: 1 | F93: 5.9 | H93: 3.3 | L93: =PRODUCT(D93:H93) -> 116.82
B94: 200mm thick | C94: m2 | D94: 6 | E94: 1 | F94: 9 | H94: 3.3 | L94: =PRODUCT(D94:H94) -> 178.2
B95: 200mm thick | C95: m2 | D95: 6 | E95: 1 | F95: 2.2 | H95: 3.3 | L95: =PRODUCT(D95:H95) -> 43.56
B96: 200mm thick | C96: m2 | D96: -6 | E96: 1 | F96: 10.5 | H96: 3.3 | L96: =PRODUCT(D96:H96) -> -207.9
B97: W4 | C97: m2 | D97: -6 | E97: 1 | F97: 0.6 | H97: 0.8 | L97: =PRODUCT(D97:H97) -> -2.88
... B101: D7 | C101: m2 | D101: -6 | E101: 1 | F101: 0.8 | H101: 2.2 | L101: =PRODUCT(D101:H101) -> -10.56
B102: 200mm thick | C102: m2 | D102: 6 | E102: 1 | F102: =1.4+17.6 -> 19 | H102: 3.3 | L102: =PRODUCT(D102:H102) -> 376.2
B103: D9 | C103: m2 | D103: -6 | E103: 2 | F103: 1.1 | H103: 2.2 | L103: =PRODUCT(D103:H103) -> -29.04
B104: 200mm thick | C104: m2 | D104: 6 | E104: 1 | F104: 1.8 | H104: 3.3 | L104: =PRODUCT(D104:H104) -> 35.64
B105: 200mm thick | C105: m2 | D105: 6 | E105: 1 | F105: 6.4 | H105: 3.3 | L105: =PRODUCT(D105:H105) -> 126.72
B106: 200mm thick | C106: m2 | D106: 6 | E106: 1 | F106: 9.8 | H106: 3.3 | L106: =PRODUCT(D106:H106) -> 194.04
B107: 200mm thick | C107: m2 | D107: 6 | E107: 1 | F107: 2 | H107: 3.3 | L107: =PRODUCT(D107:H107) -> 39.6
B108: D7 | C108: m2 | D108: -6 | E108: 1 | F108: 0.8 | H108: 2.2 | L108: =PRODUCT(D108:H108) -> -10.56
B109: 200mm thick | C109: m2 | D109: 6 | E109: 1 | F109: 3.8 | H109: 3.3 | L109: =PRODUCT(D109:H109) -> 75.24
B110: 200mm thick | C110: m2 | D110: 6 | E110: 1 | F110: 4.9 | H110: 3.3 | L110: =PRODUCT(D110:H110) -> 97.02
B111: 200mm thick | C111: m2 | D111: 6 | E111: 1 | F111: 9.5 | H111: 3.3 | L111: =PRODUCT(D111:H111) -> 188.1
B112: D5 | C112: m2 | D112: -6 | E112: 1 | F112: 1 | H112: 2.2 | L112: =PRODUCT(D112:H112) -> -13.2
B113: 200mm thick | C113: m2 | D113: 6 | E113: 1 | F113: 6.5 | H113: 3.3 | L113: =PRODUCT(D113:H113) -> 128.7
B114: D7 | C114: m2 | D114: -6 | E114: 1 | F114: 0.8 | H114: 2.2 | L114: =PRODUCT(D114:H114) -> -10.56
... B122: D5 | C122: m2 | D122: -6 | E122: 1 | F122: 1 | H122: 2.2 | L122: =PRODUCT(D122:H122) -> -13.2
B123: 200mm thick | C123: m2 | D123: 6 | E123: 1 | F123: 14.2. | H123: 3.3 | L123: =PRODUCT(D123:H123) -> 19.8
B124: D9 | C124: m2 | D124: -6 | E124: 2 | F124: 1.1 | H124: 2.2 | L124: =PRODUCT(D124:H124) -> -29.04
B125: D6 | C125: m2 | D125: -6 | E125: 1 | F125: 0.8 | H125: 2.2 | L125: =PRODUCT(D125:H125) -> -10.56
B126: 200mm thick | C126: m2 | D126: 6 | E126: 1 | F126: 2.8 | H126: 3.3 | L126: =PRODUCT(D126:H126) -> 55.44
B127: 200mm thick | C127: m2 | D127: 6 | E127: 1 | F127: 10.6 | H127: 3.3 | L127: =PRODUCT(D127:H127) -> 209.88
B128: D11 | C128: m2 | D128: -6 | E128: 1 | F128: 1 | H128: 2.2 | L128: =PRODUCT(D128:H128) -> -13.2
B129: 200mm thick | C129: m2 | D129: 6 | E129: 1 | F129: 14.2. | H129: 3.3 | L129: =PRODUCT(D129:H129) -> 19.8
B130: D9 | C130: m2 | D130: -6 | E130: 1 | F130: 1.1 | H130: 2.2 | L130: =PRODUCT(D130:H130) -> -14.52
B131: 200mm thick | C131: m2 | D131: 6 | E131: 1 | F131: 8.3 | H131: 3.3 | L131: =PRODUCT(D131:H131) -> 164.34
B132: D5 | C132: m2 | D132: -6 | E132: 1 | F132: 1 | H132: 2.2 | L132: =PRODUCT(D132:H132) -> -13.2
B133: 200mm thick | C133: m2 | D133: 6 | E133: 1 | F133: 2.5 | H133: 3.3 | L133: =PRODUCT(D133:H133) -> 49.5
B134: D7 | C134: m2 | D134: -6 | E134: 1 | F134: 0.8 | H134: 2.2 | L134: =PRODUCT(D134:H134) -> -10.56
B135: 200mm thick | C135: m2 | D135: 6 | E135: 1 | F135: =1.6+3.9+7.5+2.3 -> 15.3 | H135: 3.3 | L135: =PRODUCT(D135:H135) -> 302.94
B136: 200mm thick | C136: m2 | D136: 6 | E136: 1 | F136: 11.5 | H136: 3.3 | L136: =PRODUCT(D136:H136) -> 227.7
B137: D5 | C137: m2 | D137: -6 | E137: 1 | F137: 1 | H137: 2.2 | L137: =PRODUCT(D137:H137) -> -13.2
...

Sheet D&W
A2: S.No | B2: location | C2: D01 | D2: D02 | E2: D1 | F2: D2 | G2: D3 | H2: D4 | I2: D5 | J2: D6 | K2: D6* | L2: D7 | M2: D8 | N2: D9 | O2: D10 | P2: D11 | Q2: D12 | R2: D13 | S2: D14 | T2: D15 | U2: D16 | V2: D17 | W2: D18 | X2: W1 | Y2: W2 | Z2: W3 | AA2: W4 | AB2: W5 | AC2: W6 | AD2: W7 | AE2: W8 | AH2: CW1 | AI2: CW2 | AJ2: CW3 | AK2: CW4 | AL2: CW5 | AM2: CW6 | AN2: CW7 | AO2: CW8 | AP2: CW9 | AQ2: CW10 | AR2: CW11 | AS2: CW12 | AT2: CW13 | AU2: CW14 | AV2: CW15 | AW2: CW16 | AX2: CW17 | AY2: CW18 | AZ2: CW19 | BA2: CW20 | BB2: CW21 | BC2: CW22 | BD2: FG1 | BE2: FG | BF2: TYPE | BG2: SIZE (mm) - WIDTH | BH2: SIZE (mm) - HEIGHT | BI2: DESCRIPTION
BF3: D1 | BG3: 1700 | BH3: 2200 | BI3: HEAVY DUTY UPVC SECTION DOUBLE LEAF HINGED DOOR WITH 6mm DOUBLE GLASS 12 +mm AIR GAP IN BETWEEN
B4: Basement 2 | BF4: D2 | BG4: 1700 | BH4: 2200 | BI4: HEAVY DUTY UPVC SECTION DOUBLE LEAF HINGED DOOR WITH 6mm DOUBLE GLASS 12 +mm AIR GAP IN BETWEEN
B5: Basement 1 | G5: 1 | I5: 2 | O5: 2 | W5: 1 | BF5: D3 | BG5: 1500 | BH5: 2400 | BI5: HEAVY DUTY UPVC SECTION DOUBLE LEAF HINGED DOOR WITH 6mm DOUBLE GLASS 12 +mm AIR GAP IN BETWEEN
B6: Ground floor | E6: 1 | F6: 13 | H6: 1 | I6: 1 | J6: 2 | K6: 1 | L6: 1 | M6: 1 | O6: 3 | R6: 1 | S6: 1 | T6: 1 | U6: 1 | V6: 1 | AC6: 1 | AD6: 1 | BD6: 29 | BF6: D4 | BG6: 1000 | BH6: 2200 | BI6: MAHOGANY WOOD DECORATIVE PANELED SINGLE LEAF HINGED DOOR & 60min. FIRE RESISTANCE
B7: First floor | I7: 12 | J7: 10 | K7: 9 | M7: 9 | O7: 2 | P7: 14 | Q7: 11 | X7: 1 | Y7: 4 | Z7: 1 | AA7: 2 | AB7: 1 | AE7: 1 | AH7: 1 | AI7: 1 | AJ7: 1 | AK7: 1 | AL7: 1 | AM7: 1 | AN7: 1 | AO7: 1 | AP7: 1 | BE7: 14 | BF7: D5 | BG7: 1000 | BH7: 2200 | BI7: MAHOGANY WOOD DECORATIVE PANELED SINGLE LEAF HINGED DOOR
B8: Second floor | I8: 12 | J8: 10 | L8: 9 | N8: 9 | O8: 2 | P8: 14 | Q8: 11 | X8: 1 | Y8: 4 | Z8: 1 | AA8: 2 | AB8: 1 | AE8: 1 | AQ8: 1 | AR8: 1 | AS8: 1 | AT8: 1 | AU8: 1 | AV8: 1 | AW8: 1 | AX8: 1 | AY8: 1 | AZ8: 1 | BA8: 1 | BB8: 1 | BC8: 1 | BE8: 14 | BF8: D6 | BG8: 800 | BH8: 2200 | BI8: MAHOGANY WOOD DECORATIVE PANELED SINGLE LEAF HINGED DOOR WITH 300mm ALUMINUM PLATE
B9: Third floor | I9: 12 | J9: 10 | L9: 9 | N9: 9 | O9: 2 | P9: 14 | Q9: 11 | X9: 1 | Y9: 4 | Z9: 1 | AA9: 2 | AB9: 1 | AE9: 1 | AH9: 1 | AI9: 1 | AJ9: 1 | AK9: 1 | AL9: 1 | AM9: 1 | AN9: 1 | AO9: 1 | BE9: 14 | BF9: D6* | BG9: 1000 | BH9: 2200 | BI9: MAHOGANY WOOD DECORATIVE PANELED SINGLE LEAF HINGED DOOR WITH 300mm ALUMINUM PLATE
B10: Fourth floor | I10: 12 | J10: 10 | L10: 9 | N10: 9 | O10: 2 | P10: 14 | Q10: 11 | X10: 1 | Y10: 4 | Z10: 1 | AA10: 2 | AB10: 1 | AE10: 1 | AH10: 1 | AI10: 1 | AJ10: 1 | AK10: 1 | AL10: 1 | AM10: 1 | AN10: 1 | AO10: 1 | BE10: 14 | BF10: D7 | BG10: 800 | BH10: 2200 | BI10: HEAVY DUTY UPVC SECTION SINGLE LEAF HINGED DOOR WITH 6mm DOUBLE GLASS
B11: Fifth floor | I11: 12 | J11: 10 | L11: 9 | N11: 9 | O11: 2 | P11: 14 | Q11: 11 | X11: 1 | Y11: 4 | Z11: 1 | AA11: 2 | AB11: 1 | AE11: 1 | AH11: 1 | AI11: 1 | AJ11: 1 | AK11: 1 | AL11: 1 | AM11: 1 | AN11: 1 | AO11: 1 | BE11: 14 | BF11: D8 | BG11: 1000 | BH11: 2200 | BI11: HEAVY DUTY UPVC SECTION SINGLE LEAF HINGED DOOR GARBAGE ROOM | BK11: vv gy
B12: penthouse floor | I12: 12 | J12: 10 | L12: 9 | N12: 9 | O12: 2 | P12: 14 | Q12: 11 | X12: 1 | Y12: 4 | Z12: 1 | AA12: 2 | AB12: 1 | AE12: 1 | AH12: 1 | AI12: 1 | AJ12: 1 | AK12: 1 | AL12: 1 | AM12: 1 | AN12: 1 | AO12: 1 | BE12: 14 | BF12: D9 | BG12: 1100 | BH12: 2200 | BI12: MAHOGANY WOOD DECORATIVE PANELED SINGLE LEAF HINGED DOOR & 60min. FIRE RESISTANCE
B13: head room | O13: 2 | AB13: 2 | BF13: D10 | BG13: 1000 | BH13: 2200 | BI13: MAHOGANY WOOD DECORATIVE PANELED SINGLE LEAF HINGED DOOR & 90min. FIRE RESISTANCE
BF14: D11 | BG14: 1000 | BH14: 2200 | BI14: HEAVY DUTY UPVC SECTION SINGLE LEAF HINGED DOOR WITH 6mm DOUBLE GLASS
B15: Total | C15: =SUM(C4:C14) -> 0 | D15: =SUM(D4:D14) -> 0 | E15: =SUM(E4:E14) -> 1 | F15: =SUM(F4:F14) -> 13 | G15: =SUM(G4:G14) -> 1 | H15: =SUM(H4:H14) -> 1 | I15: =SUM(I4:I14) -> 75 | J15: =SUM(J4:J14) -> 62 | ... AE15: =SUM(AE4:AE14) -> 6 | AH15: =SUM(AH4:AH14) -> 5 | AI15: =SUM(AI4:AI14) -> 5 | AJ15: =SUM(AJ4:AJ14) -> 5 | AK15: =SUM(AK4:AK14) -> 5 | AL15: =SUM(AL4:AL14) -> 5 | AM15: =SUM(AM4:AM14) -> 5 | AN15: =SUM(AN4:AN14) -> 5 | AO15: =SUM(AO4:AO14) -> 5 | ... BE15: =SUM(BE4:BE14) -> 84 | BF15: D12 | BG15: 900 | BH15: 2200 | BI15: MAHOGANY WOOD DECORATIVE PANELED SINGLE LEAF HINGED DOOR WITH 300mm ALUMINUM PLATE
BF16: D13 | BG16: 1450 | BH16: 2200 | BI16: HEAVY DUTY UPVC SECTION SINGLE LEAF HINGED DOOR WITH 6mm DOUBLE GLASS 12 +mm AIR GAP IN BETWEEN
BF17: D14 | BG17: 1550 | BH17: 2200 | BI17: HEAVY DUTY UPVC SECTION DOUBLE LEAF HINGED DOOR WITH 6mm DOUBLE GLASS 12 +mm AIR GAP IN BETWEEN
BF18: D15 | BG18: 1350 | BH18: 2200 | BI18: HEAVY DUTY UPVC SECTION DOUBLE LEAF HINGED DOOR WITH 6mm DOUBLE GLASS 12 +mm AIR GAP IN BETWEEN
BF19: D16 | BG19: 1400 | BH19: 2200 | BI19: HEAVY DUTY UPVC SECTION DOUBLE LEAF HINGED DOOR WITH 6mm DOUBLE GLASS 12 +mm AIR GAP IN BETWEEN
B20: lintel | BF20: D17 | BG20: 1900 | BH20: 2200 | BI20: HEAVY DUTY UPVC SECTION DOUBLE LEAF HINGED DOOR WITH 6mm DOUBLE GLASS 12 +mm AIR GAP IN BETWEEN
B21: length | E21: {=TRANSPOSE((BG3:BG21 + 300) / 1000)} -> 2 | F21: 2 | G21: 1.8 | H21: 1.3 | I21: 1.3 | J21: 1.1 | K21: 1.3 | L21: 1.1 | M21: 1.3 | N21: 1.4 | O21: 1.3 | P21: 1.3 | Q21: 1.2 | R21: 1.75 | S21: 1.85 | T21: 1.65 | U21: 1.7 | V21: 2.2 | W21: 2.2 | X21: {=TRANSPOSE((BJ51:BJ55 + 300) / 1000)} -> 2.3 | Y21: 1.3 | Z21: 1.1 | AA21: 0.9 | AB21: 1.3 | AC21: 2 | AD21: 1.3 | AE21: 0.9 | BF21: D18 | BG21: 1900 | BH21: 2200 | BI21: HEAVY DUTY UPVC SECTION DOUBLE LEAF HINGED DOOR PUMP ROOM
B22: width | E22: 0.2 | F22: 0.2 | G22: 0.2 | H22: 0.2 | I22: 0.2 | J22: 0.2 | K22: 0.2 | L22: 0.2 | M22: 0.2 | N22: 0.2 | O22: 0.2 | P22: 0.2 | Q22: 0.2 | R22: 0.2 | S22: 0.2 | T22: 0.2 | U22: 0.2 | V22: 0.2 | W22: 0.2 | X22: 0.2 | Y22: 0.2 | Z22: 0.2 | AA22: 0.2 | AB22: 0.2 | AC22: 0.2 | AD22: 0.2 | AE22: 0.2
B23: depth | E23: 0.3 | F23: 0.3 | G23: 0.3 | H23: 0.3 | I23: 0.3 | J23: 0.3 | K23: 0.3 | L23: 0.3 | M23: 0.3 | N23: 0.3 | O23: 0.3 | P23: 0.3 | Q23: 0.3 | R23: 0.3 | S23: 0.3 | T23: 0.3 | U23: 0.3 | V23: 0.3 | W23: 0.3 | X23: 0.3 | Y23: 0.3 | Z23: 0.3 | AA23: 0.3 | AB23: 0.3 | AC23: 0.3 | AD23: 0.3 | AE23: 0.3 | BF23: SCHEDULE OF CURTAIN WALLS GLASS
BF24: TYPE | BG24: WIDTH (mm) | BH24: HEIGHT (mm) | BI24: GLASS 1 | BJ24: SILL LEVEL
B25: qty | E25: =PRODUCT(E21:E23)*E15 -> 0.12 | F25: =PRODUCT(F21:F23)*F15 -> 1.56 | G25: =PRODUCT(G21:G23)*G15 -> 0.108 | H25: =PRODUCT(H21:H23)*H15 -> 0.078 | I25: =PRODUCT(I21:I23)*I15 -> 5.85 | J25: =PRODUCT(J21:J23)*J15 -> 4.092 | K25: =PRODUCT(K21:K23)*K15 -> 0.78 | L25: =PRODUCT(L21:L23)*L15 -> 3.036 | ... AE25: =PRODUCT(AE21:AE23)*AE15 -> 0.324 | BF25: CW1 | BG25: 3050 | BH25: 3240 | BI25: H.Q UPVC SECTION WITH 6mm CLEAR FLOAT GLASS +12mm AIR GAP+6mm REFLECTED GLASS AWING WINDOW | BJ25: 0
B26: Cills | X26: =X25 -> 0.828 | Y26: =Y25 -> 1.872 | Z26: =Z25 -> 0.396 | AA26: =AA25 -> 0.648 | AB26: =AB25 -> 0.624 | AC26: =AC25 -> 0.12 | AD26: =AD25 -> 0.078 | AE26: =AE25 -> 0.324 | BF26: CW2 | BG26: 2100 | BH26: 3240 | BI26: H.Q UPVC SECTION WITH 6mm CLEAR FLOAT GLASS +12mm AIR GAP+6mm REFLECTED GLASS AWING WINDOW | BJ26: 0
B27: Area | E27: =E22*E21 -> 0.4 | F27: =F22*F21 -> 0.4 | G27: =G22*G21 -> 0.36 | H27: =H22*H21 -> 0.26 | I27: =I22*I21 -> 0.26 | J27: =J22*J21 -> 0.22 | K27: =K22*K21 -> 0.26 | L27: =L22*L21 -> 0.22 | ... AE27: =AE22*AE21 -> 0.18 | BF27: CW3 | BG27: 1400 | BH27: 3240 | BI27: H.Q UPVC SECTION WITH 6mm CLEAR FLOAT GLASS +12mm AIR GAP+6mm REFLECTED GLASS AWING WINDOW | BJ27: 0
B28: Total concrete | E28: =SUM(E25:E27)-E27 -> 0.12 | F28: =SUM(F25:F27)-F27 -> 1.56 | G28: =SUM(G25:G27)-G27 -> 0.108 | H28: =SUM(H25:H27)-H27 -> 0.078 | I28: =SUM(I25:I27)-I27 -> 5.85 | J28: =SUM(J25:J27)-J27 -> 4.092 | K28: =SUM(K25:K27)-K27 -> 0.78 | L28: =SUM(L25:L27)-L27 -> 3.036 | ... AE28: =SUM(AE25:AE27)-AE27 -> 0.648 | AF28: =SUM(C28:AE28) -> 43.431 | AG28: m3 | BF28: CW4 | BG28: 3400 | BH28: 3240 | BI28: H.Q UPVC SECTION WITH 6mm CLEAR FLOAT GLASS +12mm AIR GAP+6mm REFLECTED GLASS AWING WINDOW | BJ28: 0
BF29: CW5 | BG29: 2600 | BH29: 3240 | BI29: H.Q UPVC SECTION WITH 6mm CLEAR FLOAT GLASS +12mm AIR GAP+6mm REFLECTED GLASS AWING WINDOW | BJ29: 0
BF30: CW6 | BG30: 3050 | BH30: 3240 | BI30: H.Q UPVC SECTION WITH 6mm CLEAR FLOAT GLASS +12mm AIR GAP+6mm REFLECTED GLASS AWING WINDOW | BJ30: 0
B31: Cw | AH31: =AH2 -> CW1 | AI31: =AI2 -> CW2 | AJ31: =AJ2 -> CW3 | AK31: =AK2 -> CW4 | AL31: =AL2 -> CW5 | AM31: =AM2 -> CW6 | AN31: =AN2 -> CW7 | AO31: =AO2 -> CW8 | ... BC31: =BC2 -> CW22 | BF31: CW7 | BG31: 1500 | BH31: 3240 | BI31: H.Q UPVC SECTION WITH 6mm CLEAR FLOAT GLASS +12mm AIR GAP+6mm REFLECTED GLASS AWING WINDOW | BJ31: 0
B32: Width(m) | AH32: {=TRANSPOSE((BG25:BG47) / 1000)} -> 3.05 | AI32: 2.1 | AJ32: 1.4 | AK32: 3.4 | AL32: 2.6 | AM32: 3.05 | AN32: 1.5 | AO32: 1.9 | AP32: 2.3 | AQ32: 1.95 | AR32: 1.6 | AS32: 1.7 | AT32: 1.4 | AU32: 2.1 | AV32: 0.8 | AW32: 0.9 | AX32: 0.8 | AY32: 2.35 | AZ32: 1.3 | BA32: 0 | BB32: 1.7 | BC32: 0.6 | BD32: 1.3 | BF32: CW8 | BG32: 1900 | BH32: 3200 | BI32: H.Q UPVC SECTION WITH 6mm CLEAR FLOAT GLASS +12mm AIR GAP+6mm REFLECTED GLASS AWING WINDOW | BJ32: 0
B33: Height(m) | AH33: {=TRANSPOSE((BH25:BH47) / 1000)} -> 3.24 | AI33: 3.24 | AJ33: 3.24 | AK33: 3.24 | AL33: 3.24 | AM33: 3.24 | AN33: 3.24 | AO33: 3.2 | AP33: 3.2 | AQ33: 3.24 | AR33: 3.24 | AS33: 3.24 | AT33: 3.24 | AU33: 3.24 | AV33: 3.24 | AW33: 3.24 | AX33: 3.24 | AY33: 3.24 | AZ33: 3.24 | BA33: 0 | BB33: 3.2 | BC33: 3.2 | BD33: 3.2 | BF33: CW9 | BG33: 2300 | BH33: 3200 | BI33: H.Q UPVC SECTION WITH 6mm CLEAR FLOAT GLASS +12mm AIR GAP+6mm REFLECTED GLASS AWING WINDOW | BJ33: 0
BF34: CW10 | BG34: 1950 | BH34: 3240 | BI34: H.Q UPVC SECTION WITH 6mm CLEAR FLOAT GLASS +12mm AIR GAP+6mm REFLECTED GLASS AWING WINDOW | BJ34: 0
B35: Nos | AH35: =AH15 -> 5 | AI35: =AI15 -> 5 | AJ35: =AJ15 -> 5 | AK35: =AK15 -> 5 | AL35: =AL15 -> 5 | AM35: =AM15 -> 5 | AN35: =AN15 -> 5 | AO35: =AO15 -> 5 | ... BC35: =BC15 -> 1 | BF35: CW11 | BG35: 1600 | BH35: 3240 | BI35: H.Q UPVC SECTION WITH 6mm CLEAR FLOAT GLASS +12mm AIR GAP+6mm REFLECTED GLASS AWING WINDOW | BJ35: 0
BF36: CW12 | BG36: 1700 | BH36: 3240 | BI36: H.Q UPVC SECTION WITH 6mm CLEAR FLOAT GLASS +12mm AIR GAP+6mm REFLECTED GLASS AWING WINDOW | BJ36: 0
B37: Total Area | AH37: =PRODUCT(AH32:AH36) -> 49.41 | AI37: =PRODUCT(AI32:AI36) -> 34.02 | AJ37: =PRODUCT(AJ32:AJ36) -> 22.68 | AK37: =PRODUCT(AK32:AK36) -> 55.08 | AL37: =PRODUCT(AL32:AL36) -> 42.12 | AM37: =PRODUCT(AM32:AM36) -> 49.41 | AN37: =PRODUCT(AN32:AN36) -> 24.3 | AO37: =PRODUCT(AO32:AO36) -> 30.4 | ... BC37: =PRODUCT(BC32:BC36) -> 1.92 | BD37: =SUM(AH37:BC37) -> 370.416 | BE37: m2 | BF37: CW13 | BG37: 1400 | BH37: 3240 | BI37: H.Q UPVC SECTION WITH 6mm CLEAR FLOAT GLASS +12mm AIR GAP+6mm REFLECTED GLASS AWING WINDOW | BJ37: 0
BF38: CW14 | BG38: 2100 | BH38: 3240 | BI38: H.Q UPVC SECTION WITH 6mm CLEAR FLOAT GLASS +12mm AIR GAP+6mm REFLECTED GLASS AWING WINDOW | BJ38: 0
BF39: CW15 | BG39: 800 | BH39: 3240 | BI39: H.Q UPVC SECTION WITH 6mm CLEAR FLOAT GLASS +12mm AIR GAP+6mm REFLECTED GLASS AWING WINDOW | BJ39: 0
B40: FG1 | C40: FG1 | D40: FG1 | E40: FG1 | F40: FG1 | G40: FG1 | H40: FG1 | I40: FG1 | J40: FG1 | K40: FG1 | L40: FG1 | M40: FG1 | N40: FG1 | O40: FG1 | P40: FG1 | Q40: FG1 | R40: FG1 | S40: FG1 | T40: FG1 | U40: FG1 | V40: FG1 | W40: FG1 | X40: FG1 | Y40: FG1 | Z40: FG1 | AA40: FG1 | AB40: FG1 | AC40: FG1 | AD40: FG1 | AE40: FG1 | BF40: CW16 | BG40: 900 | BH40: 3240 | BI40: H.Q UPVC SECTION WITH 6mm CLEAR FLOAT GLASS +12mm AIR GAP+6mm REFLECTED GLASS AWING WINDOW | BJ40: 0
B41: Location | C41: Gf | D41: Gf | E41: Gf | F41: Gf | G41: Gf | H41: Gf | I41: Gf | J41: Gf | K41: Gf | L41: Gf | M41: Gf | N41: Gf | O41: Gf | P41: Gf | Q41: Gf | R41: Gf | S41: Gf | T41: Gf | U41: Gf | V41: Gf | W41: Gf | X41: Gf | Y41: Gf | Z41: Gf | AA41: Gf | AB41: Gf | AC41: Gf | AD41: Gf | AE41: Gf | BF41: CW17 | BG41: 800 | BH41: 3240 | BI41: H.Q UPVC SECTION WITH 6mm CLEAR FLOAT GLASS +12mm AIR GAP+6mm REFLECTED GLASS AWING WINDOW | BJ41: 0
B42: Width(m) | C42: 1.01 | D42: 0.98 | E42: 0.97 | F42: 0.49 | G42: 1.36 | H42: 0.51 | I42: 0.49 | J42: 0.9 | K42: 1.26 | L42: 1.29 | M42: 0.6 | N42: 0.72 | O42: 0.85 | P42: 0.44 | Q42: 0.56 | R42: 0.36 | S42: 0.49 | T42: 0.52 | U42: 0.64 | V42: 0.67 | W42: =0.7+1.35 -> 2.05 | X42: 2.26 | Y42: 0.82 | Z42: 0.92 | AA42: 0.59 | AB42: 0.41 | AC42: 0.34 | AD42: 0.36 | AE42: 0.64 | BF42: CW18 | BG42: 2350 | BH42: 3240 | BI42: H.Q UPVC SECTION WITH 6mm CLEAR FLOAT GLASS +12mm AIR GAP+6mm REFLECTED GLASS AWING WINDOW | BJ42: 0
B43: Height(m) | C43: 2.2 | D43: 2.2 | E43: 2.2 | F43: 2.2 | G43: 2.2 | H43: 2.2 | I43: 2.2 | J43: 2.2 | K43: 2.2 | L43: 2.2 | M43: 2.2 | N43: 2.2 | O43: 2.2 | P43: 2.2 | Q43: 2.2 | R43: 2.2 | S43: 2.2 | T43: 2.2 | U43: 2.2 | V43: 2.2 | W43: 2.2 | X43: 2.2 | Y43: 2.2 | Z43: 2.2 | AA43: 2.2 | AB43: 2.2 | AC43: 2.2 | AD43: 2.2 | AE43: 2.2 | BF43: CW19 | BG43: 1300 | BH43: 3240 | BI43: H.Q UPVC SECTION WITH 6mm CLEAR FLOAT GLASS +12mm AIR GAP+6mm REFLECTED GLASS AWING WINDOW | BJ43: 0
B44: Nos | C44: 1 | D44: 1 | E44: 1 | F44: 1 | G44: 1 | H44: 1 | I44: 1 | J44: 1 | K44: 1 | L44: 1 | M44: 1 | N44: 1 | O44: 1 | P44: 1 | Q44: 1 | R44: 1 | S44: 1 | T44: 1 | U44: 1 | V44: 1 | W44: 1 | X44: 1 | Y44: 1 | Z44: 1 | AA44: 1 | AB44: 1 | AC44: 1 | AD44: 1 | AE44: 1 | AF44: =SUM(C44:AE44) -> 29 | AG44: Nos
B45: Area(m2) | C45: =C42*C43*C44 -> 2.222 | D45: =D42*D43*D44 -> 2.156 | E45: =E42*E43*E44 -> 2.134 | F45: =F42*F43*F44 -> 1.078 | G45: =G42*G43*G44 -> 2.992 | H45: =H42*H43*H44 -> 1.122 | I45: =I42*I43*I44 -> 1.078 | J45: =J42*J43*J44 -> 1.98 | ... AE45: =AE42*AE43*AE44 -> 1.408 | AF45: =SUM(C45:AE45) -> 51.7 | AG45: m2 | BF45: CW20 | BG45: 1700 | BH45: 3200 | BI45: H.Q UPVC SECTION WITH 6mm CLEAR FLOAT GLASS +12mm AIR GAP+6mm REFLECTED GLASS AWING WINDOW | BJ45: 0
BF46: CW21 | BG46: 600 | BH46: 3200 | BI46: H.Q UPVC SECTION WITH 6mm CLEAR FLOAT GLASS +12mm AIR GAP+6mm REFLECTED GLASS AWING WINDOW | BJ46: 0
B47: FG1 | C47: FG | D47: FG | E47: FG | F47: FG | G47: FG | H47: FG | I47: FG | J47: FG | K47: FG | L47: FG | M47: FG | N47: FG | O47: FG | P47: FG | BF47: CW22 | BG47: 1300 | BH47: 3200 | BI47: H.Q UPVC SECTION WITH 6mm CLEAR FLOAT GLASS +12mm AIR GAP+6mm REFLECTED GLASS AWING WINDOW | BJ47: 0
B48: Location | C48: 1-PH | D48: 1-PH | E48: 1-PH | F48: 1-PH | G48: 1-PH | H48: 1-PH | I48: 1-PH | J48: 1-PH | K48: 1-PH | L48: 1-PH | M48: 1-PH | N48: 1-PH | O48: 1-PH | P48: 1-PH
B49: Width(m) | C49: 0.3 | D49: 0.2 | E49: 0.2 | F49: 0.25 | G49: 0.2 | H49: 0.4 | I49: 0.3 | J49: 0.35 | K49: 0.63 | L49: 0.3 | M49: 0.3 | N49: 0.2 | O49: 0.45 | P49: 0.7 | BF49: SCHEDULE OF WINDOW
B50: Height(m) | C50: 2.2 | D50: 2.2 | E50: 2.2 | F50: 2.2 | G50: 2.2 | H50: 2.2 | I50: 2.2 | J50: 2.2 | K50: 2.2 | L50: 2.2 | M50: 2.2 | N50: 2.2 | O50: 2.2 | P50: 2.2 | BF50: TYPE | BI50: GLASS 1 | BJ50: WIDTH | BK50: HEIGHT | BL50: SILL LEVEL
B51: Nos | C51: 6 | D51: 6 | E51: 6 | F51: 6 | G51: 6 | H51: 6 | I51: 6 | J51: 6 | K51: 6 | L51: 6 | M51: 6 | N51: 6 | O51: 6 | P51: 6 | AF51: =SUM(C51:AE51) -> 84 | AG51: Nos | BF51: W1 | BI51: H.Q UPVC SECTION WITH 6mm CLEAR FLOAT GLASS +12mm AIR GAP+6mm REFLECTED GLASS SLIDING WINDOW | BJ51: 2000 | BK51: 1400 | BL51: 800
B52: Area(m2) | C52: =C49*C50*C51 -> 3.96 | D52: =D49*D50*D51 -> 2.64 | E52: =E49*E50*E51 -> 2.64 | F52: =F49*F50*F51 -> 3.3 | G52: =G49*G50*G51 -> 2.64 | H52: =H49*H50*H51 -> 5.28 | I52: =I49*I50*I51 -> 3.96 | J52: =J49*J50*J51 -> 4.62 | ... P52: =P49*P50*P51 -> 9.24 | AF52: =SUM(C52:AE52) -> 63.096 | AG52: m2 | BF52: W2 | BI52: H.Q UPVC SECTION WITH 6mm CLEAR FLOAT GLASS +12mm AIR GAP+6mm REFLECTED GLASS SLIDING WINDOW | BJ52: 1000 | BK52: 1100 | BL52: 1100
BF53: W3 | BI53: H.Q UPVC SECTION WITH 6mm CLEAR FLOAT GLASS +12mm AIR GAP+6mm REFLECTED GLASS SLIDING WINDOW | BJ53: 800 | BK53: 1100 | BL53: 1100
BF54: W4 | BI54: H.Q UPVC SECTION WITH 6MM OBSCURED GLASS AWNING WINDOW WITH VENTILATOR OPENING | BJ54: 600 | BK54: 800 | BL54: 1400
BF55: W5 | BI55: H.Q UPVC SECTION WITH 6mm CLEAR FLOAT GLASS +12mm AIR GAP+6mm REFLECTED GLASS SLIDING WINDOW | BJ55: 1000 | BK55: FROM MIDLADING 80 CM HEIGHT
BF56: W6 | BI56: H.Q UPVC SECTION WITH 6mm CLEAR FLOAT GLASS +12mm AIR GAP+6mm REFLECTED GLASS SLIDING WINDOW | BJ56: AS PER PLAN AS PER ELEVATION | BL56: 1000
BF57: W7 | BI57: H.Q UPVC SECTION WITH 6mm CLEAR FLOAT GLASS +12mm AIR GAP+6mm REFLECTED GLASS SLIDING WINDOW | BJ57: 1000 | BK57: 1100 | BL57: 1100
BF58: W8 | BI58: H.Q UPVC SECTION WITH 6mm CLEAR FLOAT GLASS +12mm AIR GAP+6mm REFLECTED GLASS SLIDING WINDOW | BJ58: 600 | BK58: 1100 | BL58: 1100
BF59: FG1 | BI59: H.Q UPVC SECTION WITH 6mm CLEAR FLOAT GLASS +12mm FIXED GLASS | BJ59: AS PER PLAN AS PER ELEVATION | BL59: 0
BF61: SCHEDULE OF FINISHING
BF62: FLOORING
BF63: TYPE | BI63: DESCRIPTION
BF64: F1 | BI64: 20mm THICK ITALIAN MARBLE STEPS COLOR ,DESIGN & SHAPE TO BE APPROVED
BF65: F2 | BI65: 300X600X20mm ITALIAN MARBLE TILES COLOR ,DESIGN & SHAPE TO BE APPROVED
BF66: F3 | BI66: 400X400X20mm PORCELAIN TILES COLOR ,DESIGN & SHAPE TO BE APPROVED
BF67: F4 | BI67: 200X200X8mm FULLY VITRIFIED NON-SLIPPERY ITALIAN CERAMIC TILES COLOR ,DESIGN & SHAPE TO BE APPROVED
BF68: F5 | BI68: 300X300X8mm BEST QUALITY TERRAZZO TILES COLOR ,DESIGN & SHAPE TO BE APPROVED
BF69: SKIRTING
BF70: TYPE | BI70: DESCRIPTION
BF71: S1 | BI71: 600X100X20mm ITALIAN MARBLE SKIRTING WITH HALF ROUND TOP EDGE COLOR ,DESIGN & SHAPE TO BE APPROVED.
BF72: S2 | BI72: 400X100X20mm HEIGHT PORCELAIN SKIRTING WITH HALF ROUND TOP EDGE
BF73: S3 | BI73: 300X100X20mm HEIGHT TERRAZZO SKIRTING WITH HALF ROUND TOP EDGE
BF74: S4 | BI74: 20mm THICK GRAY NIGHT MARBLE STEPS COLOR ,DESIGN & SHAPE TO BE APPROVED
BF75: WALLS
BF76: TYPE | BI76: DESCRIPTION
BF77: W1 | BI77: 1 COAT PRIMER +2 COATS OF PUTTY + 3 COATS OF FENOMASTIC GOLD PAINT OR EQUIVALENT (COLOR SHALL BE FROM M.LN COLOR CHART AS APPROVED BY ENGINEER) ON 20mm THICK CEMENT SAND PLASTER
BF78: W2 | BI78: 200X300mm GLAZED ITALIAN CERAMIC TILES FOR WALLS UP TO CEILING LEVEL COLOR & DESIGN TO BE APPROVED
BF79: CEILING
BF80: TYPE | BI80: DESCRIPTION
BF81: C1 | BI81: 1 COAT PRIMER +2 COATS OF PUTTY + 3 COATS OF FENOMASTIC GOLD PAINT OR EQUIVALENT (COLOR SHALL BE FROM AS APPROVED BY ENGINEER)
BF82: C2 | BI82: DECORATIVE SUSPENDED FIRE RESISTANT 12mm THICK GYPSUM BOARD (DANOGIPS OR EQUIVALENT) CEILING FIXED WITH CONCEALED METAL SUSPENSION SYSTEM FIXED TO THE SOFFIT OF SLAB/BEAM OR TO WALL ALL BOARD JOINTS TO BE TAPED AND SKIMMED AND PAINTED AS STANDARD IN C2

Sheet Sheet1
